<?xml version="1.0" encoding="UTF-8"?>
<mei xmlns:xs="http://www.w3.org/2001/XMLSchema" xmlns="http://www.music-encoding.org/ns/mei" meiversion="4.0.0">
   <fileDesc>
      <titleStmt>
         <title>Variationen und Fuge B-Dur</title>
         <respStmt>
            <persName role="editor" xml:id="VP">Vasiliki Papadopoulou</persName>
            <persName role="editor" xml:id="KE">Kathrin Eich</persName>
            <persName role="editor" xml:id="CG">Clemens Gubsch</persName>
            <persName role="editor" xml:id="MJ">Monika Jaroš</persName>
            <persName role="editor" xml:id="MW">Magdalena Weber</persName>
         </respStmt>
      </titleStmt>
      <pubStmt/>
      <seriesStmt>
         <title>Werke mit Opus</title>
         <identifier type="file_collection">Werkdateien</identifier>
      </seriesStmt>
   </fileDesc>
   <encodingDesc>
      <projectDesc>
         <p>Alle Werke werden in einer Datei separaten Datei angelegt und verlinkt.</p>
      </projectDesc>
   </encodingDesc>
   <workList>
      <work n="24" xml:id="work_op._24">
         <identifier label="Opus-Nummer">op. 24</identifier>
         <title>Variationen und Fuge B-Dur</title>
         <composer>
            <persName auth="GND" auth.uri="https://d-nb.info/gnd/" codedval="118514253">Johannes Brahms</persName>
         </composer>
         <history>
            <eventList type="performances">
               <event>
                  <persName type="Pianist_in" corresp="../Brahms-Personenregister-ID/0031">Brahms, Johannes</persName>
                  <date isodate="1862-11-29">29.11.1862</date>
                  <geogName role="place">Wien</geogName>
                  <geogName role="venue">Musikvereinssaal</geogName>
                  <biblList>
                     <bibl sameas="recordid_669277 recordid_669278 " type="Rubrik_2 Rubrik_9">
                        <term label="Rubrik_2">Werkkritik</term>
                        <term label="Rubrik_9">Brahms als Pianist</term>
                        <genre>article</genre>
                        <genre>newspaper</genre>
                        <author/>
                        <title level="j">Vaterland</title>
                        <editor/>
                        <biblScope unit="vol">Jg. 3</biblScope>
                        <biblScope unit="issue">Nr. 279</biblScope>
                        <biblScope unit="page">S. [1]</biblScope>
                        <imprint>
                           <date isodate="1862-12-04">04.12.1862</date>
                           <pubPlace/>
                           <publisher/>
                        </imprint>
                        <annot>
                           <p label="Weitere_Informationen">(Konzert von J. Brahms, abends; vgl. <bibl type="bibl" target="#HofmannChronologie">Hofmann, Chronologie</bibl>, S. 72)</p>
                           <p label="Vollständiger_Nachweis">Vaterland, Jg. 3, Nr. 279, 04.12.1862, S. [1]</p>
                        </annot>
                        <ptr label="ANNO-ÖNB" target="http://anno.onb.ac.at/cgi-content/anno?aid=vtl&amp;datum=18621204&amp;seite=1&amp;zoom=33&amp;query=%22brahms%22&amp;ref=anno-search"/>
                        <relationList>
                           <relation rel="isRealizationOf" target="#work_op._24"/>
                        </relationList>
                        <relatedItem rel="host">
                           <bibl>
                              <title>vgl. Hofmann, Chronologie</title>
                              <biblScope/>
                           </bibl>
                        </relatedItem>
                     </bibl>
                     <bibl sameas="recordid_669298 recordid_669299 " type="Rubrik_9 Rubrik_2">
                        <term label="Rubrik_9">Brahms als Pianist</term>
                        <term label="Rubrik_2">Werkkritik</term>
                        <genre>article</genre>
                        <genre>newspaper</genre>
                        <author/>
                        <title level="j">Vaterland</title>
                        <editor/>
                        <biblScope unit="vol">Jg. 4</biblScope>
                        <biblScope unit="issue">Nr. 6</biblScope>
                        <biblScope unit="page">S. [2]</biblScope>
                        <imprint>
                           <date isodate="1863-01-09">09.01.1863</date>
                           <pubPlace/>
                           <publisher/>
                        </imprint>
                        <annot>
                           <p label="Weitere_Informationen">(Erwähnung im Rahmen einer Rezension des 2. Konzerts von J. Brahms in der Saison 1862/63; Datum und Werke gemäß <bibl type="bibl" target="#HofmannChronologie">Hofmann, Chronologie</bibl>, S. 72: op. 26, Anh. IIb, Nr. 1, op. 24 sowie Schumanns op. 17 und Begleitung der Sänger Adele Passy-Cornet und Emil Förchtgott)</p>
                           <p label="Vollständiger_Nachweis">Vaterland, Jg. 4, Nr. 6, 09.01.1863, S. [2]</p>
                        </annot>
                        <ptr label="ANNO-ÖNB" target="http://anno.onb.ac.at/cgi-content/anno?aid=vtl&amp;datum=18630109&amp;seite=2&amp;zoom=33&amp;query=%22brahms%22&amp;ref=anno-search"/>
                        <relationList>
                           <relation rel="isRealizationOf" target="#work_op._24"/>
                        </relationList>
                        <relatedItem rel="host">
                           <bibl>
                              <title>gemäß Hofmann, Chronologie</title>
                              <biblScope/>
                           </bibl>
                        </relatedItem>
                     </bibl>
                     <bibl sameas="recordid_666248 recordid_666254 " type="Rubrik_2 Rubrik_9">
                        <term label="Rubrik_2">Werkkritik</term>
                        <term label="Rubrik_9">Brahms als Pianist</term>
                        <genre>article</genre>
                        <genre>newspaper</genre>
                        <author/>
                        <title level="j">Presse</title>
                        <editor/>
                        <biblScope unit="vol">Jg. 15</biblScope>
                        <biblScope unit="issue">Nr. 331</biblScope>
                        <biblScope unit="page">S. [1] f.</biblScope>
                        <imprint>
                           <date isodate="1862-12-03">03.12.1862</date>
                           <pubPlace/>
                           <publisher/>
                        </imprint>
                        <annot>
                           <p label="Weitere_Informationen">(Mehrmalige Erwähnung im Rahmen einer Hanslick-Rezension des 1. Brahms-Konzerts in Wien; Datum gemäß <bibl type="bibl" target="#HofmannChronologie">Hofmann, Chronologie</bibl>, S. 72.</p>
                           <p label="Weitere_Informationen">(1. Brahms-Konzert in Wien; vgl. <bibl type="bibl" target="#HofmannChronologie">Hofmann, Chronologie</bibl>, S. 72)</p>
                           <p label="Vollständiger_Nachweis">Presse, Jg. 15, Nr. 331, 03.12.1862, S. [1] f.</p>
                        </annot>
                        <ptr label="ANNO-ÖNB" target="http://anno.onb.ac.at/cgi-content/anno?aid=apr&amp;datum=18621203&amp;seite=1&amp;zoom=33&amp;query=text%3A%22brahms%22&amp;ref=anno-search"/>
                        <relationList>
                           <relation rel="isRealizationOf" target="#work_op._24"/>
                        </relationList>
                        <relatedItem rel="host">
                           <bibl>
                              <title>gemäß Hofmann, Chronologie</title>
                              <title>vgl. Hofmann, Chronologie</title>
                              <biblScope/>
                           </bibl>
                        </relatedItem>
                     </bibl>
                  </biblList>
               </event>
               <event>
                  <persName type="Pianist_in" corresp="../Brahms-Personenregister-ID/0003">Albert, Eugen d’</persName>
                  <date isodate="1885-01-22">22.01.1885</date>
                  <geogName role="place">Wien</geogName>
                  <geogName role="venue">Saal Bösendorfer</geogName>
                  <biblList>
                     <bibl sameas="recordid_669629 " type="Rubrik_18">
                        <term label="Rubrik_18">Vorankündigung</term>
                        <genre>article</genre>
                        <genre>newspaper</genre>
                        <author/>
                        <title level="j">Vaterland</title>
                        <editor/>
                        <biblScope unit="vol">Jg. 26</biblScope>
                        <biblScope unit="issue">Nr. 18</biblScope>
                        <biblScope unit="page">S. 8</biblScope>
                        <imprint>
                           <date isodate="1885-01-18">18.01.1885</date>
                           <pubPlace/>
                           <publisher/>
                        </imprint>
                        <annot>
                           <p label="Weitere_Informationen">(Zweites Konzert von Eugen d'Albert)</p>
                           <p label="Vollständiger_Nachweis">Vaterland, Jg. 26, Nr. 18, 18.01.1885, S. 8</p>
                        </annot>
                        <ptr label="ANNO-ÖNB" target="http://anno.onb.ac.at/cgi-content/anno?aid=vtl&amp;datum=18850118&amp;seite=8&amp;zoom=33&amp;query=%22brahms%22&amp;ref=anno-search"/>
                        <relationList>
                           <relation rel="isRealizationOf" target="#work_op._24"/>
                        </relationList>
                        <relatedItem rel="host">
                           <bibl>
                              <biblScope/>
                           </bibl>
                        </relatedItem>
                     </bibl>
                     <bibl sameas="recordid_667549 " type="Rubrik_18">
                        <term label="Rubrik_18">Vorankündigung</term>
                        <genre>article</genre>
                        <genre>newspaper</genre>
                        <author/>
                        <title level="j">Presse</title>
                        <title level="j">Local-Anzeiger</title>
                        <editor/>
                        <biblScope unit="vol">Jg. 38</biblScope>
                        <biblScope unit="issue">Nr. 21</biblScope>
                        <biblScope unit="page">S. 15</biblScope>
                        <imprint>
                           <date isodate="1885-01-21">21.01.1885</date>
                           <pubPlace/>
                           <publisher/>
                        </imprint>
                        <annot>
                           <p label="Weitere_Informationen">(Zweites Konzert von Eugen d'Albert)</p>
                           <p label="Vollständiger_Nachweis">Presse, Local-Anzeiger, Jg. 38, Nr. 21, 21.01.1885, S. 15</p>
                        </annot>
                        <ptr label="ANNO-ÖNB" target="http://anno.onb.ac.at/cgi-content/anno?aid=apr&amp;datum=18850121&amp;seite=9&amp;zoom=33&amp;query=%22brahms%22&amp;ref=anno-search"/>
                        <relationList>
                           <relation rel="isRealizationOf" target="#work_op._24"/>
                        </relationList>
                        <relatedItem rel="host">
                           <bibl>
                              <biblScope/>
                           </bibl>
                        </relatedItem>
                     </bibl>
                     <bibl sameas="recordid_667558 " type="Rubrik_2">
                        <term label="Rubrik_2">Werkkritik</term>
                        <genre>article</genre>
                        <genre>newspaper</genre>
                        <author/>
                        <title level="j">Presse</title>
                        <editor/>
                        <biblScope unit="vol">Jg. 38</biblScope>
                        <biblScope unit="issue">Nr. 28</biblScope>
                        <biblScope unit="page">S. 3</biblScope>
                        <imprint>
                           <date isodate="1885-01-28">28.01.1885</date>
                           <pubPlace/>
                           <publisher/>
                        </imprint>
                        <annot>
                           <p label="Weitere_Informationen">(2. Konzert von Eugen d'Albert; Datum gemäß Die Presse, Local-Anzeiger, 21.01.1885, S. 15)</p>
                           <p label="Vollständiger_Nachweis">Presse, Jg. 38, Nr. 28, 28.01.1885, S. 3</p>
                        </annot>
                        <ptr label="ANNO-ÖNB" target="http://anno.onb.ac.at/cgi-content/anno?aid=apr&amp;datum=18850128&amp;seite=3&amp;zoom=33&amp;query=%22brahms%22&amp;ref=anno-search"/>
                        <relationList>
                           <relation rel="isRealizationOf" target="#work_op._24"/>
                        </relationList>
                        <relatedItem rel="host">
                           <bibl>
                              <biblScope/>
                           </bibl>
                        </relatedItem>
                     </bibl>
                  </biblList>
               </event>
               <event>
                  <date isodate="1897-01-18">18.01.1897</date>
                  <geogName role="place">Wien</geogName>
                  <geogName role="venue">Saal Bösendorfer</geogName>
                  <persName type="Pianist_in" corresp="../Brahms-Personenregister-ID/0226">Sauer, Emil</persName>
                  <biblList>
                     <bibl sameas="recordid_670311 " type="Rubrik_18">
                        <term label="Rubrik_18">Vorankündigung</term>
                        <genre>article</genre>
                        <genre>newspaper</genre>
                        <author/>
                        <title level="j">Vaterland</title>
                        <title level="j">Morgenblatt</title>
                        <editor/>
                        <biblScope unit="vol">Jg. 38</biblScope>
                        <biblScope unit="issue">Nr. 12</biblScope>
                        <biblScope unit="page">S. 7</biblScope>
                        <imprint>
                           <date isodate="1897-01-12">12.01.1897</date>
                           <pubPlace/>
                           <publisher/>
                        </imprint>
                        <annot>
                           <p label="Weitere_Informationen">(Klavierabend von Emil Sauer)</p>
                           <p label="Vollständiger_Nachweis">Vaterland, Morgenblatt, Jg. 38, Nr. 12, 12.01.1897, S. 7</p>
                        </annot>
                        <ptr label="ANNO-ÖNB" target="http://anno.onb.ac.at/cgi-content/anno?aid=vtl&amp;datum=18970112&amp;seite=7&amp;zoom=33&amp;query=%22brahms%22&amp;ref=anno-search"/>
                        <relationList>
                           <relation rel="isRealizationOf" target="#work_op._24"/>
                        </relationList>
                        <relatedItem rel="host">
                           <bibl>
                              <biblScope/>
                           </bibl>
                        </relatedItem>
                     </bibl>
                  </biblList>
               </event>
               <event>
                  <date isodate="1897-02-01">01.02.1897</date>
                  <geogName role="place">Wien</geogName>
                  <geogName role="venue">Saal Bösendorfer</geogName>
                  <persName type="Pianist_in" corresp="../Brahms-Personenregister-ID/0003">d'Albert, Eugen</persName>
                  <biblList>
                     <bibl sameas="recordid_670327 " type="Rubrik_18">
                        <term label="Rubrik_18">Vorankündigung</term>
                        <genre>article</genre>
                        <genre>newspaper</genre>
                        <author/>
                        <title level="j">Vaterland</title>
                        <title level="j">Morgenblatt</title>
                        <editor/>
                        <biblScope unit="vol">Jg. 38</biblScope>
                        <biblScope unit="issue">Nr. 31</biblScope>
                        <biblScope unit="page">S. 7</biblScope>
                        <imprint>
                           <date isodate="1897-01-31">31.01.1897</date>
                           <pubPlace/>
                           <publisher/>
                        </imprint>
                        <annot>
                           <p label="Weitere_Informationen">(Einziges Konzert von Eugen d'Albert, 19.30 Uhr)</p>
                           <p label="Vollständiger_Nachweis">Vaterland, Morgenblatt, Jg. 38, Nr. 31, 31.01.1897, S. 7</p>
                        </annot>
                        <ptr label="ANNO-ÖNB" target="http://anno.onb.ac.at/cgi-content/anno?aid=vtl&amp;datum=18970131&amp;seite=7&amp;zoom=33&amp;query=%22brahms%22&amp;ref=anno-search"/>
                        <relationList>
                           <relation rel="isRealizationOf" target="#work_op._24"/>
                        </relationList>
                        <relatedItem rel="host">
                           <bibl>
                              <biblScope/>
                           </bibl>
                        </relatedItem>
                     </bibl>
                  </biblList>
               </event>
               <event>
                  <persName type="Pianist_in" corresp="../Brahms-Personenregister-ID/0012">Basch-Mahler, Fanny</persName>
                  <date isodate="1898-02-05">05.02.1898</date>
                  <geogName role="place">Wien</geogName>
                  <geogName role="venue">Saal Bösendorfer</geogName>
                  <biblList>
                     <bibl sameas="recordid_670474 " type="Rubrik_18">
                        <term label="Rubrik_18">Vorankündigung</term>
                        <genre>article</genre>
                        <genre>newspaper</genre>
                        <author/>
                        <title level="j">Vaterland</title>
                        <title level="j">Morgenblatt</title>
                        <editor/>
                        <biblScope unit="vol">Jg. 39</biblScope>
                        <biblScope unit="issue">Beiblatt zu Nr. 15</biblScope>
                        <biblScope unit="page">S. I</biblScope>
                        <imprint>
                           <date isodate="1898-01-16">16.01.1898</date>
                           <pubPlace/>
                           <publisher/>
                        </imprint>
                        <annot>
                           <p label="Weitere_Informationen">(Brahms-Abend der Damen Neuda-Bernstein und Basch-Mahler; Werke: op. 3, Nr. 1, op. 71, Nr. 3, op. 69, Nr. 9, op. 91, Nr. 1 und 2, op. 33, Nr. 6 und 9 sowie op. 120 und op. 24)</p>
                           <p label="Vollständiger_Nachweis">Vaterland, Morgenblatt, Jg. 39, Beiblatt zu Nr. 15, 16.01.1898, S. I</p>
                        </annot>
                        <ptr label="ANNO-ÖNB" target="http://anno.onb.ac.at/cgi-content/anno?aid=vtl&amp;datum=18980116&amp;seite=9&amp;zoom=33&amp;query=%22brahms%22&amp;ref=anno-search"/>
                        <relationList>
                           <relation rel="isRealizationOf" target="#work_op._24"/>
                        </relationList>
                        <relatedItem rel="host">
                           <bibl>
                              <biblScope/>
                           </bibl>
                        </relatedItem>
                     </bibl>
                  </biblList>
               </event>
               <event>
                  <date isodate="1898-12-06">06.12.1898</date>
                  <geogName role="place">Wien</geogName>
                  <geogName role="venue">Saal Bösendorfer</geogName>
                  <persName type="Pianist_in" corresp="../Brahms-Personenregister-ID/0042">Busoni, Ferruccio</persName>
                  <biblList>
                     <bibl sameas="recordid_670550 " type="Rubrik_18">
                        <term label="Rubrik_18">Vorankündigung</term>
                        <genre>article</genre>
                        <genre>newspaper</genre>
                        <author/>
                        <title level="j">Vaterland</title>
                        <title level="j">Morgenblatt</title>
                        <editor/>
                        <biblScope unit="vol">Jg. 39</biblScope>
                        <biblScope unit="issue">Nr. 327</biblScope>
                        <biblScope unit="page">S. 9</biblScope>
                        <imprint>
                           <date isodate="1898-11-27">27.11.1898</date>
                           <pubPlace/>
                           <publisher/>
                        </imprint>
                        <annot>
                           <p label="Weitere_Informationen">(Konzert von Ferruccio Busoni)</p>
                           <p label="Vollständiger_Nachweis">Vaterland, Morgenblatt, Jg. 39, Nr. 327, 27.11.1898, S. 9</p>
                        </annot>
                        <ptr label="ANNO-ÖNB" target="http://anno.onb.ac.at/cgi-content/anno?aid=vtl&amp;datum=18981127&amp;seite=9&amp;zoom=33&amp;query=%22brahms%22&amp;ref=anno-search"/>
                        <relationList>
                           <relation rel="isRealizationOf" target="#work_op._24"/>
                        </relationList>
                        <relatedItem rel="host">
                           <bibl>
                              <biblScope/>
                           </bibl>
                        </relatedItem>
                     </bibl>
                  </biblList>
               </event>
               <event>
                  <date isodate="1900-03-14">14.03.1900</date>
                  <geogName role="place">Wien</geogName>
                  <geogName role="venue">Saal Bösendorfer</geogName>
                  <persName type="Pianist_in" corresp="#">Galston, Gottfried</persName>
                  <biblList>
                     <bibl sameas="recordid_670684 " type="Rubrik_18">
                        <term label="Rubrik_18">Vorankündigung</term>
                        <genre>article</genre>
                        <genre>newspaper</genre>
                        <author/>
                        <title level="j">Vaterland</title>
                        <title level="j">Morgenblatt</title>
                        <editor/>
                        <biblScope unit="vol">Jg. 41</biblScope>
                        <biblScope unit="issue">1. Beiblatt zu Nr. 68</biblScope>
                        <biblScope unit="page">S. IV</biblScope>
                        <imprint>
                           <date isodate="1900-03-11">11.03.1900</date>
                           <pubPlace/>
                           <publisher/>
                        </imprint>
                        <annot>
                           <p label="Weitere_Informationen">(Konzert des Pianisten Gottfried Galston)</p>
                           <p label="Vollständiger_Nachweis">Vaterland, Morgenblatt, Jg. 41, 1. Beiblatt zu Nr. 68, 11.03.1900, S. IV</p>
                        </annot>
                        <ptr label="ANNO-ÖNB" target="http://anno.onb.ac.at/cgi-content/anno?aid=vtl&amp;datum=19000311&amp;seite=10&amp;zoom=33&amp;query=%22brahms%22&amp;ref=anno-search"/>
                        <relationList>
                           <relation rel="isRealizationOf" target="#work_op._24"/>
                        </relationList>
                        <relatedItem rel="host">
                           <bibl>
                              <biblScope/>
                           </bibl>
                        </relatedItem>
                     </bibl>
                  </biblList>
               </event>
               <event>
                  <date isodate="1901-08-20">20.08.1901</date>
                  <geogName role="place">Regensburg</geogName>
                  <geogName role="venue">Großer Saal des Neuen Hauses</geogName>
                  <persName type="Pianist_in" corresp="#">Tovey, Donald Francis</persName>
                  <biblList>
                     <bibl sameas="recordid_670782 " type="Rubrik_3">
                        <term label="Rubrik_3">Vorankündigung</term>
                        <genre>article</genre>
                        <genre>newspaper</genre>
                        <author/>
                        <title level="j">Vaterland</title>
                        <title level="j">Abendblatt</title>
                        <editor/>
                        <biblScope unit="vol">Jg. 42</biblScope>
                        <biblScope unit="issue">Nr. 229</biblScope>
                        <biblScope unit="page">S. 2</biblScope>
                        <imprint>
                           <date isodate="1901-08-22">22.08.1901</date>
                           <pubPlace/>
                           <publisher/>
                        </imprint>
                        <annot>
                           <p label="Weitere_Informationen">(Konzert des Klaviervirtuosen Mr. Tovey zum Besten der neuerbauten St. Cäcilienkirche im Rahmen der 16. Generalversammlung des Allgemeinen deutschen Cäcilien-Vereins; u.a. "Variationen und Fuge von Händel und Brahms")</p>
                           <p label="Vollständiger_Nachweis">Vaterland, Abendblatt, Jg. 42, Nr. 229, 22.08.1901, S. 2</p>
                        </annot>
                        <ptr label="ANNO-ÖNB" target="http://anno.onb.ac.at/cgi-content/anno?aid=vtl&amp;datum=19010822&amp;seite=10&amp;zoom=33&amp;query=%22brahms%22&amp;ref=anno-search"/>
                        <relationList>
                           <relation rel="isRealizationOf" target="#work_op._24"/>
                        </relationList>
                        <relatedItem rel="host">
                           <bibl>
                              <biblScope/>
                           </bibl>
                        </relatedItem>
                     </bibl>
                  </biblList>
               </event>
               <event>
                  <date isodate="1901-12-11">11.12.1901</date>
                  <geogName role="place">Wien</geogName>
                  <persName type="Pianist_in" corresp="../Brahms-Personenregister-ID/0226">Sauer, Emil</persName>
                  <biblList>
                     <bibl sameas="recordid_670796 " type="Rubrik_2">
                        <term label="Rubrik_2">Werkkritik</term>
                        <genre>article</genre>
                        <genre>newspaper</genre>
                        <author>K.</author>
                        <title level="j">Vaterland</title>
                        <title level="j">Morgenblatt</title>
                        <editor/>
                        <biblScope unit="vol">Jg. 42</biblScope>
                        <biblScope unit="issue">2. Beiblatt zu Nr. 344</biblScope>
                        <biblScope unit="page">S. I</biblScope>
                        <imprint>
                           <date isodate="1901-12-15">15.12.1901</date>
                           <pubPlace/>
                           <publisher/>
                        </imprint>
                        <annot>
                           <p label="Weitere_Informationen">(Konzert von Emil Sauer; Datum gemäß NWT, 23.11.1901, S. 10; Verfasser: K.)</p>
                           <p label="Vollständiger_Nachweis">Vaterland, Morgenblatt, Jg. 42, 2. Beiblatt zu Nr. 344, 15.12.1901, S. I</p>
                        </annot>
                        <ptr label="ANNO-ÖNB" target="http://anno.onb.ac.at/cgi-content/anno?aid=vtl&amp;datum=19011215&amp;seite=17&amp;zoom=33&amp;query=%22brahms%22&amp;ref=anno-search"/>
                        <relationList>
                           <relation rel="isRealizationOf" target="#work_op._24"/>
                        </relationList>
                        <relatedItem rel="host">
                           <bibl>
                              <biblScope/>
                           </bibl>
                        </relatedItem>
                     </bibl>
                  </biblList>
               </event>
               <event>
                  <persName type="Pianist_in" corresp="../Brahms-Personenregister-ID/0031">Brahms, Johannes</persName>
                  <date isodate="1867-04-07">07.04.1867</date>
                  <geogName role="place">Wien</geogName>
                  <geogName role="venue">Musikvereinssaal</geogName>
                  <biblList>
                     <bibl sameas="recordid_666360 recordid_666361 " type="Rubrik_2 Rubrik_9">
                        <term label="Rubrik_2">Werkkritik</term>
                        <term label="Rubrik_9">Brahms als Pianist</term>
                        <genre>article</genre>
                        <genre>newspaper</genre>
                        <author/>
                        <title level="j">Presse</title>
                        <editor/>
                        <biblScope unit="vol">Jg. 20</biblScope>
                        <biblScope unit="issue">Nr. 101</biblScope>
                        <biblScope unit="page">S. [1]</biblScope>
                        <imprint>
                           <date isodate="1867-04-13">13.04.1867</date>
                           <pubPlace/>
                           <publisher/>
                        </imprint>
                        <annot>
                           <p label="Weitere_Informationen">(2. Konzert von Johannes Brahms; vgl. <bibl type="bibl" target="#HofmannChronologie">Hofmann, Chronologie</bibl>, S. 94 f.; weitere Werke: Schumanns op. 17, Bachs Toccata F-Dur, Schuberts Oktett [Anh. IIb, Nr. 4], 2 Capricen von Domenico Scarlatti, 2 "noch ungedruckte Stücke von Schubert", Schumanns Toccata op. 7, Beethovens Klaviersonate op. 109 sowie sein op. 64, Nr. 1 und op. 31, Nr. 1.)</p>
                           <p label="Vollständiger_Nachweis">Presse, Jg. 20, Nr. 101, 13.04.1867, S. [1]</p>
                        </annot>
                        <ptr label="ANNO-ÖNB" target="http://anno.onb.ac.at/cgi-content/anno?aid=apr&amp;datum=18670413&amp;seite=1&amp;zoom=33&amp;query=%22brahms%22&amp;ref=anno-search"/>
                        <relationList>
                           <relation rel="isRealizationOf" target="#work_op._24"/>
                        </relationList>
                        <relatedItem rel="host">
                           <bibl>
                              <title>vgl. Hofmann, Chronologie</title>
                              <biblScope/>
                           </bibl>
                        </relatedItem>
                     </bibl>
                  </biblList>
               </event>
               <event>
                  <persName type="Pianist_in" corresp="../Brahms-Personenregister-ID/0044">Bülow, Hans von</persName>
                  <date isodate="1872-11-02">02.11.1872</date>
                  <geogName role="place">Wien</geogName>
                  <biblList>
                     <bibl sameas="recordid_666506 " type="Rubrik_2">
                        <term label="Rubrik_2">Werkkritik</term>
                        <genre>article</genre>
                        <genre>newspaper</genre>
                        <author/>
                        <title level="j">Presse</title>
                        <title level="j">Local-Anzeiger</title>
                        <editor/>
                        <biblScope unit="vol">Jg. 25</biblScope>
                        <biblScope unit="issue">Nr. 309</biblScope>
                        <biblScope unit="page">S. [1]</biblScope>
                        <imprint>
                           <date isodate="1872-11-09">09.11.1872</date>
                           <pubPlace/>
                           <publisher/>
                        </imprint>
                        <annot>
                           <p label="Weitere_Informationen">(1. Konzert von Hans v. Bülow; u.a. J. Brahms: op. 24, "zwei Balladen aus op. 10" sowie op. 4)</p>
                           <p label="Vollständiger_Nachweis">Presse, Local-Anzeiger, Jg. 25, Nr. 309, 09.11.1872, S. [1]</p>
                        </annot>
                        <ptr label="ANNO-ÖNB" target="http://anno.onb.ac.at/cgi-content/anno?aid=apr&amp;datum=18721109&amp;seite=9&amp;zoom=33&amp;query=%22brahms%22&amp;ref=anno-search"/>
                        <relationList>
                           <relation rel="isRealizationOf" target="#work_op._24"/>
                        </relationList>
                        <relatedItem rel="host">
                           <bibl>
                              <biblScope/>
                           </bibl>
                        </relatedItem>
                     </bibl>
                     <bibl sameas="recordid_666520 " type="Rubrik_2">
                        <term label="Rubrik_2">Werkkritik</term>
                        <genre>article</genre>
                        <genre>newspaper</genre>
                        <author/>
                        <title level="j">Presse</title>
                        <editor/>
                        <biblScope unit="vol">Jg. 25</biblScope>
                        <biblScope unit="issue">Nr. 323</biblScope>
                        <biblScope unit="page">S. [1]</biblScope>
                        <imprint>
                           <date isodate="1872-11-23">23.11.1872</date>
                           <pubPlace/>
                           <publisher/>
                        </imprint>
                        <annot>
                           <p label="Weitere_Informationen">(Erwähnung der "prachtvollen Variationen von Brahms über ein englisches Thema". Da diese Anmerkung im Rahmen einer Rezension über die Bülow'schen Konzerte in Wien gemacht wurde, dürfte das angesprochene Brahms-Werk op. 24 sein, das Bülow bei seinem 1. Konzert gespielt hat. Datum und Werk gemäß Die Presse, Local-Anzeiger, 09.11.1872, S. [1])</p>
                           <p label="Vollständiger_Nachweis">Presse, Jg. 25, Nr. 323, 23.11.1872, S. [1]</p>
                        </annot>
                        <ptr label="ANNO-ÖNB" target="http://anno.onb.ac.at/cgi-content/anno?aid=apr&amp;datum=18721123&amp;seite=1&amp;zoom=33&amp;query=%22brahms%22&amp;ref=anno-search"/>
                        <relationList>
                           <relation rel="isRealizationOf" target="#work_op._24"/>
                        </relationList>
                        <relatedItem rel="host">
                           <bibl>
                              <biblScope/>
                           </bibl>
                        </relatedItem>
                     </bibl>
                  </biblList>
               </event>
               <event>
                  <date isodate="1873-04-03">03.04.1873</date>
                  <geogName role="place">Wien</geogName>
                  <persName type="Pianist_in" corresp="../Brahms-Personenregister-ID/0289">Smietanski, Emil</persName>
                  <biblList>
                     <bibl sameas="recordid_666579 " type="Rubrik_2">
                        <term label="Rubrik_2">Werkkritik</term>
                        <genre>article</genre>
                        <genre>newspaper</genre>
                        <author/>
                        <title level="j">Presse</title>
                        <editor/>
                        <biblScope unit="vol">Jg. 26</biblScope>
                        <biblScope unit="issue">Nr. 101</biblScope>
                        <biblScope unit="page">S. [1]</biblScope>
                        <imprint>
                           <date isodate="1873-04-12">12.04.1873</date>
                           <pubPlace/>
                           <publisher/>
                        </imprint>
                        <annot>
                           <p label="Weitere_Informationen">(Konzert des Pianisten Smietanski)</p>
                           <p label="Vollständiger_Nachweis">Presse, Jg. 26, Nr. 101, 12.04.1873, S. [1]</p>
                        </annot>
                        <ptr label="ANNO-ÖNB" target="http://anno.onb.ac.at/cgi-content/anno?aid=apr&amp;datum=18730412&amp;seite=1&amp;zoom=33&amp;query=%22brahms%22&amp;ref=anno-search"/>
                        <relationList>
                           <relation rel="isRealizationOf" target="#work_op._24"/>
                        </relationList>
                        <relatedItem rel="host">
                           <bibl>
                              <biblScope/>
                           </bibl>
                        </relatedItem>
                     </bibl>
                  </biblList>
               </event>
               <event>
                  <date isodate="1874-02-02">02.02.1874</date>
                  <geogName role="place">Wien</geogName>
                  <geogName role="venue">Kleiner Musikvereinssaal</geogName>
                  <persName type="Pianist_in" corresp="../Brahms-Personenregister-ID/0038">Brüll, Ignaz</persName>
                  <biblList>
                     <bibl sameas="recordid_666677 " type="Rubrik_3">
                        <term label="Rubrik_3">Vorankündigung</term>
                        <genre>article</genre>
                        <genre>newspaper</genre>
                        <author/>
                        <title level="j">Presse</title>
                        <editor/>
                        <biblScope unit="vol">Jg. 27</biblScope>
                        <biblScope unit="issue">Nr. 37</biblScope>
                        <biblScope unit="page">S. 2</biblScope>
                        <imprint>
                           <date isodate="1874-02-07">07.02.1874</date>
                           <pubPlace/>
                           <publisher/>
                        </imprint>
                        <annot>
                           <p label="Weitere_Informationen">(Konzert von Ignaz Brüll)</p>
                           <p label="Vollständiger_Nachweis">Presse, Jg. 27, Nr. 37, 07.02.1874, S. 2</p>
                        </annot>
                        <ptr label="ANNO-ÖNB" target="http://anno.onb.ac.at/cgi-content/anno?aid=apr&amp;datum=18740207&amp;seite=2&amp;zoom=33&amp;query=%22brahms%22&amp;ref=anno-search"/>
                        <relationList>
                           <relation rel="isRealizationOf" target="#work_op._24"/>
                        </relationList>
                        <relatedItem rel="host">
                           <bibl>
                              <biblScope/>
                           </bibl>
                        </relatedItem>
                     </bibl>
                  </biblList>
               </event>
               <event>
                  <date isodate="1876-12-20">20.12.1876</date>
                  <geogName role="place">Wien</geogName>
                  <geogName role="venue">Salon Bösendorfer</geogName>
                  <persName type="Pianist_in" corresp="../Brahms-Personenregister-ID/0225">Saphier, Josef</persName>
                  <biblList>
                     <bibl sameas="recordid_666931 " type="Rubrik_18">
                        <term label="Rubrik_18">Vorankündigung</term>
                        <genre>article</genre>
                        <genre>newspaper</genre>
                        <author/>
                        <title level="j">Presse</title>
                        <title level="j">Local-Anzeiger</title>
                        <editor/>
                        <biblScope unit="vol">Jg. 29</biblScope>
                        <biblScope unit="issue">Nr. 348</biblScope>
                        <biblScope unit="page">S. 8</biblScope>
                        <imprint>
                           <date isodate="1876-12-17">17.12.1876</date>
                           <pubPlace/>
                           <publisher/>
                        </imprint>
                        <annot>
                           <p label="Weitere_Informationen">(Konzert des Pianisten Josef Saphier, 19.30 Uhr)</p>
                           <p label="Vollständiger_Nachweis">Presse, Local-Anzeiger, Jg. 29, Nr. 348, 17.12.1876, S. 8</p>
                        </annot>
                        <ptr label="ANNO-ÖNB" target="http://anno.onb.ac.at/cgi-content/anno?aid=apr&amp;datum=18761217&amp;seite=8&amp;zoom=33&amp;query=%22brahms%22&amp;ref=anno-search"/>
                        <relationList>
                           <relation rel="isRealizationOf" target="#work_op._24"/>
                        </relationList>
                        <relatedItem rel="host">
                           <bibl>
                              <biblScope/>
                           </bibl>
                        </relatedItem>
                     </bibl>
                  </biblList>
               </event>
               <event>
                  <date isodate="1882-11-08">08.11.1882</date>
                  <geogName role="place">Wien</geogName>
                  <geogName role="venue">Kleiner Musikvereinssaal</geogName>
                  <persName type="Pianist_in" corresp="../Brahms-Personenregister-ID/0009">Barth, Heinrich</persName>
                  <biblList>
                     <bibl sameas="recordid_667314 " type="Rubrik_3">
                        <term label="Rubrik_3">Vorankündigung</term>
                        <genre>article</genre>
                        <genre>newspaper</genre>
                        <author/>
                        <title level="j">Presse</title>
                        <title level="j">Local-Anzeiger</title>
                        <editor/>
                        <biblScope unit="vol">Jg. 35</biblScope>
                        <biblScope unit="issue">Nr. 311</biblScope>
                        <biblScope unit="page">S. 11</biblScope>
                        <imprint>
                           <date isodate="1882-11-10">10.11.1882</date>
                           <pubPlace/>
                           <publisher/>
                        </imprint>
                        <annot>
                           <p label="Weitere_Informationen">(Konzert des königl. preußischen Professors und Hofpianisten Heinrich Barth, abends)</p>
                           <p label="Vollständiger_Nachweis">Presse, Local-Anzeiger, Jg. 35, Nr. 311, 10.11.1882, S. 11</p>
                        </annot>
                        <ptr label="ANNO-ÖNB" target="http://anno.onb.ac.at/cgi-content/anno?aid=apr&amp;datum=18821110&amp;seite=11&amp;zoom=33&amp;query=text%253A%2522brahms%2522&amp;ref=anno-search"/>
                        <relationList>
                           <relation rel="isRealizationOf" target="#work_op._24"/>
                        </relationList>
                        <relatedItem rel="host">
                           <bibl>
                              <biblScope/>
                           </bibl>
                        </relatedItem>
                     </bibl>
                  </biblList>
               </event>
               <event>
                  <persName type="Pianist_in" corresp="../Brahms-Personenregister-ID/0031">Brahms, Johannes</persName>
                  <date isodate="1864-02-06">06.02.1864</date>
                  <geogName role="place">Wien</geogName>
                  <biblList>
                     <bibl sameas="recordid_667347 " type="Rubrik_3">
                        <term label="Rubrik_3">Vorankündigung</term>
                        <genre>article</genre>
                        <genre>newspaper</genre>
                        <author/>
                        <title level="j">Presse</title>
                        <title level="j">Local-Anzeiger</title>
                        <editor/>
                        <biblScope unit="vol">Jg. 36</biblScope>
                        <biblScope unit="issue">Nr. 51</biblScope>
                        <biblScope unit="page">S. 11</biblScope>
                        <imprint>
                           <date isodate="1883-02-22">22.02.1883</date>
                           <pubPlace/>
                           <publisher/>
                        </imprint>
                        <annot>
                           <p label="Weitere_Informationen">(Hausmusik bei Richard Wagner; Erwähnung im Rahmen einer Meldung aus Berlin vom 20.02.1883, dass die Kranzspende von J. Brahms zur Leichenfeier von Richard Wagner in der Berliner Hochschule für Musik "große Bewegung hervorgerufen" habe. Datum gemäß <bibl type="bibl" target="#HofmannChronologie">Hofmann, Chronologie</bibl>, S. 79)</p>
                           <p label="Vollständiger_Nachweis">Presse, Local-Anzeiger, Jg. 36, Nr. 51, 22.02.1883, S. 11</p>
                        </annot>
                        <ptr label="ANNO-ÖNB" target="http://anno.onb.ac.at/cgi-content/anno?aid=apr&amp;datum=18830222&amp;seite=11&amp;zoom=33&amp;query=text%253A%2522brahms%2522&amp;ref=anno-search"/>
                        <relationList>
                           <relation rel="isRealizationOf" target="#work_op._24"/>
                        </relationList>
                        <relatedItem rel="host">
                           <bibl>
                              <title>gemäß Hofmann, Chronologie</title>
                              <biblScope/>
                           </bibl>
                        </relatedItem>
                     </bibl>
                  </biblList>
               </event>
               <event>
                  <date isodate="1886-02-21">21.02.1886</date>
                  <geogName role="place">Wien</geogName>
                  <geogName role="venue">Saal Bösendorfer</geogName>
                  <persName type="Pianist_in" corresp="../Brahms-Personenregister-ID/0147">Lamond, Frédéric</persName>
                  <biblList>
                     <bibl sameas="recordid_667672 " type="Rubrik_2">
                        <term label="Rubrik_2">Werkkritik</term>
                        <genre>article</genre>
                        <genre>newspaper</genre>
                        <author/>
                        <title level="j">Presse</title>
                        <editor/>
                        <biblScope unit="vol">Jg. 39</biblScope>
                        <biblScope unit="issue">Nr. 56</biblScope>
                        <biblScope unit="page">S. 2</biblScope>
                        <imprint>
                           <date isodate="1886-02-25">25.02.1886</date>
                           <pubPlace/>
                           <publisher/>
                        </imprint>
                        <annot>
                           <p label="Weitere_Informationen">(Brahms-Abend des Pianisten Frédéric Lamond; Werke: "F-moll-Sonate, eine Rhapsodie, zwei Balladen, das Es-moll-Scherzo, zwei Stücke aus op. 76, sowie die sämmtlichen Händel- und Paganini-Variationen"; Datum gemäß Die Presse, 18.02.1886, S. 16)</p>
                           <p label="Vollständiger_Nachweis">Presse, Jg. 39, Nr. 56, 25.02.1886, S. 2</p>
                        </annot>
                        <ptr label="ANNO-ÖNB" target="http://anno.onb.ac.at/cgi-content/anno?aid=apr&amp;datum=18860225&amp;seite=2&amp;zoom=33&amp;query=%22brahms%22&amp;ref=anno-search"/>
                        <relationList>
                           <relation rel="isRealizationOf" target="#work_op._24"/>
                        </relationList>
                        <relatedItem rel="host">
                           <bibl>
                              <biblScope/>
                           </bibl>
                        </relatedItem>
                     </bibl>
                  </biblList>
               </event>
               <event>
                  <date isodate="1887-12-12">12.12.1887</date>
                  <geogName role="place">Wien</geogName>
                  <persName type="Pianist_in" corresp="../Brahms-Personenregister-ID/0480">Reich, Ida</persName>
                  <biblList>
                     <bibl sameas="recordid_667895 " type="Rubrik_2">
                        <term label="Rubrik_2">Werkkritik</term>
                        <genre>article</genre>
                        <genre>newspaper</genre>
                        <author/>
                        <title level="j">Presse</title>
                        <editor/>
                        <biblScope unit="vol">Jg. 40</biblScope>
                        <biblScope unit="issue">Nr. 344</biblScope>
                        <biblScope unit="page">S. 3</biblScope>
                        <imprint>
                           <date isodate="1887-12-14">14.12.1887</date>
                           <pubPlace/>
                           <publisher/>
                        </imprint>
                        <annot>
                           <p label="Weitere_Informationen">(Konzert der Pianistin Ida Reich; Datum gemäß Wiener Allgemeine Zeitung, 11.12.1887, S. 8)</p>
                           <p label="Vollständiger_Nachweis">Presse, Jg. 40, Nr. 344, 14.12.1887, S. 3</p>
                        </annot>
                        <ptr label="ANNO-ÖNB" target="http://anno.onb.ac.at/cgi-content/anno?aid=apr&amp;datum=18871214&amp;seite=3&amp;zoom=33&amp;query=%22brahms%22&amp;ref=anno-search"/>
                        <relationList>
                           <relation rel="isRealizationOf" target="#work_op._24"/>
                        </relationList>
                        <relatedItem rel="host">
                           <bibl>
                              <biblScope/>
                           </bibl>
                        </relatedItem>
                     </bibl>
                  </biblList>
               </event>
               <event>
                  <persName type="Pianist_in" corresp="../Brahms-Personenregister-ID/0012">Basch-Mahler, Fanny</persName>
                  <date isodate="1888-03-28">28.03.1888</date>
                  <geogName role="place">Wien</geogName>
                  <geogName role="venue">Großer Musikvereinssaal</geogName>
                  <biblList>
                     <bibl sameas="recordid_667946 " type="Rubrik_2">
                        <term label="Rubrik_2">Werkkritik</term>
                        <genre>article</genre>
                        <genre>newspaper</genre>
                        <author/>
                        <title level="j">Presse</title>
                        <title level="j">Local-Anzeiger</title>
                        <editor/>
                        <biblScope unit="vol">Jg. 41</biblScope>
                        <biblScope unit="issue">Nr. 90</biblScope>
                        <biblScope unit="page">S. 11</biblScope>
                        <imprint>
                           <date isodate="1888-03-30">30.03.1888</date>
                           <pubPlace/>
                           <publisher/>
                        </imprint>
                        <annot>
                           <p label="Weitere_Informationen">(Volkskonzert des Wiener Männergesangvereins)</p>
                           <p label="Vollständiger_Nachweis">Presse, Local-Anzeiger, Jg. 41, Nr. 90, 30.03.1888, S. 11</p>
                        </annot>
                        <ptr label="ANNO-ÖNB" target="http://anno.onb.ac.at/cgi-content/anno?aid=apr&amp;datum=18880330&amp;seite=11&amp;zoom=33&amp;query=%22brahms%22&amp;ref=anno-search"/>
                        <relationList>
                           <relation rel="isRealizationOf" target="#work_op._24"/>
                        </relationList>
                        <relatedItem rel="host">
                           <bibl>
                              <biblScope/>
                           </bibl>
                        </relatedItem>
                     </bibl>
                  </biblList>
               </event>
               <event>
                  <persName type="Pianist_in" corresp="../Brahms-Personenregister-ID/0038">Brüll, Ignaz</persName>
                  <date isodate="1890-12-07">07.12.1890</date>
                  <geogName role="place">Wien</geogName>
                  <geogName role="venue">Saal der Horak'schen Wiedener Schule</geogName>
                  <biblList>
                     <bibl sameas="recordid_668181 " type="Rubrik_17">
                        <term label="Rubrik_17">Vorankündigung</term>
                        <genre>article</genre>
                        <genre>newspaper</genre>
                        <author/>
                        <title level="j">Presse</title>
                        <title level="j">Local-Anzeiger</title>
                        <editor/>
                        <biblScope unit="vol">Jg. 43</biblScope>
                        <biblScope unit="issue">Nr. 333</biblScope>
                        <biblScope unit="page">S. 11</biblScope>
                        <imprint>
                           <date isodate="1890-12-05">05.12.1890</date>
                           <pubPlace/>
                           <publisher/>
                        </imprint>
                        <annot>
                           <p label="Weitere_Informationen">(Vortragsabend von Ignaz Brüll für die Zöglinge der Horak'schen Wiedener Schule zugunsten armer Schulkinder, 19.00 Uhr)</p>
                           <p label="Vollständiger_Nachweis">Presse, Local-Anzeiger, Jg. 43, Nr. 333, 05.12.1890, S. 11</p>
                        </annot>
                        <ptr label="ANNO-ÖNB" target="http://anno.onb.ac.at/cgi-content/anno?aid=apr&amp;datum=18901205&amp;seite=11&amp;zoom=33&amp;query=%22brahms%22&amp;ref=anno-search"/>
                        <relationList>
                           <relation rel="isRealizationOf" target="#work_op._24"/>
                        </relationList>
                        <relatedItem rel="host">
                           <bibl>
                              <biblScope/>
                           </bibl>
                        </relatedItem>
                     </bibl>
                  </biblList>
               </event>
               <event>
                  <date isodate="1893-02-26">26.02.1893</date>
                  <geogName role="place">Wien</geogName>
                  <geogName role="venue"> Turnsaal der Bürgerschule Zeltgasse</geogName>
                  <persName type="Pianist_in" corresp="../Brahms-Personenregister-ID/0480">Reich, Ida</persName>
                  <biblList>
                     <bibl sameas="recordid_668564 " type="Rubrik_18">
                        <term label="Rubrik_18">Vorankündigung</term>
                        <genre>article</genre>
                        <genre>newspaper</genre>
                        <author/>
                        <title level="j">Presse</title>
                        <title level="j">Local-Anzeiger</title>
                        <editor/>
                        <biblScope unit="vol">Jg. 46</biblScope>
                        <biblScope unit="issue">Nr. 57</biblScope>
                        <biblScope unit="page">S. 16</biblScope>
                        <imprint>
                           <date isodate="1893-02-26">26.02.1893</date>
                           <pubPlace/>
                           <publisher/>
                        </imprint>
                        <annot>
                           <p label="Weitere_Informationen">(Volkskonzert der Pianistin Ida Reich und der Sängerin Nini Pollatschek, Zeltgasse 7, 8. Bezirk)</p>
                           <p label="Vollständiger_Nachweis">Presse, Local-Anzeiger, Jg. 46, Nr. 57, 26.02.1893, S. 16</p>
                        </annot>
                        <ptr label="ANNO-ÖNB" target="http://anno.onb.ac.at/cgi-content/anno?aid=apr&amp;datum=18930226&amp;seite=14&amp;zoom=33&amp;query=%22brahms%22&amp;ref=anno-search"/>
                        <relationList>
                           <relation rel="isRealizationOf" target="#work_op._24"/>
                        </relationList>
                        <relatedItem rel="host">
                           <bibl>
                              <biblScope/>
                           </bibl>
                        </relatedItem>
                     </bibl>
                  </biblList>
               </event>
               <event>
                  <date isodate="1893-11-16">16.11.1893</date>
                  <geogName role="place">Wien</geogName>
                  <geogName role="venue">Saal Bösendorfer</geogName>
                  <persName type="Pianist_in" corresp="../Brahms-Personenregister-ID/0067">Eibenschütz, Ilona</persName>
                  <biblList>
                     <bibl sameas="recordid_668648 " type="Rubrik_2">
                        <term label="Rubrik_2">Werkkritik</term>
                        <genre>article</genre>
                        <genre>newspaper</genre>
                        <author/>
                        <title level="j">Presse</title>
                        <title level="j">Local-Anzeiger</title>
                        <editor/>
                        <biblScope unit="vol">Jg. 46</biblScope>
                        <biblScope unit="issue">Nr. 322</biblScope>
                        <biblScope unit="page">S. 11</biblScope>
                        <imprint>
                           <date isodate="1893-11-21">21.11.1893</date>
                           <pubPlace/>
                           <publisher/>
                        </imprint>
                        <annot>
                           <p label="Weitere_Informationen">(Klavierkonzert von Ilona Eibenschütz; Datum gemäß Die Presse, Local-Anzeiger, 15.11.1893, S. 15)</p>
                           <p label="Vollständiger_Nachweis">Presse, Local-Anzeiger, Jg. 46, Nr. 322, 21.11.1893, S. 11</p>
                        </annot>
                        <ptr label="ANNO-ÖNB" target="http://anno.onb.ac.at/cgi-content/anno?aid=apr&amp;datum=18931121&amp;seite=11&amp;zoom=33&amp;query=%22brahms%22&amp;ref=anno-search"/>
                        <relationList>
                           <relation rel="isRealizationOf" target="#work_op._24"/>
                        </relationList>
                        <relatedItem rel="host">
                           <bibl>
                              <biblScope/>
                           </bibl>
                        </relatedItem>
                     </bibl>
                  </biblList>
               </event>
               <event>
                  <persName type="Pianist_in" corresp="../Brahms-Personenregister-ID/0073">Epstein, Richard</persName>
                  <date isodate="1894-01-17">17.01.1894</date>
                  <geogName role="place">Wien</geogName>
                  <biblList>
                     <bibl sameas="recordid_668778 " type="Rubrik_3">
                        <term label="Rubrik_3">Vorankündigung</term>
                        <genre>article</genre>
                        <genre>newspaper</genre>
                        <author/>
                        <title level="j">Presse</title>
                        <editor/>
                        <biblScope unit="vol">Jg. 47</biblScope>
                        <biblScope unit="issue">Nr. 53</biblScope>
                        <biblScope unit="page">S. 2</biblScope>
                        <imprint>
                           <date isodate="1894-02-24">24.02.1894</date>
                           <pubPlace/>
                           <publisher/>
                        </imprint>
                        <annot>
                           <p label="Weitere_Informationen">(Konzert von Richard Epstein; Datum gemäß NWT, 20.01.1894, S. 8)</p>
                           <p label="Vollständiger_Nachweis">Presse, Jg. 47, Nr. 53, 24.02.1894, S. 2</p>
                        </annot>
                        <ptr label="ANNO-ÖNB" target="http://anno.onb.ac.at/cgi-content/anno?aid=apr&amp;datum=18940224&amp;seite=2&amp;zoom=33&amp;query=%22brahms%22&amp;ref=anno-search"/>
                        <relationList>
                           <relation rel="isRealizationOf" target="#work_op._24"/>
                        </relationList>
                        <relatedItem rel="host">
                           <bibl>
                              <biblScope/>
                           </bibl>
                        </relatedItem>
                     </bibl>
                  </biblList>
               </event>
               <event>
                  <date/>
                  <geogName role="place"/>
                  <persName type="Komponist_in" corresp="../Brahms-Personenregister-ID/0031">Brahms, Johannes</persName>
                  <biblList>
                     <bibl sameas="recordid_668828 " type="Rubrik_4">
                        <term label="Rubrik_4">Werkerwähnung</term>
                        <genre>article</genre>
                        <genre>newspaper</genre>
                        <author/>
                        <title level="j">Presse</title>
                        <title level="j">Local-Anzeiger</title>
                        <editor/>
                        <biblScope unit="vol">Jg. 47</biblScope>
                        <biblScope unit="issue">Nr. 182</biblScope>
                        <biblScope unit="page">S. [9]</biblScope>
                        <imprint>
                           <date isodate="1894-07-05">05.07.1894</date>
                           <pubPlace/>
                           <publisher/>
                        </imprint>
                        <annot>
                           <p label="Weitere_Informationen">(Erwähnung der thematischen Bedeutung "selbst der Vorschläge" bei der 21. Händel-Variation im Rahmen einer Besprechung der Neuerscheinung "Studien bei Hans v. Bülow" von Theodor Pfeiffer, Verlag Friedrich Luckhardt, Berlin 1894, einer Sammlung von Äußerungen Bülows aus seinen Frankfurter Unterrichtskursen der Sommer 1884, 1885 und 1886.)</p>
                           <p label="Vollständiger_Nachweis">Presse, Local-Anzeiger, Jg. 47, Nr. 182, 05.07.1894, S. [9]</p>
                        </annot>
                        <ptr label="ANNO-ÖNB" target="http://anno.onb.ac.at/cgi-content/anno?aid=apr&amp;datum=18940705&amp;seite=9&amp;zoom=33&amp;query=%22brahms%22&amp;ref=anno-search"/>
                        <relationList>
                           <relation rel="isRealizationOf" target="#work_op._24"/>
                        </relationList>
                        <relatedItem rel="host">
                           <bibl>
                              <biblScope/>
                           </bibl>
                        </relatedItem>
                     </bibl>
                  </biblList>
               </event>
               <event>
                  <date isodate="1894-12-07">07.12.1894</date>
                  <geogName role="place">Wien</geogName>
                  <persName type="Pianist_in" corresp="../Brahms-Personenregister-ID/0009">Barth, Karl Heinrich</persName>
                  <biblList>
                     <bibl sameas="recordid_668915 " type="Rubrik_2">
                        <term label="Rubrik_2">Werkkritik</term>
                        <genre>article</genre>
                        <genre>newspaper</genre>
                        <author/>
                        <title level="j">Presse</title>
                        <editor/>
                        <biblScope unit="vol">Jg. 47</biblScope>
                        <biblScope unit="issue">Nr. 344</biblScope>
                        <biblScope unit="page">S. 2</biblScope>
                        <imprint>
                           <date isodate="1894-12-16">16.12.1894</date>
                           <pubPlace/>
                           <publisher/>
                        </imprint>
                        <annot>
                           <p label="Weitere_Informationen">(Konzert von Prof. Barth; in Brahms' op. 24 "beruhte der künstlerische Ertrag des Abends"; Datum gemäß Neues Wiener Journal, 03.12.1894, S. 4)</p>
                           <p label="Vollständiger_Nachweis">Presse, Jg. 47, Nr. 344, 16.12.1894, S. 2</p>
                        </annot>
                        <ptr label="ANNO-ÖNB" target="http://anno.onb.ac.at/cgi-content/anno?aid=apr&amp;datum=18941216&amp;seite=2&amp;zoom=33&amp;query=%22brahms%22&amp;ref=anno-search"/>
                        <relationList>
                           <relation rel="isRealizationOf" target="#work_op._24"/>
                        </relationList>
                        <relatedItem rel="host">
                           <bibl>
                              <biblScope/>
                           </bibl>
                        </relatedItem>
                     </bibl>
                  </biblList>
               </event>
            </eventList>
         </history>
         <perfMedium>
            <perfResList>
               <head>Besetzung: Klavier</head>
               <perfResList>
                  <perfRes>Klavier</perfRes>
               </perfResList>
            </perfResList>
         </perfMedium>
         <notesStmt/>
         <expressionList/>
      </work>
   </workList>
</mei>
