<?xml version="1.0" encoding="UTF-8"?>
<mei xmlns:xs="http://www.w3.org/2001/XMLSchema" xmlns="http://www.music-encoding.org/ns/mei" meiversion="4.0.0">
   <fileDesc>
      <titleStmt>
         <title>Fünf Lieder</title>
         <respStmt>
            <persName role="editor" xml:id="VP">Vasiliki Papadopoulou</persName>
            <persName role="editor" xml:id="KE">Kathrin Eich</persName>
            <persName role="editor" xml:id="CG">Clemens Gubsch</persName>
            <persName role="editor" xml:id="MJ">Monika Jaroš</persName>
            <persName role="editor" xml:id="MW">Magdalena Weber</persName>
         </respStmt>
      </titleStmt>
      <pubStmt/>
      <seriesStmt>
         <title>Werke mit Opus</title>
         <identifier type="file_collection">Werkdateien</identifier>
      </seriesStmt>
   </fileDesc>
   <encodingDesc>
      <projectDesc>
         <p>Alle Werke werden in einer Datei separaten Datei angelegt und verlinkt.</p>
      </projectDesc>
   </encodingDesc>
   <workList>
      <work n="110" xml:id="work_op._105">
         <identifier label="Opus-Nummer">op. 105</identifier>
         <title>Fünf Lieder</title>
         <composer>
            <persName auth="GND" auth.uri="https://d-nb.info/gnd/" codedval="118514253">Johannes Brahms</persName>
         </composer>
         <history>
               <eventList type="performances">
                  <event>
                     <persName type="Pianist_in" corresp="../Brahms-Personenregister-ID/0217">Rottenberg, Ludwig</persName>
                     <persName type="Sänger_in" corresp="../Brahms-Personenregister-ID/0457">Walter, Gustav</persName>
                     <date isodate="1887-02-11">11.02.1887</date>
                     <geogName role="place">Wien</geogName>
                     <geogName role="venue">Saal Bösendorfer</geogName>
                     <biblList>
                        <bibl sameas="recordid_669722 " type="Rubrik_18">
                           <term label="Rubrik_18">Vorankündigung</term>
                           <genre>article</genre>
                           <genre>newspaper</genre>
                           <author/>
                           <title level="j">Vaterland</title>
                           <editor/>
                           <biblScope unit="vol">Jg. 28</biblScope>
                           <biblScope unit="issue">Nr. 40</biblScope>
                           <biblScope unit="page">S. 6</biblScope>
                           <imprint>
                              <date isodate="1887-02-10">10.02.1887</date>
                              <pubPlace/>
                              <publisher/>
                           </imprint>
                           <annot>
                              <p label="Weitere_Informationen">(2. Liederabend, "Brahms-Abend", von Kammersänger Gustav Walter unter Mitwirkung von Marie Baumayer und Ludwig Rottenberg, 19.30 Uhr; u.a. "drei noch ungedruckte neue Lieder"; Werk gemäß <bibl type="bibl" target="#BrahmsWV">BrahmsWV</bibl>, S. 426)</p>
                              <p label="Vollständiger_Nachweis">Vaterland, Jg. 28, Nr. 40, 10.02.1887, S. 6</p>
                           </annot>
                           <ptr label="ANNO-ÖNB" target="http://anno.onb.ac.at/cgi-content/anno?aid=vtl&amp;datum=18870210&amp;seite=6&amp;zoom=33&amp;query=%22brahms%22&amp;ref=anno-search"/>
                           <relationList>
                              <relation rel="isRealizationOf" target="#component_op._105,Nr.1"/>
                           </relationList>
                           <relatedItem rel="host">
                              <bibl>
                                 <title>gemäß BrahmsWV</title>
                                 <biblScope/>
                              </bibl>
                           </relatedItem>
                        </bibl>
                        <bibl sameas="recordid_667813 " type="Rubrik_2">
                           <term label="Rubrik_2">Werkkritik</term>
                           <genre>article</genre>
                           <genre>newspaper</genre>
                           <author/>
                           <title level="j">Presse</title>
                           <editor/>
                           <biblScope unit="vol">Jg. 40</biblScope>
                           <biblScope unit="issue">Nr. 52</biblScope>
                           <biblScope unit="page">S. [1] f.</biblScope>
                           <imprint>
                              <date isodate="1887-02-22">22.02.1887</date>
                              <pubPlace/>
                              <publisher/>
                           </imprint>
                           <annot>
                              <p label="Weitere_Informationen">(2. Liederabend, Brahms-Abend, von Gustav Walter; u.a. "drei Novitäten"; Uraufführung; Datum gemäß <bibl type="bibl" target="#BrahmsWV">BrahmsWV</bibl>, S. 426)</p>
                              <p label="Vollständiger_Nachweis">Presse, Jg. 40, Nr. 52, 22.02.1887, S. [1] f.</p>
                           </annot>
                           <ptr label="ANNO-ÖNB" target="http://anno.onb.ac.at/cgi-content/anno?aid=apr&amp;datum=18870222&amp;seite=1&amp;zoom=33&amp;query=%22brahms%22&amp;ref=anno-search"/>
                           <relationList>
                              <relation rel="isRealizationOf" target="#component_op._105,Nr.1"/>
                           </relationList>
                           <relatedItem rel="host">
                              <bibl>
                                 <title>gemäß BrahmsWV</title>
                                 <biblScope/>
                              </bibl>
                           </relatedItem>
                        </bibl>
                     </biblList>
                  </event>
                  <event>
                     <date isodate="1888-12-07">07.12.1888</date>
                     <geogName role="place">Wien</geogName>
                     <geogName role="venue">Saal Bösendorfer</geogName>
                     <persName type="Sänger_in" corresp="../Brahms-Personenregister-ID/0190">Papier, Rosa</persName>
                     <biblList>
                        <bibl sameas="recordid_669774 " type="Rubrik_18">
                           <term label="Rubrik_18">Vorankündigung</term>
                           <genre>article</genre>
                           <genre>newspaper</genre>
                           <author/>
                           <title level="j">Vaterland</title>
                           <editor/>
                           <biblScope unit="vol">Jg. 29</biblScope>
                           <biblScope unit="issue">Nr. 328</biblScope>
                           <biblScope unit="page">S. 4</biblScope>
                           <imprint>
                              <date isodate="1888-11-26">26.11.1888</date>
                              <pubPlace/>
                              <publisher/>
                           </imprint>
                           <annot>
                              <p label="Weitere_Informationen">(Liederabend der k. k. Kammersängerin Rosa Papier; "Wie Melodien zieht es mir" bzw. "Auf dem Kirchhofe", Datum gemäß NWT, 05.12.1888, S. 7)</p>
                              <p label="Vollständiger_Nachweis">Vaterland, Jg. 29, Nr. 328, 26.11.1888, S. 4</p>
                           </annot>
                           <ptr label="ANNO-ÖNB" target="http://anno.onb.ac.at/cgi-content/anno?aid=vtl&amp;datum=18881126&amp;seite=4&amp;zoom=33&amp;query=%22brahms%22&amp;ref=anno-search"/>
                           <relationList>
                              <relation rel="isRealizationOf" target="#component_op._105,Nr.1,3und4"/>
                           </relationList>
                           <relatedItem rel="host">
                              <bibl>
                                 <biblScope/>
                              </bibl>
                           </relatedItem>
                        </bibl>
                        <bibl sameas="recordid_669777 " type="Rubrik_18">
                           <term label="Rubrik_18">Vorankündigung</term>
                           <genre>article</genre>
                           <genre>newspaper</genre>
                           <author/>
                           <title level="j">Vaterland</title>
                           <editor/>
                           <biblScope unit="vol">Jg. 29</biblScope>
                           <biblScope unit="issue">Nr. 337</biblScope>
                           <biblScope unit="page">S. 6</biblScope>
                           <imprint>
                              <date isodate="1888-12-05">05.12.1888</date>
                              <pubPlace/>
                              <publisher/>
                           </imprint>
                           <annot>
                              <p label="Weitere_Informationen">(Liederabend der Kammersängerin Rosa Papier, 19.30 Uhr)</p>
                              <p label="Vollständiger_Nachweis">Vaterland, Jg. 29, Nr. 337, 05.12.1888, S. 6</p>
                           </annot>
                           <ptr label="ANNO-ÖNB" target="http://anno.onb.ac.at/cgi-content/anno?aid=vtl&amp;datum=18881205&amp;seite=6&amp;zoom=33&amp;query=%22brahms%22&amp;ref=anno-search"/>
                           <relationList>
                              <relation rel="isRealizationOf" target="#component_op._105,Nr.1,3und4"/>
                           </relationList>
                           <relatedItem rel="host">
                              <bibl>
                                 <biblScope/>
                              </bibl>
                           </relatedItem>
                        </bibl>
                     </biblList>
                  </event>
                  <event>
                     <date isodate="1889-01-16">16.01.1889</date>
                     <geogName role="place">Wien</geogName>
                     <geogName role="venue">Saal Bösendorfer</geogName>
                     <persName type="Sänger_in" corresp="../Brahms-Personenregister-ID/0208">Reichmann, Theodor</persName>
                     <biblList>
                        <bibl sameas="recordid_669788 " type="Rubrik_18">
                           <term label="Rubrik_18">Vorankündigung</term>
                           <genre>article</genre>
                           <genre>newspaper</genre>
                           <author/>
                           <title level="j">Vaterland</title>
                           <editor/>
                           <biblScope unit="vol">Jg. 30</biblScope>
                           <biblScope unit="issue">Nr. 6</biblScope>
                           <biblScope unit="page">S. 5</biblScope>
                           <imprint>
                              <date isodate="1889-01-06">06.01.1889</date>
                              <pubPlace/>
                              <publisher/>
                           </imprint>
                           <annot>
                              <p label="Weitere_Informationen">(Liederabend von Kammersänger Reichmann; Werke von J. Brahms: "Von ewiger Liebe", "Immer leiser wird mein Schlummer")</p>
                              <p label="Vollständiger_Nachweis">Vaterland, Jg. 30, Nr. 6, 06.01.1889, S. 5</p>
                           </annot>
                           <ptr label="ANNO-ÖNB" target="http://anno.onb.ac.at/cgi-content/anno?aid=vtl&amp;datum=18890106&amp;seite=5&amp;zoom=33&amp;query=%22brahms%22&amp;ref=anno-search"/>
                           <relationList>
                              <relation rel="isRealizationOf" target="#component_op._105,Nr.2"/>
                           </relationList>
                           <relatedItem rel="host">
                              <bibl>
                                 <biblScope/>
                              </bibl>
                           </relatedItem>
                        </bibl>
                     </biblList>
                  </event>
                  <event>
                     <date isodate="1889-03-18">18.03.1889</date>
                     <geogName role="place">Wien</geogName>
                     <geogName role="venue">Saal Bösendorfer</geogName>
                     <persName type="Sänger_in" corresp="../Brahms-Personenregister-ID/0208">Reichmann, Theodor</persName>
                     <persName type="Pianist_in" corresp="../Brahms-Personenregister-ID/0259">Stavenhagen, Bernhard</persName>
                     <biblList>
                        <bibl sameas="recordid_669820 " type="Rubrik_18">
                           <term label="Rubrik_18">Vorankündigung</term>
                           <genre>article</genre>
                           <genre>newspaper</genre>
                           <author/>
                           <title level="j">Vaterland</title>
                           <editor/>
                           <biblScope unit="vol">Jg. 30</biblScope>
                           <biblScope unit="issue">Nr. 71</biblScope>
                           <biblScope unit="page">S. 7</biblScope>
                           <imprint>
                              <date isodate="1889-03-13">13.03.1889</date>
                              <pubPlace/>
                              <publisher/>
                           </imprint>
                           <annot>
                              <p label="Weitere_Informationen">(Liederabend von Kammersänger Reichmann unter Mitwirkung vonBernhard Stavenhagen, 19.30 Uhr)</p>
                              <p label="Vollständiger_Nachweis">Vaterland, Jg. 30, Nr. 71, 13.03.1889, S. 7</p>
                           </annot>
                           <ptr label="ANNO-ÖNB" target="http://anno.onb.ac.at/cgi-content/anno?aid=vtl&amp;datum=18890313&amp;seite=7&amp;zoom=33&amp;query=%22brahms%22&amp;ref=anno-search"/>
                           <relationList>
                              <relation rel="isRealizationOf" target="#component_op._105,Nr.2"/>
                           </relationList>
                           <relatedItem rel="host">
                              <bibl>
                                 <biblScope/>
                              </bibl>
                           </relatedItem>
                        </bibl>
                     </biblList>
                  </event>
                  <event>
                     <date isodate="1889-11-22">22.11.1889</date>
                     <geogName role="place">Wien</geogName>
                     <geogName role="venue">Saal Bösendorfer</geogName>
                     <persName type="Sänger_in" corresp="../Brahms-Personenregister-ID/0190">Papier, Rosa</persName>
                     <biblList>
                        <bibl sameas="recordid_669841 " type="Rubrik_18">
                           <term label="Rubrik_18">Vorankündigung</term>
                           <genre>article</genre>
                           <genre>newspaper</genre>
                           <author/>
                           <title level="j">Vaterland</title>
                           <editor/>
                           <biblScope unit="vol">Jg. 30</biblScope>
                           <biblScope unit="issue">Nr. 311</biblScope>
                           <biblScope unit="page">S. 6</biblScope>
                           <imprint>
                              <date isodate="1889-11-12">12.11.1889</date>
                              <pubPlace/>
                              <publisher/>
                           </imprint>
                           <annot>
                              <p label="Weitere_Informationen">(Liederabend der Kammersängerin Rosa Papier; u.a. Brahms: "Immer leiser wird mein Schlummer", "Vergebliches Ständchen")</p>
                              <p label="Vollständiger_Nachweis">Vaterland, Jg. 30, Nr. 311, 12.11.1889, S. 6</p>
                           </annot>
                           <ptr label="ANNO-ÖNB" target="http://anno.onb.ac.at/cgi-content/anno?aid=vtl&amp;datum=18891112&amp;seite=6&amp;zoom=33&amp;query=%22brahms%22&amp;ref=anno-search"/>
                           <relationList>
                              <relation rel="isRealizationOf" target="#component_op._105,Nr.2"/>
                           </relationList>
                           <relatedItem rel="host">
                              <bibl>
                                 <biblScope/>
                              </bibl>
                           </relatedItem>
                        </bibl>
                     </biblList>
                  </event>
                  <event>
                     <persName type="musikalische_r_Direktor_in" corresp="../Brahms-Personenregister-ID/0470">Weinzierl, Max von</persName>
                     <corpName type="Chor" corresp="../Brahms-Körperschaftenregister-ID/0036">Wiener Singakademie</corpName>
                     <date isodate="1890-12-18">18.12.1890</date>
                     <geogName role="place">Wien</geogName>
                     <geogName role="venue">Kleiner Musikvereinssaal</geogName>
                     <biblList>
                        <bibl sameas="recordid_669891 " type="Rubrik_18">
                           <term label="Rubrik_18">Vorankündigung</term>
                           <genre>article</genre>
                           <genre>newspaper</genre>
                           <author/>
                           <title level="j">Vaterland</title>
                           <editor/>
                           <biblScope unit="vol">Jg. 31</biblScope>
                           <biblScope unit="issue">1. Beiblatt zu Nr. 341</biblScope>
                           <biblScope unit="page">S. 3</biblScope>
                           <imprint>
                              <date isodate="1890-12-14">14.12.1890</date>
                              <pubPlace/>
                              <publisher/>
                           </imprint>
                           <annot>
                              <p label="Weitere_Informationen">(1. Konzert der Wiener Singakademie, 19.30 Uhr; Werke von J. Brahms: op. 62, Nr. 2, op. 105, Nr. 4 und op. 107, Nr. 3)</p>
                              <p label="Vollständiger_Nachweis">Vaterland, Jg. 31, 1. Beiblatt zu Nr. 341, 14.12.1890, S. 3</p>
                           </annot>
                           <ptr label="ANNO-ÖNB" target="http://anno.onb.ac.at/cgi-content/anno?aid=vtl&amp;datum=18901214&amp;seite=11&amp;zoom=33&amp;query=%22brahms%22&amp;ref=anno-search"/>
                           <relationList>
                              <relation rel="isRealizationOf" target="#component_op._105,Nr.4"/>
                           </relationList>
                           <relatedItem rel="host">
                              <bibl>
                                 <biblScope/>
                              </bibl>
                           </relatedItem>
                        </bibl>
                     </biblList>
                  </event>
                  <event>
                     <date isodate="1892-04-05">05.04.1892</date>
                     <geogName role="place">Wien</geogName>
                     <persName type="Sänger_in" corresp="../Brahms-Personenregister-ID/0007">Barbi, Alice</persName>
                     <biblList>
                        <bibl sameas="recordid_669954 " type="Rubrik_18">
                           <term label="Rubrik_18">Vorankündigung</term>
                           <genre>article</genre>
                           <genre>newspaper</genre>
                           <author/>
                           <title level="j">Vaterland</title>
                           <editor/>
                           <biblScope unit="vol">Jg. 33</biblScope>
                           <biblScope unit="issue">Nr. 96</biblScope>
                           <biblScope unit="page">S. 6</biblScope>
                           <imprint>
                              <date isodate="1892-04-05">05.04.1892</date>
                              <pubPlace/>
                              <publisher/>
                           </imprint>
                           <annot>
                              <p label="Weitere_Informationen">(Konzert der Kammersängerin Alice Barbi; u.a. 6 Lieder von Brahms: "Von ewiger Liebe", "Am jüngsten Tag", "Der Tod, das ist die kühle Nacht", "Vor dem Fenster", "Immer leiser wird mein Schlummer", "Ei schmollte mein Vater")</p>
                              <p label="Vollständiger_Nachweis">Vaterland, Jg. 33, Nr. 96, 05.04.1892, S. 6</p>
                           </annot>
                           <ptr label="ANNO-ÖNB" target="http://anno.onb.ac.at/cgi-content/anno?aid=vtl&amp;datum=18920405&amp;seite=6&amp;zoom=33&amp;query=%22brahms%22&amp;ref=anno-search"/>
                           <relationList>
                              <relation rel="isRealizationOf" target="#component_op._105,Nr.2"/>
                           </relationList>
                           <relatedItem rel="host">
                              <bibl>
                                 <biblScope/>
                              </bibl>
                           </relatedItem>
                        </bibl>
                        <bibl sameas="recordid_668433 " type="Rubrik_18">
                           <term label="Rubrik_18">Vorankündigung</term>
                           <genre>article</genre>
                           <genre>newspaper</genre>
                           <author/>
                           <title level="j">Presse</title>
                           <title level="j">Local-Anzeiger</title>
                           <editor/>
                           <biblScope unit="vol">Jg. 45</biblScope>
                           <biblScope unit="issue">Nr. 96</biblScope>
                           <biblScope unit="page">S. 11</biblScope>
                           <imprint>
                              <date isodate="1892-04-05">05.04.1892</date>
                              <pubPlace/>
                              <publisher/>
                           </imprint>
                           <annot>
                              <p label="Weitere_Informationen">(Konzert der Kammersängerin Alice Barbi; u.a. 6 Lieder von Brahms: "Von ewiger Liebe", "Am jüngsten Tag", "Der Tod das ist die kühle Nacht", "Vor dem Fenster", "Immer leiser wird mein Schlummer", "Es schmollte mein Vater")</p>
                              <p label="Vollständiger_Nachweis">Presse, Local-Anzeiger, Jg. 45, Nr. 96, 05.04.1892, S. 11</p>
                           </annot>
                           <ptr label="ANNO-ÖNB" target="http://anno.onb.ac.at/cgi-content/anno?aid=apr&amp;datum=18920405&amp;seite=11&amp;zoom=33&amp;query=%22brahms%22&amp;ref=anno-search"/>
                           <relationList>
                              <relation rel="isRealizationOf" target="#component_op._105,Nr.2"/>
                           </relationList>
                           <relatedItem rel="host">
                              <bibl>
                                 <biblScope/>
                              </bibl>
                           </relatedItem>
                        </bibl>
                     </biblList>
                  </event>
                  <event>
                     <date isodate="1892-05-27">27.05.1892</date>
                     <geogName role="place">Wien</geogName>
                     <geogName role="venue">Vortragssaal der Internationalen Theater- und Musikausstellung</geogName>
                     <persName type="Sänger_in" corresp="../Brahms-Personenregister-ID/0007">Barbi, Alice</persName>
                     <biblList>
                        <bibl sameas="recordid_669969 " type="Rubrik_18">
                           <term label="Rubrik_18">Vorankündigung</term>
                           <genre>article</genre>
                           <genre>newspaper</genre>
                           <author/>
                           <title level="j">Vaterland</title>
                           <editor/>
                           <biblScope unit="vol">Jg. 33</biblScope>
                           <biblScope unit="issue">Nr. 146</biblScope>
                           <biblScope unit="page">S. 4</biblScope>
                           <imprint>
                              <date isodate="1892-05-26">26.05.1892</date>
                              <pubPlace/>
                              <publisher/>
                           </imprint>
                           <annot>
                              <p label="Weitere_Informationen">(Konzert der Kammersängerin Alice Barbi im Rahmen der Internationalen Theater- und Musikausstellung, 20.00 Uhr; u.a. 2 Lieder von Brahms: "Des Liebsten Schwur" und "Immer leiser wird mein Schlummer")</p>
                              <p label="Vollständiger_Nachweis">Vaterland, Jg. 33, Nr. 146, 26.05.1892, S. 4</p>
                           </annot>
                           <ptr label="ANNO-ÖNB" target="http://anno.onb.ac.at/cgi-content/anno?aid=vtl&amp;datum=18920526&amp;seite=4&amp;zoom=33&amp;query=%22brahms%22&amp;ref=anno-search"/>
                           <relationList>
                              <relation rel="isRealizationOf" target="#component_op._105,Nr.2"/>
                           </relationList>
                           <relatedItem rel="host">
                              <bibl>
                                 <biblScope/>
                              </bibl>
                           </relatedItem>
                        </bibl>
                     </biblList>
                  </event>
                  <event>
                     <date isodate="1892-11-21">21.11.1892</date>
                     <geogName role="place">Wien</geogName>
                     <geogName role="venue">Saal Bösendorfer</geogName>
                     <persName type="Sänger_in" corresp="#">Finkenstein, Jettka</persName>
                     <biblList>
                        <bibl sameas="recordid_669984 " type="Rubrik_18">
                           <term label="Rubrik_18">Vorankündigung</term>
                           <genre>article</genre>
                           <genre>newspaper</genre>
                           <author/>
                           <title level="j">Vaterland</title>
                           <editor/>
                           <biblScope unit="vol">Jg. 33</biblScope>
                           <biblScope unit="issue">Nr. 319</biblScope>
                           <biblScope unit="page">S. 6</biblScope>
                           <imprint>
                              <date isodate="1892-11-17">17.11.1892</date>
                              <pubPlace/>
                              <publisher/>
                           </imprint>
                           <annot>
                              <p label="Weitere_Informationen">(Liederabend von Jettka Finkenstein)</p>
                              <p label="Vollständiger_Nachweis">Vaterland, Jg. 33, Nr. 319, 17.11.1892, S. 6</p>
                           </annot>
                           <ptr label="ANNO-ÖNB" target="http://anno.onb.ac.at/cgi-content/anno?aid=vtl&amp;datum=18921117&amp;seite=6&amp;zoom=33&amp;query=%22brahms%22&amp;ref=anno-search"/>
                           <relationList>
                              <relation rel="isRealizationOf" target="#component_op._105,Nr.1und2"/>
                           </relationList>
                           <relatedItem rel="host">
                              <bibl>
                                 <biblScope/>
                              </bibl>
                           </relatedItem>
                        </bibl>
                        <bibl sameas="recordid_668498 " type="Rubrik_18">
                           <term label="Rubrik_18">Vorankündigung</term>
                           <genre>article</genre>
                           <genre>newspaper</genre>
                           <author/>
                           <title level="j">Presse</title>
                           <title level="j">Local-Anzeiger</title>
                           <editor/>
                           <biblScope unit="vol">Jg. 45</biblScope>
                           <biblScope unit="issue">Nr. 319</biblScope>
                           <biblScope unit="page">S. 11</biblScope>
                           <imprint>
                              <date isodate="1892-11-17">17.11.1892</date>
                              <pubPlace/>
                              <publisher/>
                           </imprint>
                           <annot>
                              <p label="Weitere_Informationen">(Liederabend von Jettka Finkenstein)</p>
                              <p label="Vollständiger_Nachweis">Presse, Local-Anzeiger, Jg. 45, Nr. 319, 17.11.1892, S. 11</p>
                           </annot>
                           <ptr label="ANNO-ÖNB" target="http://anno.onb.ac.at/cgi-content/anno?aid=apr&amp;datum=18921117&amp;seite=11&amp;zoom=33&amp;query=%22brahms%22&amp;ref=anno-search"/>
                           <relationList>
                              <relation rel="isRealizationOf" target="#component_op._105,Nr.1und2"/>
                           </relationList>
                           <relatedItem rel="host">
                              <bibl>
                                 <biblScope/>
                              </bibl>
                           </relatedItem>
                        </bibl>
                     </biblList>
                  </event>
                  <event>
                     <date isodate="1893-12-19">19.12.1893</date>
                     <geogName role="place">Wien</geogName>
                     <geogName role="venue">Großer Musikvereinssaal</geogName>
                     <persName type="Sänger_in" corresp="../Brahms-Personenregister-ID/0007">Barbi, Alice</persName>
                     <biblList>
                        <bibl sameas="recordid_670058 " type="Rubrik_18">
                           <term label="Rubrik_18">Vorankündigung</term>
                           <genre>article</genre>
                           <genre>newspaper</genre>
                           <author/>
                           <title level="j">Vaterland</title>
                           <title level="j">Morgenblatt</title>
                           <editor/>
                           <biblScope unit="vol">Jg. 34</biblScope>
                           <biblScope unit="issue">Nr. 347</biblScope>
                           <biblScope unit="page">S. [6]</biblScope>
                           <imprint>
                              <date isodate="1893-12-16">16.12.1893</date>
                              <pubPlace/>
                              <publisher/>
                           </imprint>
                           <annot>
                              <p label="Weitere_Informationen">(Abschiedskonzert von Alice Barbi, 19.30 Uhr; u.a. 4 Lieder von Brahms: "Immer leiser wird mein Schlummer", "Nicht mehr zu Dir zu gehen, beschloß ich", "Die Nachtigall", "Der Mond steht über dem Berge")</p>
                              <p label="Vollständiger_Nachweis">Vaterland, Morgenblatt, Jg. 34, Nr. 347, 16.12.1893, S. [6]</p>
                           </annot>
                           <ptr label="ANNO-ÖNB" target="http://anno.onb.ac.at/cgi-content/anno?aid=vtl&amp;datum=18931216&amp;seite=6&amp;zoom=33&amp;query=%22brahms%22&amp;ref=anno-search"/>
                           <relationList>
                              <relation rel="isRealizationOf" target="#component_op._105,Nr.2"/>
                           </relationList>
                           <relatedItem rel="host">
                              <bibl>
                                 <biblScope/>
                              </bibl>
                           </relatedItem>
                        </bibl>
                        <bibl sameas="recordid_668696 " type="Rubrik_18">
                           <term label="Rubrik_18">Vorankündigung</term>
                           <genre>article</genre>
                           <genre>newspaper</genre>
                           <author/>
                           <title level="j">Presse</title>
                           <title level="j">Local-Anzeiger</title>
                           <editor/>
                           <biblScope unit="vol">Jg. 46</biblScope>
                           <biblScope unit="issue">Nr. 347</biblScope>
                           <biblScope unit="page">S. 15</biblScope>
                           <imprint>
                              <date isodate="1893-12-16">16.12.1893</date>
                              <pubPlace/>
                              <publisher/>
                           </imprint>
                           <annot>
                              <p label="Weitere_Informationen">(Abschiedskonzert der Kammersängerin Alice Barbi, 19.30 Uhr; u.a. 4 Lieder von Brahms: "Immer leiser wird mein Schlummer", "Nicht mehr zu Dir zu gehen, beschloß ich", "Die Nachtigall", "Der Mond steht über dem Berge")</p>
                              <p label="Vollständiger_Nachweis">Presse, Local-Anzeiger, Jg. 46, Nr. 347, 16.12.1893, S. 15</p>
                           </annot>
                           <ptr label="ANNO-ÖNB" target="http://anno.onb.ac.at/cgi-content/anno?aid=apr&amp;datum=18931216&amp;seite=9&amp;zoom=33&amp;query=%22brahms%22&amp;ref=anno-search"/>
                           <relationList>
                              <relation rel="isRealizationOf" target="#component_op._105,Nr.2"/>
                           </relationList>
                           <relatedItem rel="host">
                              <bibl>
                                 <biblScope/>
                              </bibl>
                           </relatedItem>
                        </bibl>
                     </biblList>
                  </event>
                  <event>
                     <persName type="Pianist_in" corresp="../Brahms-Personenregister-ID/0192">Paumgartner, Hans</persName>
                     <persName type="Sänger_in" corresp="../Brahms-Personenregister-ID/0098">Gura, Eugen</persName>
                     <date isodate="1894-11-29">29.11.1894</date>
                     <geogName role="place">Wien</geogName>
                     <geogName role="venue">Saal Bösendorfer</geogName>
                     <biblList>
                        <bibl sameas="recordid_670115 " type="Rubrik_18">
                           <term label="Rubrik_18">Vorankündigung</term>
                           <genre>article</genre>
                           <genre>newspaper</genre>
                           <author/>
                           <title level="j">Vaterland</title>
                           <title level="j">Morgenblatt</title>
                           <editor/>
                           <biblScope unit="vol">Jg. 35</biblScope>
                           <biblScope unit="issue">Nr. 324</biblScope>
                           <biblScope unit="page">S. 7</biblScope>
                           <imprint>
                              <date isodate="1894-11-25">25.11.1894</date>
                              <pubPlace/>
                              <publisher/>
                           </imprint>
                           <annot>
                              <p label="Weitere_Informationen">(Liederabend von Eugen Gura; u.a. 3 Lieder von Brahms: "Auf dem Kirchhof", "Verrath", "Von ewiger Liebe")</p>
                              <p label="Vollständiger_Nachweis">Vaterland, Morgenblatt, Jg. 35, Nr. 324, 25.11.1894, S. 7</p>
                           </annot>
                           <ptr label="ANNO-ÖNB" target="http://anno.onb.ac.at/cgi-content/anno?aid=vtl&amp;datum=18941125&amp;seite=7&amp;zoom=33&amp;query=%22brahms%22&amp;ref=anno-search"/>
                           <relationList>
                              <relation rel="isRealizationOf" target="#component_op._105,Nr.4und5"/>
                           </relationList>
                           <relatedItem rel="host">
                              <bibl>
                                 <biblScope/>
                              </bibl>
                           </relatedItem>
                        </bibl>
                        <bibl sameas="recordid_668887 " type="Rubrik_18">
                           <term label="Rubrik_18">Vorankündigung</term>
                           <genre>article</genre>
                           <genre>newspaper</genre>
                           <author/>
                           <title level="j">Presse</title>
                           <title level="j">Local-Anzeiger</title>
                           <editor/>
                           <biblScope unit="vol">Jg. 47</biblScope>
                           <biblScope unit="issue">Nr. 324</biblScope>
                           <biblScope unit="page">S. 15</biblScope>
                           <imprint>
                              <date isodate="1894-11-25">25.11.1894</date>
                              <pubPlace/>
                              <publisher/>
                           </imprint>
                           <annot>
                              <p label="Weitere_Informationen">(Liederabend von Eugen Gura; u.a. Werke von Brahms: op. 105, Nr. 4 und 5 sowie op. 43, Nr. 1)</p>
                              <p label="Vollständiger_Nachweis">Presse, Local-Anzeiger, Jg. 47, Nr. 324, 25.11.1894, S. 15</p>
                           </annot>
                           <ptr label="ANNO-ÖNB" target="http://anno.onb.ac.at/cgi-content/anno?aid=apr&amp;datum=18941125&amp;seite=15&amp;zoom=33&amp;query=%22brahms%22&amp;ref=anno-search"/>
                           <relationList>
                              <relation rel="isRealizationOf" target="#component_op._105,Nr.4und5"/>
                           </relationList>
                           <relatedItem rel="host">
                              <bibl>
                                 <biblScope/>
                              </bibl>
                           </relatedItem>
                        </bibl>
                        <bibl sameas="recordid_668913 " type="Rubrik_3">
                           <term label="Rubrik_3">Vorankündigung</term>
                           <genre>article</genre>
                           <genre>newspaper</genre>
                           <author/>
                           <title level="j">Presse</title>
                           <editor/>
                           <biblScope unit="vol">Jg. 47</biblScope>
                           <biblScope unit="issue">Nr. 344</biblScope>
                           <biblScope unit="page">S. [1]</biblScope>
                           <imprint>
                              <date isodate="1894-12-16">16.12.1894</date>
                              <pubPlace/>
                              <publisher/>
                           </imprint>
                           <annot>
                              <p label="Weitere_Informationen">(Liederabend von Eugen Gura; Datum gemäß NWT, 01.12.1894, S. 7)</p>
                              <p label="Vollständiger_Nachweis">Presse, Jg. 47, Nr. 344, 16.12.1894, S. [1]</p>
                           </annot>
                           <ptr label="ANNO-ÖNB" target="http://anno.onb.ac.at/cgi-content/anno?aid=apr&amp;datum=18941216&amp;seite=1&amp;zoom=33&amp;query=%22brahms%22&amp;ref=anno-search"/>
                           <relationList>
                              <relation rel="isRealizationOf" target="#component_op._105,Nr.4und5"/>
                           </relationList>
                           <relatedItem rel="host">
                              <bibl>
                                 <biblScope/>
                              </bibl>
                           </relatedItem>
                        </bibl>
                     </biblList>
                  </event>
                  <event>
                     <date isodate="1896-01-31">31.01.1896</date>
                     <geogName role="place">Wien</geogName>
                     <persName type="Sänger_in" corresp="../Brahms-Personenregister-ID/0251">Sistermans, Anton</persName>
                     <biblList>
                        <bibl sameas="recordid_670225 " type="Rubrik_18">
                           <term label="Rubrik_18">Vorankündigung</term>
                           <genre>article</genre>
                           <genre>newspaper</genre>
                           <author/>
                           <title level="j">Vaterland</title>
                           <title level="j">Morgenblatt</title>
                           <editor/>
                           <biblScope unit="vol">Jg. 37</biblScope>
                           <biblScope unit="issue">Nr. 21</biblScope>
                           <biblScope unit="page">S. 6</biblScope>
                           <imprint>
                              <date isodate="1896-01-22">22.01.1896</date>
                              <pubPlace/>
                              <publisher/>
                           </imprint>
                           <annot>
                              <p label="Weitere_Informationen">(Liederabend von Anton Sistermans; u.a. 4 Lieder von Brahms: "Alte Liebe", "Verrath [Ballade]", "Ständchen", "Entführung")</p>
                              <p label="Vollständiger_Nachweis">Vaterland, Morgenblatt, Jg. 37, Nr. 21, 22.01.1896, S. 6</p>
                           </annot>
                           <ptr label="ANNO-ÖNB" target="http://anno.onb.ac.at/cgi-content/anno?aid=vtl&amp;datum=18960122&amp;seite=6&amp;zoom=33&amp;query=%22brahms%22&amp;ref=anno-search"/>
                           <relationList>
                              <relation rel="isRealizationOf" target="#component_op._105,Nr.5"/>
                           </relationList>
                           <relatedItem rel="host">
                              <bibl>
                                 <biblScope/>
                              </bibl>
                           </relatedItem>
                        </bibl>
                        <bibl sameas="recordid_669135 " type="Rubrik_18">
                           <term label="Rubrik_18">Vorankündigung</term>
                           <genre>article</genre>
                           <genre>newspaper</genre>
                           <author/>
                           <title level="j">Presse</title>
                           <title level="j">Local-Anzeiger</title>
                           <editor/>
                           <biblScope unit="vol">Jg. 49</biblScope>
                           <biblScope unit="issue">Nr. 22</biblScope>
                           <biblScope unit="page">S. 11</biblScope>
                           <imprint>
                              <date isodate="1896-01-23">23.01.1896</date>
                              <pubPlace/>
                              <publisher/>
                           </imprint>
                           <annot>
                              <p label="Weitere_Informationen">(Liederabend von Anton Sistermans; Werke von Brahms: "'Alte Liebe', 'Verrath' [Ballade], Ständchen, 'Entführung'")</p>
                              <p label="Vollständiger_Nachweis">Presse, Local-Anzeiger, Jg. 49, Nr. 22, 23.01.1896, S. 11</p>
                           </annot>
                           <ptr label="ANNO-ÖNB" target="http://anno.onb.ac.at/cgi-content/anno?aid=apr&amp;datum=18960123&amp;seite=11&amp;zoom=33&amp;query=%22brahms%22&amp;ref=anno-search"/>
                           <relationList>
                              <relation rel="isRealizationOf" target="#component_op._105,Nr.5"/>
                           </relationList>
                           <relatedItem rel="host">
                              <bibl>
                                 <biblScope/>
                              </bibl>
                           </relatedItem>
                        </bibl>
                     </biblList>
                  </event>
                  <event>
                     <persName type="Sänger_in" corresp="../Brahms-Personenregister-ID/0034">Forster-Brandt, Ellen</persName>
                     <date isodate="1900-02-21">21.02.1900</date>
                     <geogName role="place">Wien</geogName>
                     <geogName role="venue">Großer Musikvereinssaal</geogName>
                     <biblList>
                        <bibl sameas="recordid_670660 " type="Rubrik_18">
                           <term label="Rubrik_18">Vorankündigung</term>
                           <genre>article</genre>
                           <genre>newspaper</genre>
                           <author/>
                           <title level="j">Vaterland</title>
                           <title level="j">Morgenblatt</title>
                           <editor/>
                           <biblScope unit="vol">Jg. 41</biblScope>
                           <biblScope unit="issue">Nr. 47</biblScope>
                           <biblScope unit="page">S. 9</biblScope>
                           <imprint>
                              <date isodate="1900-02-18">18.02.1900</date>
                              <pubPlace/>
                              <publisher/>
                           </imprint>
                           <annot>
                              <p label="Weitere_Informationen">(Liederabend von Ellen Brand-Forster und Fritz Schrödter; weiteres Werk von Brahms: op. 75, Nr. 3)</p>
                              <p label="Vollständiger_Nachweis">Vaterland, Morgenblatt, Jg. 41, Nr. 47, 18.02.1900, S. 9</p>
                           </annot>
                           <ptr label="ANNO-ÖNB" target="http://anno.onb.ac.at/cgi-content/anno?aid=vtl&amp;datum=19000218&amp;seite=9&amp;zoom=33&amp;query=%22brahms%22&amp;ref=anno-search"/>
                           <relationList>
                              <relation rel="isRealizationOf" target="#component_op._105,Nr.1"/>
                           </relationList>
                           <relatedItem rel="host">
                              <bibl>
                                 <biblScope/>
                              </bibl>
                           </relatedItem>
                        </bibl>
                     </biblList>
                  </event>
                  <event>
                     <date isodate="1900-03-24">24.03.1900</date>
                     <geogName role="place">Wien</geogName>
                     <geogName role="venue">Saal Bösendorfer</geogName>
                     <persName type="Sänger_in" corresp="#">Wüllner, Ludwig</persName>
                     <biblList>
                        <bibl sameas="recordid_670694 " type="Rubrik_18">
                           <term label="Rubrik_18">Vorankündigung</term>
                           <genre>article</genre>
                           <genre>newspaper</genre>
                           <author/>
                           <title level="j">Vaterland</title>
                           <title level="j">Morgenblatt</title>
                           <editor/>
                           <biblScope unit="vol">Jg. 41</biblScope>
                           <biblScope unit="issue">Nr. 78</biblScope>
                           <biblScope unit="page">S. 6</biblScope>
                           <imprint>
                              <date isodate="1900-03-21">21.03.1900</date>
                              <pubPlace/>
                              <publisher/>
                           </imprint>
                           <annot>
                              <p label="Weitere_Informationen">(Liederabend von Dr. Ludwig Wüllner; u.a. 5 Lieder von Brahms: "Auf dem Kirchhofe, Liebesgluth, Auf dem See, In Waldeseinsamkeit, Verrath")</p>
                              <p label="Vollständiger_Nachweis">Vaterland, Morgenblatt, Jg. 41, Nr. 78, 21.03.1900, S. 6</p>
                           </annot>
                           <ptr label="ANNO-ÖNB" target="http://anno.onb.ac.at/cgi-content/anno?aid=vtl&amp;datum=19000321&amp;seite=6&amp;zoom=33&amp;query=%22brahms%22&amp;ref=anno-search"/>
                           <relationList>
                              <relation rel="isRealizationOf" target="#component_op._105,Nr.4und5"/>
                           </relationList>
                           <relatedItem rel="host">
                              <bibl>
                                 <biblScope/>
                              </bibl>
                           </relatedItem>
                        </bibl>
                     </biblList>
                  </event>
                  <event>
                     <date isodate="1901-01-07">07.01.1901</date>
                     <geogName role="place">Wien</geogName>
                     <persName type="Sänger_in" corresp="../Brahms-Personenregister-ID/0007">Barbi, Alice</persName>
                     <biblList>
                        <bibl sameas="recordid_670744 " type="Rubrik_3">
                           <term label="Rubrik_3">Vorankündigung</term>
                           <genre>article</genre>
                           <genre>newspaper</genre>
                           <author/>
                           <title level="j">Vaterland</title>
                           <title level="j">Morgenblatt</title>
                           <editor/>
                           <biblScope unit="vol">Jg. 42</biblScope>
                           <biblScope unit="issue">Nr. 13</biblScope>
                           <biblScope unit="page">S. 2</biblScope>
                           <imprint>
                              <date isodate="1901-01-13">13.01.1901</date>
                              <pubPlace/>
                              <publisher/>
                           </imprint>
                           <annot>
                              <p label="Weitere_Informationen">(1. Liederabend zu Gunsten wohltätiger Zwecke von Alice Barbi; Datum gemäß NWT, 09.01.1901, S. 9)</p>
                              <p label="Vollständiger_Nachweis">Vaterland, Morgenblatt, Jg. 42, Nr. 13, 13.01.1901, S. 2</p>
                           </annot>
                           <ptr label="ANNO-ÖNB" target="http://anno.onb.ac.at/cgi-content/anno?aid=vtl&amp;datum=19010113&amp;seite=2&amp;zoom=33&amp;query=%22brahms%22&amp;ref=anno-search"/>
                           <relationList>
                              <relation rel="isRealizationOf" target="#component_op._105,Nr.2"/>
                           </relationList>
                           <relatedItem rel="host">
                              <bibl>
                                 <biblScope/>
                              </bibl>
                           </relatedItem>
                        </bibl>
                     </biblList>
                  </event>
                  <event>
                     <persName type="Pianist_in" corresp="../Brahms-Personenregister-ID/0220">Röntgen, Julius</persName>
                     <persName type="Sänger_in" corresp="../Brahms-Personenregister-ID/0467">Messchaert, Johannes</persName>
                     <date isodate="1896-10-30">30.10.1896</date>
                     <geogName role="place">Wien</geogName>
                     <biblList>
                        <bibl sameas="recordid_670925 " type="Rubrik_18">
                           <term label="Rubrik_18">Vorankündigung</term>
                           <genre>article</genre>
                           <genre>newspaper</genre>
                           <author/>
                           <title level="j">Vaterland</title>
                           <title level="j">Morgenblatt</title>
                           <editor/>
                           <biblScope unit="vol">Jg. 37</biblScope>
                           <biblScope unit="issue">Beiblatt zu Nr. 299</biblScope>
                           <biblScope unit="page">S. I</biblScope>
                           <imprint>
                              <date isodate="1896-10-30">30.10.1896</date>
                              <pubPlace/>
                              <publisher/>
                           </imprint>
                           <annot>
                              <p label="Weitere_Informationen">(Liederabend von Johannes Messchaert; u.a. 4 Lieder von "Brahm's": "Auf dem Kirchhofe; Wie Melodien zieht es; Am Sonntag Morgen; Regenlied")</p>
                              <p label="Vollständiger_Nachweis">Vaterland, Morgenblatt, Jg. 37, Beiblatt zu Nr. 299, 30.10.1896, S. I</p>
                           </annot>
                           <ptr label="ANNO-ÖNB" target="http://anno.onb.ac.at/cgi-content/anno?aid=vtl&amp;datum=18961030&amp;seite=9&amp;zoom=33&amp;query=%22brahm%27s%22&amp;ref=anno-search"/>
                           <relationList>
                              <relation rel="isRealizationOf" target="#component_op._105,Nr.1und4"/>
                           </relationList>
                           <relatedItem rel="host">
                              <bibl>
                                 <biblScope/>
                              </bibl>
                           </relatedItem>
                        </bibl>
                     </biblList>
                  </event>
                  <event> <!-- nicht nachvollziehbar wer genau die aufführende/n Person/en war/en -->
                     <persName type="Mitwirkende_r" corresp="../Brahms-Personenregister-ID/0424">Neuda, Rosa</persName>
                     <persName type="Sänger_in" corresp="../Brahms-Personenregister-ID/0391">Walter, Minna</persName>
                     <persName type="Pianist_in" corresp="#">Wienzkowska, Melanie</persName>
                     <persName type="Sänger_in" corresp="../Brahms-Personenregister-ID/0239">Schrötter, Fritz</persName>
                     <persName type="Sänger_in" corresp="../Brahms-Personenregister-ID/0208">Reichmann, Theodor</persName>
                     <persName type="Sänger_in" corresp="#">Demuth, Leopold</persName>
                     <date isodate="1889-03-28">28.03.1889</date>
                     <geogName role="place">Wien</geogName>
                     <geogName role="venue">Großer Musikvereinssaal</geogName>
                     <biblList>
                        <bibl sameas="recordid_668035 " type="Rubrik_80">
                           <term label="Rubrik_80">Vorankündigung</term>
                           <genre>article</genre>
                           <genre>newspaper</genre>
                           <author/>
                           <title level="j">Presse</title>
                           <title level="j">Local-Anzeiger</title>
                           <editor/>
                           <biblScope unit="vol">Jg. 42</biblScope>
                           <biblScope unit="issue">Nr. 83</biblScope>
                           <biblScope unit="page">S. 16</biblScope>
                           <imprint>
                              <date isodate="1889-03-24">24.03.1889</date>
                              <pubPlace/>
                              <publisher/>
                           </imprint>
                           <annot>
                              <p label="Weitere_Informationen">(1. außerordentliches Gesellschaftskonzert, 19.30 Uhr; Singverein, Hans Richter: Dirigent; vgl. <bibl type="bibl" target="#Perger-Hirschfeld_GdGdM_I">Perger/Hirschfeld, Geschichte der GdM</bibl>, I, S. 311)</p>
                              <p label="Vollständiger_Nachweis">Presse, Local-Anzeiger, Jg. 42, Nr. 83, 24.03.1889, S. 16</p>
                           </annot>
                           <ptr label="ANNO-ÖNB" target="http://anno.onb.ac.at/cgi-content/anno?aid=apr&amp;datum=18890324&amp;seite=16&amp;zoom=33&amp;query=%22brahms%22&amp;ref=anno-search"/>
                           <relationList>
                              <relation rel="isRealizationOf" target="#component_op._105,Nr.2"/>
                           </relationList>
                           <relatedItem rel="host">
                              <bibl>
                                 <title>vgl. Perger/Hirschfeld, Geschichte der GdM</title>
                                 <biblScope/>
                              </bibl>
                           </relatedItem>
                        </bibl>
                     </biblList>
                  </event>
                  <event>
                     <date isodate="1891-11-27">27.11.1891</date>
                     <geogName role="place">Wien</geogName>
                     <geogName role="venue">Großer Musikvereinssaal</geogName>
                     <persName type="Sänger_in" corresp="../Brahms-Personenregister-ID/0007">Barbi, Alice</persName>
                     <biblList>
                        <bibl sameas="recordid_668264 " type="Rubrik_18">
                           <term label="Rubrik_18">Vorankündigung</term>
                           <genre>article</genre>
                           <genre>newspaper</genre>
                           <author/>
                           <title level="j">Presse</title>
                           <title level="j">Local-Anzeiger</title>
                           <editor/>
                           <biblScope unit="vol">Jg. 44</biblScope>
                           <biblScope unit="issue">Nr. 321</biblScope>
                           <biblScope unit="page">S. 16</biblScope>
                           <imprint>
                              <date isodate="1891-11-22">22.11.1891</date>
                              <pubPlace/>
                              <publisher/>
                           </imprint>
                           <annot>
                              <p label="Weitere_Informationen">(Konzert der Kammersängerin Alice Barbi; u.a. 4 Lieder von Brahms: "Mädchenlied", "Immer leiser wird mein Schlummer", "Vor dem Fenster" "Liebe und Frühling")</p>
                              <p label="Vollständiger_Nachweis">Presse, Local-Anzeiger, Jg. 44, Nr. 321, 22.11.1891, S. 16</p>
                           </annot>
                           <ptr label="ANNO-ÖNB" target="http://anno.onb.ac.at/cgi-content/anno?aid=apr&amp;datum=18911122&amp;seite=16&amp;zoom=33&amp;query=%22brahms%22&amp;ref=anno-search"/>
                           <relationList>
                              <relation rel="isRealizationOf" target="#component_op._105,Nr.2"/>
                           </relationList>
                           <relatedItem rel="host">
                              <bibl>
                                 <biblScope/>
                              </bibl>
                           </relatedItem>
                        </bibl>
                     </biblList>
                  </event>
                  <event>
                     <persName type="Pianist_in" corresp="../Brahms-Personenregister-ID/0192">Paumgartner, Hans</persName>
                     <persName type="Sänger_in" corresp="../Brahms-Personenregister-ID/0208">Reichmann, Theodor</persName>
                     <date isodate="1891-11-25">25.11.1891</date>
                     <geogName role="place">Wien</geogName>
                     <geogName role="venue">Großer Musikvereinssaal</geogName>
                     <biblList>
                        <bibl sameas="recordid_668267 " type="Rubrik_18">
                           <term label="Rubrik_18">Vorankündigung</term>
                           <genre>article</genre>
                           <genre>newspaper</genre>
                           <author/>
                           <title level="j">Presse</title>
                           <title level="j">Local-Anzeiger</title>
                           <editor/>
                           <biblScope unit="vol">Jg. 44</biblScope>
                           <biblScope unit="issue">Nr. 321</biblScope>
                           <biblScope unit="page">S. 16</biblScope>
                           <imprint>
                              <date isodate="1891-11-22">22.11.1891</date>
                              <pubPlace/>
                              <publisher/>
                           </imprint>
                           <annot>
                              <p label="Weitere_Informationen">(Lieder- und Balladenabend von Kammersänger Reichmann)</p>
                              <p label="Vollständiger_Nachweis">Presse, Local-Anzeiger, Jg. 44, Nr. 321, 22.11.1891, S. 16</p>
                           </annot>
                           <ptr label="ANNO-ÖNB" target="http://anno.onb.ac.at/cgi-content/anno?aid=apr&amp;datum=18911122&amp;seite=16&amp;zoom=33&amp;query=%22brahms%22&amp;ref=anno-search"/>
                           <relationList>
                              <relation rel="isRealizationOf" target="#component_op._105,Nr.2"/>
                           </relationList>
                           <relatedItem rel="host">
                              <bibl>
                                 <biblScope/>
                              </bibl>
                           </relatedItem>
                        </bibl>
                        <bibl sameas="recordid_668269 " type="Rubrik_3">
                           <term label="Rubrik_3">Vorankündigung</term>
                           <genre>article</genre>
                           <genre>newspaper</genre>
                           <author/>
                           <title level="j">Presse</title>
                           <title level="j">Local-Anzeiger</title>
                           <editor/>
                           <biblScope unit="vol">Jg. 44</biblScope>
                           <biblScope unit="issue">Nr. 325</biblScope>
                           <biblScope unit="page">S. 11</biblScope>
                           <imprint>
                              <date isodate="1891-11-26">26.11.1891</date>
                              <pubPlace/>
                              <publisher/>
                           </imprint>
                           <annot>
                              <p label="Weitere_Informationen">(Konzert von Theodor Reichmann)</p>
                              <p label="Vollständiger_Nachweis">Presse, Local-Anzeiger, Jg. 44, Nr. 325, 26.11.1891, S. 11</p>
                           </annot>
                           <ptr label="ANNO-ÖNB" target="http://anno.onb.ac.at/cgi-content/anno?aid=apr&amp;datum=18911126&amp;seite=11&amp;zoom=33&amp;query=%22brahms%22&amp;ref=anno-search"/>
                           <relationList>
                              <relation rel="isRealizationOf" target="#component_op._105,Nr.2"/>
                           </relationList>
                           <relatedItem rel="host">
                              <bibl>
                                 <biblScope/>
                              </bibl>
                           </relatedItem>
                        </bibl>
                     </biblList>
                  </event>
                  <event>
                     <persName type="Pianist_in" corresp="../Brahms-Personenregister-ID/0031">Brahms, Johannes</persName>
                     <persName type="Sänger_in" corresp="../Brahms-Personenregister-ID/0457">Walter, Gustav</persName>
                     <date isodate="1891-12-15">15.12.1891</date>
                     <geogName role="place">Wien</geogName>
                     <geogName role="venue">Großer Musikvereinssaal</geogName>
                     <biblList>
                        <bibl sameas="recordid_668292 recordid_668293 " type="Rubrik_90 Rubrik_18">
                           <term label="Rubrik_90">Vorankündigung</term>
                           <term label="Rubrik_18">Vorankündigung</term>
                           <genre>article</genre>
                           <genre>newspaper</genre>
                           <author/>
                           <title level="j">Presse</title>
                           <title level="j">Local-Anzeiger</title>
                           <editor/>
                           <biblScope unit="vol">Jg. 44</biblScope>
                           <biblScope unit="issue">Nr. 337</biblScope>
                           <biblScope unit="page">S. 19</biblScope>
                           <imprint>
                              <date isodate="1891-12-08">08.12.1891</date>
                              <pubPlace/>
                              <publisher/>
                           </imprint>
                           <annot>
                              <p label="Weitere_Informationen">(Konzert zu Gunsten des Pensionsvereins des Konservatoriums, 19.30 Uhr; Schuberts "Sei mir gegrüßt", Brahms: op. 105, Nr. 1, op. 106, Nr. 1, op. 71, Nr. 5 sowie Rubinsteins "Gelb rollt mir zu Füßen"; Werke gemäß <bibl type="bibl" target="#HofmannChronologie">Hofmann, Chronologie</bibl>, S. 286 f.)</p>
                              <p label="Vollständiger_Nachweis">Presse, Local-Anzeiger, Jg. 44, Nr. 337, 08.12.1891, S. 19</p>
                           </annot>
                           <ptr label="ANNO-ÖNB" target="http://anno.onb.ac.at/cgi-content/anno?aid=apr&amp;datum=18911208&amp;seite=19&amp;zoom=33&amp;query=%22brahms%22&amp;ref=anno-search"/>
                           <relationList>
                              <relation rel="isRealizationOf" target="#component_op._105,Nr.1"/>
                           </relationList>
                           <relatedItem rel="host">
                              <bibl>
                                 <title>gemäß Hofmann, Chronologie</title>
                                 <biblScope/>
                              </bibl>
                           </relatedItem>
                        </bibl>
                        <bibl sameas="recordid_668305 recordid_668306 " type="Rubrik_90 Rubrik_18">
                           <term label="Rubrik_90">Vorankündigung</term>
                           <term label="Rubrik_18">Vorankündigung</term>
                           <genre>article</genre>
                           <genre>newspaper</genre>
                           <author/>
                           <title level="j">Presse</title>
                           <title level="j">Local-Anzeiger</title>
                           <editor/>
                           <biblScope unit="vol">Jg. 44</biblScope>
                           <biblScope unit="issue">Nr. 341</biblScope>
                           <biblScope unit="page">S. 11</biblScope>
                           <imprint>
                              <date isodate="1891-12-12">12.12.1891</date>
                              <pubPlace/>
                              <publisher/>
                           </imprint>
                           <annot>
                              <p label="Weitere_Informationen">(Konzert des Pensionsvereins des Konservatoriums, 19.30 Uhr; Werke gemeinsam mit Gustav Walter gemäß <bibl type="bibl" target="#HofmannChronologie">Hofmann, Chronologie</bibl>, S. 286 f.: Schuberts "Sei mir gegrüßt", Rubinsteins "Gelb rollt mir zu Füßen" sowie Brahms' op. 105, Nr. 1, op. 106, Nr. 1, op. 71, Nr. 5)</p>
                              <p label="Vollständiger_Nachweis">Presse, Local-Anzeiger, Jg. 44, Nr. 341, 12.12.1891, S. 11</p>
                           </annot>
                           <ptr label="ANNO-ÖNB" target="http://anno.onb.ac.at/cgi-content/anno?aid=apr&amp;datum=18911212&amp;seite=11&amp;zoom=33&amp;query=%22brahms%22&amp;ref=anno-search"/>
                           <relationList>
                              <relation rel="isRealizationOf" target="#component_op._105,Nr.1"/>
                           </relationList>
                           <relatedItem rel="host">
                              <bibl>
                                 <title>gemäß Hofmann, Chronologie</title>
                                 <biblScope/>
                              </bibl>
                           </relatedItem>
                        </bibl>
                        <bibl sameas="recordid_668309 recordid_668310 " type="Rubrik_80 Rubrik_90">
                           <term label="Rubrik_80">Vorankündigung</term>
                           <term label="Rubrik_90">Vorankündigung</term>
                           <genre>article</genre>
                           <genre>newspaper</genre>
                           <author/>
                           <title level="j">Presse</title>
                           <editor/>
                           <biblScope unit="vol">Jg. 44</biblScope>
                           <biblScope unit="issue">Nr. 342</biblScope>
                           <biblScope unit="page">S. 11</biblScope>
                           <imprint>
                              <date isodate="1891-12-13">13.12.1891</date>
                              <pubPlace/>
                              <publisher/>
                           </imprint>
                           <annot>
                              <p label="Weitere_Informationen">(Konzert des Pensionsvereins des Konservatoriums, 19.30 Uhr; vgl. <bibl type="bibl" target="#HofmannChronologie">Hofmann, Chronologie</bibl>, S. 286 f.)</p>
                              <p label="Vollständiger_Nachweis">Presse, Jg. 44, Nr. 342, 13.12.1891, S. 11</p>
                           </annot>
                           <ptr label="ANNO-ÖNB" target="http://anno.onb.ac.at/cgi-content/anno?aid=apr&amp;datum=18911213&amp;seite=11&amp;zoom=33&amp;query=%22brahms%22&amp;ref=anno-search"/>
                           <relationList>
                              <relation rel="isRealizationOf" target="#component_op._105,Nr.1"/>
                           </relationList>
                           <relatedItem rel="host">
                              <bibl>
                                 <title>vgl. Hofmann, Chronologie</title>
                                 <biblScope/>
                              </bibl>
                           </relatedItem>
                        </bibl>
                        <bibl sameas="recordid_668322 recordid_668323 " type="Rubrik_90 Rubrik_18">
                           <term label="Rubrik_90">Vorankündigung</term>
                           <term label="Rubrik_18">Vorankündigung</term>
                           <genre>article</genre>
                           <genre>newspaper</genre>
                           <author/>
                           <title level="j">Presse</title>
                           <title level="j">Local-Anzeiger</title>
                           <editor/>
                           <biblScope unit="vol">Jg. 44</biblScope>
                           <biblScope unit="issue">Nr. 342</biblScope>
                           <biblScope unit="page">S. 19</biblScope>
                           <imprint>
                              <date isodate="1891-12-13">13.12.1891</date>
                              <pubPlace/>
                              <publisher/>
                           </imprint>
                           <annot>
                              <p label="Weitere_Informationen">(Großes Konzert zugunsten des Pensionsvereins des Konservatoriums, abends; Werke gemäß <bibl type="bibl" target="#HofmannChronologie">Hofmann, Chronologie</bibl>, S. 286 f., gemeinsam mit Gustav Walter: Schuberts "Sei mir gegrüßt", Rubinsteins "Gelb rollt mir zu Füßen" sowie von Brahms op. 105, Nr. 1, op. 106, Nr. 1 und op. 71, Nr. 5)</p>
                              <p label="Vollständiger_Nachweis">Presse, Local-Anzeiger, Jg. 44, Nr. 342, 13.12.1891, S. 19</p>
                           </annot>
                           <ptr label="ANNO-ÖNB" target="http://anno.onb.ac.at/cgi-content/anno?aid=apr&amp;datum=18911213&amp;seite=19&amp;zoom=33&amp;query=%22brahms%22&amp;ref=anno-search"/>
                           <relationList>
                              <relation rel="isRealizationOf" target="#component_op._105,Nr.1"/>
                           </relationList>
                           <relatedItem rel="host">
                              <bibl>
                                 <title>gemäß Hofmann, Chronologie</title>
                                 <biblScope/>
                              </bibl>
                           </relatedItem>
                        </bibl>
                        <bibl sameas="recordid_668329 recordid_668330 " type="Rubrik_90 Rubrik_80">
                           <term label="Rubrik_90">Vorankündigung</term>
                           <term label="Rubrik_80">Vorankündigung</term>
                           <genre>article</genre>
                           <genre>newspaper</genre>
                           <author/>
                           <title level="j">Presse</title>
                           <title level="j">Local-Anzeiger</title>
                           <editor/>
                           <biblScope unit="vol">Jg. 44</biblScope>
                           <biblScope unit="issue">Nr. 344</biblScope>
                           <biblScope unit="page">S. 16</biblScope>
                           <imprint>
                              <date isodate="1891-12-15">15.12.1891</date>
                              <pubPlace/>
                              <publisher/>
                           </imprint>
                           <annot>
                              <p label="Weitere_Informationen">(Konzert des Pensionsvereins des Konservatoriums, 19.30 Uhr; Schuberts "Sei mir gegrüsst" sowie von Brahms op. 105, Nr. 1, op. 106, Nr. 1 und op. 71, Nr. 5; vgl. <bibl type="bibl" target="#HofmannChronologie">Hofmann, Chronologie</bibl>, S. 286 f.)</p>
                              <p label="Vollständiger_Nachweis">Presse, Local-Anzeiger, Jg. 44, Nr. 344, 15.12.1891, S. 16</p>
                           </annot>
                           <ptr label="ANNO-ÖNB" target="http://anno.onb.ac.at/cgi-content/anno?aid=apr&amp;datum=18911215&amp;seite=10&amp;zoom=33&amp;query=%22brahms%22&amp;ref=anno-search"/>
                           <relationList>
                              <relation rel="isRealizationOf" target="#component_op._105,Nr.1"/>
                           </relationList>
                           <relatedItem rel="host">
                              <bibl>
                                 <title>vgl. Hofmann, Chronologie</title>
                                 <biblScope/>
                              </bibl>
                           </relatedItem>
                        </bibl>
                        <bibl sameas="recordid_668341 recordid_668342 " type="Rubrik_9 Rubrik_3">
                           <term label="Rubrik_9">Brahms als Pianist</term>
                           <term label="Rubrik_3">Vorankündigung</term>
                           <genre>article</genre>
                           <genre>newspaper</genre>
                           <author/>
                           <title level="j">Presse</title>
                           <editor/>
                           <biblScope unit="vol">Jg. 44</biblScope>
                           <biblScope unit="issue">Nr. 348</biblScope>
                           <biblScope unit="page">S. [1]</biblScope>
                           <imprint>
                              <date isodate="1891-12-19">19.12.1891</date>
                              <pubPlace/>
                              <publisher/>
                           </imprint>
                           <annot>
                              <p label="Weitere_Informationen">(Großes Konzert des Pensionsvereins des Konservatoriums; Lieder von "Schubert, Brahms und Rubinstein"; Werke gemäß <bibl type="bibl" target="#HofmannChronologie">Hofmann, Chronologie</bibl>, S. 286 f.: Schuberts "Sei mir gegrüßt", Brahms' op. 105, Nr. 1, op. 106, Nr. 1, op. 71, Nr. 5 sowie Rubinsteins "Gelb rollt mir zu Füßen")</p>
                              <p label="Vollständiger_Nachweis">Presse, Jg. 44, Nr. 348, 19.12.1891, S. [1]</p>
                           </annot>
                           <ptr label="ANNO-ÖNB" target="http://anno.onb.ac.at/cgi-content/anno?aid=apr&amp;datum=18911219&amp;seite=1&amp;zoom=33&amp;query=%22brahms%22&amp;ref=anno-search"/>
                           <relationList>
                              <relation rel="isRealizationOf" target="#component_op._105,Nr.1"/>
                           </relationList>
                           <relatedItem rel="host">
                              <bibl>
                                 <title>gemäß Hofmann, Chronologie</title>
                                 <biblScope/>
                              </bibl>
                           </relatedItem>
                        </bibl>
                     </biblList>
                  </event>
                  <event>
                     <date isodate="1892-01-21">21.01.1892</date>
                     <geogName role="place">Wien</geogName>
                     <geogName role="venue">Saal Bösendorfer</geogName>
                     <persName type="Sänger_in" corresp="../Brahms-Personenregister-ID/0433">Nicklaß-Kempner, Selma</persName>
                     <biblList>
                        <bibl sameas="recordid_668374 " type="Rubrik_18">
                           <term label="Rubrik_18">Vorankündigung</term>
                           <genre>article</genre>
                           <genre>newspaper</genre>
                           <author/>
                           <title level="j">Presse</title>
                           <title level="j">Local-Anzeiger</title>
                           <editor/>
                           <biblScope unit="vol">Jg. 45</biblScope>
                           <biblScope unit="issue">Nr. 17</biblScope>
                           <biblScope unit="page">S. 15</biblScope>
                           <imprint>
                              <date isodate="1892-01-17">17.01.1892</date>
                              <pubPlace/>
                              <publisher/>
                           </imprint>
                           <annot>
                              <p label="Weitere_Informationen">(Liederabend von Selma Nicklaß-Kempner, 19.30 Uhr; u.a. 2 Lieder von Brahms: "Immer leiser wird mein Schlummer", "Ständchen")</p>
                              <p label="Vollständiger_Nachweis">Presse, Local-Anzeiger, Jg. 45, Nr. 17, 17.01.1892, S. 15</p>
                           </annot>
                           <ptr label="ANNO-ÖNB" target="http://anno.onb.ac.at/cgi-content/anno?aid=apr&amp;datum=18920117&amp;seite=9&amp;zoom=33&amp;query=%22brahms%22&amp;ref=anno-search"/>
                           <relationList>
                              <relation rel="isRealizationOf" target="#component_op._105,Nr.2"/>
                           </relationList>
                           <relatedItem rel="host">
                              <bibl>
                                 <biblScope/>
                              </bibl>
                           </relatedItem>
                        </bibl>
                     </biblList>
                  </event>
                  <event>
                     <date isodate="1893-02-16">16.02.1893</date>
                     <geogName role="place">Wien</geogName>
                     <geogName role="venue">Großer Musikvereinssaal</geogName>
                     <persName type="Sänger_in" corresp="../Brahms-Personenregister-ID/0208">Reichmann, Theodor</persName>
                     <biblList>
                        <bibl sameas="recordid_668559 " type="Rubrik_18">
                           <term label="Rubrik_18">Vorankündigung</term>
                           <genre>article</genre>
                           <genre>newspaper</genre>
                           <author/>
                           <title level="j">Presse</title>
                           <title level="j">Local-Anzeiger</title>
                           <editor/>
                           <biblScope unit="vol">Jg. 46</biblScope>
                           <biblScope unit="issue">Nr. 47</biblScope>
                           <biblScope unit="page">S. 11</biblScope>
                           <imprint>
                              <date isodate="1893-02-16">16.02.1893</date>
                              <pubPlace/>
                              <publisher/>
                           </imprint>
                           <annot>
                              <p label="Weitere_Informationen">(Konzert des Kammersängers Reichmann, 19.30 Uhr; u.a. 2 Brahms-Lieder: "Immer leiser wird mein Schlummer", "Von ewiger Liebe")</p>
                              <p label="Vollständiger_Nachweis">Presse, Local-Anzeiger, Jg. 46, Nr. 47, 16.02.1893, S. 11</p>
                           </annot>
                           <ptr label="ANNO-ÖNB" target="http://anno.onb.ac.at/cgi-content/anno?aid=apr&amp;datum=18930216&amp;seite=11&amp;zoom=33&amp;query=%22brahms%22&amp;ref=anno-search"/>
                           <relationList>
                              <relation rel="isRealizationOf" target="#component_op._105,Nr.2"/>
                           </relationList>
                           <relatedItem rel="host">
                              <bibl>
                                 <biblScope/>
                              </bibl>
                           </relatedItem>
                        </bibl>
                     </biblList>
                  </event>
                  <event>
                     <date isodate="1893-03-20">20.03.1893</date>
                     <geogName role="place">Wien</geogName>
                     <persName type="Sänger_in" corresp="../Brahms-Personenregister-ID/0098">Gura, Eugen</persName>
                     <persName type="Pianist_in" corresp="../Brahms-Personenregister-ID/0192">Paumgartner, Hans</persName>
                     <biblList>
                        <bibl sameas="recordid_668581 " type="Rubrik_18">
                           <term label="Rubrik_18">Vorankündigung</term>
                           <genre>article</genre>
                           <genre>newspaper</genre>
                           <author/>
                           <title level="j">Presse</title>
                           <title level="j">Local-Anzeiger</title>
                           <editor/>
                           <biblScope unit="vol">Jg. 46</biblScope>
                           <biblScope unit="issue">Nr. 76</biblScope>
                           <biblScope unit="page">S. 11</biblScope>
                           <imprint>
                              <date isodate="1893-03-17">17.03.1893</date>
                              <pubPlace/>
                              <publisher/>
                           </imprint>
                           <annot>
                              <p label="Weitere_Informationen">(Konzert des Kammersängers Eugen Gura; u.a. 3 Brahms-Lieder: "Mainacht", "Auf dem Kirchhof", "Verrath")</p>
                              <p label="Vollständiger_Nachweis">Presse, Local-Anzeiger, Jg. 46, Nr. 76, 17.03.1893, S. 11</p>
                           </annot>
                           <ptr label="ANNO-ÖNB" target="http://anno.onb.ac.at/cgi-content/anno?aid=apr&amp;datum=18930317&amp;seite=11&amp;zoom=33&amp;query=%22brahms%22&amp;ref=anno-search"/>
                           <relationList>
                              <relation rel="isRealizationOf" target="#component_op._105,Nr.4und5"/>
                           </relationList>
                           <relatedItem rel="host">
                              <bibl>
                                 <biblScope/>
                              </bibl>
                           </relatedItem>
                        </bibl>
                     </biblList>
                  </event>
                  <event>
                     <persName type="Pianist_in" corresp="../Brahms-Personenregister-ID/0192">Paumgartner, Hans</persName>
                     <persName type="Sänger_in" corresp="../Brahms-Personenregister-ID/0098">Gura, Eugen</persName>
                     <date startdate="1893" enddate="1893" cert="unknown">ca. März 1893</date>
                     <geogName role="place">Wien</geogName>
                     <biblList>
                        <bibl sameas="recordid_668587 " type="Rubrik_3">
                           <term label="Rubrik_3">Vorankündigung</term>
                           <genre>article</genre>
                           <genre>newspaper</genre>
                           <author/>
                           <title level="j">Presse</title>
                           <title level="j">Local-Anzeiger</title>
                           <editor/>
                           <biblScope unit="vol">Jg. 46</biblScope>
                           <biblScope unit="issue">Nr. 82</biblScope>
                           <biblScope unit="page">S. 11</biblScope>
                           <imprint>
                              <date isodate="1893-03-23">23.03.1893</date>
                              <pubPlace/>
                              <publisher/>
                           </imprint>
                           <annot>
                              <p label="Weitere_Informationen">(Lieder- und Balladenabende von Eugen Gura)</p>
                              <p label="Vollständiger_Nachweis">Presse, Local-Anzeiger, Jg. 46, Nr. 82, 23.03.1893, S. 11</p>
                           </annot>
                           <ptr label="ANNO-ÖNB" target="http://anno.onb.ac.at/cgi-content/anno?aid=apr&amp;datum=18930323&amp;seite=11&amp;zoom=33&amp;query=%22brahms%22&amp;ref=anno-search"/>
                           <relationList>
                              <relation rel="isRealizationOf" target="#component_op._105,Nr.4und5"/>
                           </relationList>
                           <relatedItem rel="host">
                              <bibl>
                                 <biblScope/>
                              </bibl>
                           </relatedItem>
                        </bibl>
                     </biblList>
                  </event>
                  <event>
                     <date/>
                     <geogName role="place"/>
                     <persName type="Komponist_in" corresp="../Brahms-Personenregister-ID/0031">Brahms, Johannes</persName>
                     <biblList>
                        <bibl sameas="recordid_668664 " type="Rubrik_1">
                           <term label="Rubrik_1">Werkkritik</term>
                           <genre>article</genre>
                           <genre>newspaper</genre>
                           <author/>
                           <title level="j">Presse</title>
                           <editor/>
                           <biblScope unit="vol">Jg. 46</biblScope>
                           <biblScope unit="issue">Nr. 331</biblScope>
                           <biblScope unit="page">S. 2</biblScope>
                           <imprint>
                              <date isodate="1893-11-30">30.11.1893</date>
                              <pubPlace/>
                              <publisher/>
                           </imprint>
                           <annot>
                              <p label="Weitere_Informationen">(Erwähnung im Rahmen einer Rezension von op. 100 anlässlich einer Aufführung durch das Böhmische Streichquartett vom 17.11.1893, wobei von der Sonate "vielfach bemerkt wurde", dass es eine Reminiszenz an op. 105, Nr. 1 enthalte, wogegen sich Hirschfeld verwahrt, da "doch nur umgekehrt jenes Lied, welches in opus 105 enthalten ist, als eine Erinnerung an die Sonate op. 100 gelten" dürfe.)</p>
                              <p label="Vollständiger_Nachweis">Presse, Jg. 46, Nr. 331, 30.11.1893, S. 2</p>
                           </annot>
                           <ptr label="ANNO-ÖNB" target="http://anno.onb.ac.at/cgi-content/anno?aid=apr&amp;datum=18931130&amp;seite=2&amp;zoom=33&amp;query=%22brahms%22&amp;ref=anno-search"/>
                           <relationList>
                              <relation rel="isRealizationOf" target="#component_op._105,Nr.1"/>
                           </relationList>
                           <relatedItem rel="host">
                              <bibl>
                                 <biblScope/>
                              </bibl>
                           </relatedItem>
                        </bibl>
                     </biblList>
                  </event>
                  <event>
                     <persName type="Sänger_in" corresp="../Brahms-Personenregister-ID/0208">Reichmann, Theodor</persName>
                     <date isodate="1894-01-24">24.01.1894</date>
                     <geogName role="place">Wien</geogName>
                     <geogName role="venue">Musikvereinssaal</geogName>
                     <biblList>
                        <bibl sameas="recordid_668743 " type="Rubrik_3">
                           <term label="Rubrik_3">Vorankündigung</term>
                           <genre>article</genre>
                           <genre>newspaper</genre>
                           <author/>
                           <title level="j">Presse</title>
                           <title level="j">Local-Anzeiger</title>
                           <editor/>
                           <biblScope unit="vol">Jg. 47</biblScope>
                           <biblScope unit="issue">Nr. 23</biblScope>
                           <biblScope unit="page">S. [9]</biblScope>
                           <imprint>
                              <date isodate="1894-01-25">25.01.1894</date>
                              <pubPlace/>
                              <publisher/>
                           </imprint>
                           <annot>
                              <p label="Weitere_Informationen">(Festkonzert des Weißen Kreuzes, 21.00 Uhr)</p>
                              <p label="Vollständiger_Nachweis">Presse, Local-Anzeiger, Jg. 47, Nr. 23, 25.01.1894, S. [9]</p>
                           </annot>
                           <ptr label="ANNO-ÖNB" target="http://anno.onb.ac.at/cgi-content/anno?aid=apr&amp;datum=18940125&amp;seite=9&amp;zoom=33&amp;query=%22brahms%22&amp;ref=anno-search"/>
                           <relationList>
                              <relation rel="isRealizationOf" target="#component_op._105,Nr.2"/>
                           </relationList>
                           <relatedItem rel="host">
                              <bibl>
                                 <biblScope/>
                              </bibl>
                           </relatedItem>
                        </bibl>
                     </biblList>
                  </event>
                  <event>
                     <date isodate="1894-02-14">14.02.1894</date>
                     <geogName role="place">Wien</geogName>
                     <persName type="Sänger_in" corresp="../Brahms-Personenregister-ID/0251">Sistermans, Anton</persName>
                     <biblList>
                        <bibl sameas="recordid_668756 " type="Rubrik_18">
                           <term label="Rubrik_18">Vorankündigung</term>
                           <genre>article</genre>
                           <genre>newspaper</genre>
                           <author/>
                           <title level="j">Presse</title>
                           <title level="j">Local-Anzeiger</title>
                           <editor/>
                           <biblScope unit="vol">Jg. 47</biblScope>
                           <biblScope unit="issue">Nr. 39</biblScope>
                           <biblScope unit="page">S. 11</biblScope>
                           <imprint>
                              <date isodate="1894-02-10">10.02.1894</date>
                              <pubPlace/>
                              <publisher/>
                           </imprint>
                           <annot>
                              <p label="Weitere_Informationen">(Liederabend von Anton Sistermans; u.a. 5 Brahms-Lieder: "Auf dem Kirchhofe", "Verrath", "Feldeinsamkeit", "Sonntag", "Minnelied")</p>
                              <p label="Vollständiger_Nachweis">Presse, Local-Anzeiger, Jg. 47, Nr. 39, 10.02.1894, S. 11</p>
                           </annot>
                           <ptr label="ANNO-ÖNB" target="http://anno.onb.ac.at/cgi-content/anno?aid=apr&amp;datum=18940210&amp;seite=11&amp;zoom=33&amp;query=%22brahms%22&amp;ref=anno-search"/>
                           <relationList>
                              <relation rel="isRealizationOf" target="#component_op._105,Nr.4und5"/>
                           </relationList>
                           <relatedItem rel="host">
                              <bibl>
                                 <biblScope/>
                              </bibl>
                           </relatedItem>
                        </bibl>
                     </biblList>
                  </event>
               </eventList>
            </history>
         <perfMedium>
            <perfResList>
               <head>Besetzung: 1 Singstimme (tiefere Stimme) und Klavier</head>
               <perfResList>
                  <perfRes>1 Singstimme (tiefere Stimme)</perfRes>
                  <perfRes>Klavier</perfRes>
               </perfResList>
            </perfResList>
         </perfMedium>
         <notesStmt/>
         <expressionList/>
         <componentList>
            <work n="1" xml:id="component_op._105,Nr.1">
               <identifier label="Opus-Nummer">op. 105, Nr.1</identifier>
               <title>Wie Melodien zieht es mir.</title>
               <relationList>
                  <relation rel="isPartof" target="#work_op._105"/>
               </relationList>
            </work>
            <work n="2" xml:id="component_op._105,Nr.2">
               <identifier label="Opus-Nummer">op. 105, Nr.2</identifier>
               <title>Immer leiser wird mein Schlummer.</title>
               <relationList>
                  <relation rel="isPartof" target="#work_op._105"/>
               </relationList>
            </work>
            <work n="3" xml:id="component_op._105,Nr.3">
               <identifier label="Opus-Nummer">op. 105, Nr.3</identifier>
               <title>Klage.</title>
               <relationList>
                  <relation rel="isPartof" target="#work_op._105"/>
               </relationList>
            </work>
            <work n="4" xml:id="component_op._105,Nr.4">
               <identifier label="Opus-Nummer">op. 105, Nr.4</identifier>
               <title>Auf dem Kirchhofe.</title>
               <relationList>
                  <relation rel="isPartof" target="#work_op._105"/>
               </relationList>
            </work>
            <work n="5" xml:id="component_op._105,Nr.5">
               <identifier label="Opus-Nummer">op. 105, Nr.5</identifier>
               <title>Verrat.</title>
               <relationList>
                  <relation rel="isPartof" target="#work_op._105"/>
               </relationList>
            </work>
         </componentList>
      </work>
   </workList>
</mei>
