{"stem":"07.08","instances":[{"docId":"Personenregister-verkuerzt","docUri":"Personenregister-verkuerzt.html","score":2,"contexts":[{"form":"07.08","weight":"1","pos":95,"context":"(18.06.1843-<mark>07.08<\/mark>.1913)","fid":"registerTable"},{"form":"07.08","weight":"1","pos":101,"context":"(<mark>07.08<\/mark>.1832-02.03.1926)","fid":"registerTable"}]},{"docId":"Epstein-Julius-d1e2267","docUri":"Epstein-Julius-d1e2267.html","score":1,"contexts":[{"form":"07.08","weight":"1","pos":41,"context":"<mark>07.08<\/mark>.1832","fid":"page"}]},{"docId":"Popper-David-d1e6323","docUri":"Popper-David-d1e6323.html","score":1,"contexts":[{"form":"07.08","weight":"1","pos":46,"context":"<mark>07.08<\/mark>.1913","fid":"page"}]}]}