{"stem":"16.03","instances":[{"docId":"JBWV_0008_op8_Klaviertrio-Nr1-H-Dur","docUri":"JBWV_0008_op8_Klaviertrio-Nr1-H-Dur.html","score":1,"contexts":[{"form":"16.03","weight":"1","pos":99,"context":" Richard Epstein <mark>16.03<\/mark>.1898 Wien Saal Bösendorfer             ","fid":"event_d5e286"}]},{"docId":"JBWV_0050_op49_Fuenf-Lieder","docUri":"JBWV_0050_op49_Fuenf-Lieder.html","score":1,"contexts":[{"form":"16.03","weight":"1","pos":516,"context":"performances <mark>16.03<\/mark>.1896 Wien Saal Bösendorfer                       ","fid":"event_d8e1097"}]}]}