{"stem":"17.04","instances":[{"docId":"JBWV_0050_op49_Fuenf-Lieder","docUri":"JBWV_0050_op49_Fuenf-Lieder.html","score":2,"contexts":[{"form":"17.04","weight":"1","pos":1125,"context":" <mark>17.04<\/mark>.1874 ","fid":"recordid_666713"},{"form":"17.04","weight":"1","pos":1141,"context":"Presse, Jg. 27, Nr. 105, <mark>17.04<\/mark>.1874, S. [1]","fid":"recordid_666713"}]},{"docId":"work_op49_history_event_d6e2069_recordid_666713","docUri":"work_op49_history_event_d6e2069_recordid_666713.html","score":1,"contexts":[{"form":"17.04","weight":"1","pos":61,"context":"Presse, Jg. 27, Nr. 105, <mark>17.04<\/mark>.1874, S. [1]  ","fid":"page"}]}]}