{"stem":"19.07","instances":[{"docId":"JBWV_0050_op49_Fuenf-Lieder","docUri":"JBWV_0050_op49_Fuenf-Lieder.html","score":5,"contexts":[{"form":"19.07","weight":"1","pos":172,"context":" <mark>19.07<\/mark>.1892 Wien                                                                 ","fid":"work_op49"},{"form":"19.07","weight":"1","pos":180,"context":" <mark>19.07<\/mark>.1892 ","fid":"recordid_669971"},{"form":"19.07","weight":"1","pos":205,"context":"Vaterland, Jg. 33, Nr. 199, <mark>19.07<\/mark>.1892, S. 4","fid":"d8e509"},{"form":"19.07","weight":"1","pos":256,"context":" <mark>19.07<\/mark>.1892 ","fid":"recordid_668463"},{"form":"19.07","weight":"1","pos":282,"context":"...Local-Anzeiger, Jg. 45, Nr. 199, <mark>19.07<\/mark>.1892, S. 10","fid":"d8e642"}]},{"docId":"JBWV_0032_op32_Neun-Lieder-und-Gesaenge","docUri":"JBWV_0032_op32_Neun-Lieder-und-Gesaenge.html","score":1,"contexts":[{"form":"19.07","weight":"1","pos":829,"context":" Luise Dustmann <mark>19.07<\/mark>.1877 Salzburg                 ","fid":"work_op32"}]}]}