{"stem":"193","instances":[{"docId":"JBWV_0046_op45_Ein-deutsches-Requiem-recordid_667305--72","docUri":"JBWV_0046_op45_Ein-deutsches-Requiem-recordid_667305--72.html","score":0.07601258614441064,"contexts":[{"form":"193","weight":"1","pos":22,"context":"...-Anzeiger, Jg. 35, Nr. <mark>193<\/mark>, 15.07.1882, S. 10 f. Rubrik..."}]},{"docId":"JBWV_0102_op97_Sechs-Lieder-recordid_667846--28","docUri":"JBWV_0102_op97_Sechs-Lieder-recordid_667846--28.html","score":0.05429470438886473,"contexts":[{"form":"193","weight":"1","pos":21,"context":"...-Anzeiger, Jg. 40, Nr. <mark>193<\/mark>, 15.07.1887, S. 10 Rubrik(en)..."}]},{"docId":"JBWV_0086_op82_Naenie-(von-Friedrich-Schiller)-recordid_667303--13","docUri":"JBWV_0086_op82_Naenie-(von-Friedrich-Schiller)-recordid_667303--13.html","score":0.08001324857306383,"contexts":[{"form":"193","weight":"1","pos":27,"context":"...-Anzeiger, Jg. 35, Nr. <mark>193<\/mark>, 15.07.1882, S. 10 f. Rubrik..."}]},{"docId":"JBWV_0088_op84_Fuenf-Romanzen-und-Lieder-recordid_667845--31","docUri":"JBWV_0088_op84_Fuenf-Romanzen-und-Lieder-recordid_667845--31.html","score":0.05429470438886473,"contexts":[{"form":"193","weight":"1","pos":21,"context":"...-Anzeiger, Jg. 40, Nr. <mark>193<\/mark>, 15.07.1887, S. 10 Rubrik(en)..."}]}]}