{"stem":"21.12","instances":[{"docId":"JBWV_0032_op32_Neun-Lieder-und-Gesaenge","docUri":"JBWV_0032_op32_Neun-Lieder-und-Gesaenge.html","score":2,"contexts":[{"form":"21.12","weight":"1","pos":45,"context":"<mark>21.12<\/mark>.1867","fid":"workTable"},{"form":"21.12","weight":"1","pos":49,"context":"<mark>21.12<\/mark>.1867","fid":"workTable"}]},{"docId":"Neun-Lieder-und-Ges%C3%A4nge-recordid_669351","docUri":"Neun-Lieder-und-Ges%C3%A4nge-recordid_669351.html","score":1,"contexts":[{"form":"21.12","weight":"1","pos":10,"context":"<mark>21.12<\/mark>.1867","fid":"workTableDetail"}]},{"docId":"Neun-Lieder-und-Ges%C3%A4nge-recordid_669355","docUri":"Neun-Lieder-und-Ges%C3%A4nge-recordid_669355.html","score":1,"contexts":[{"form":"21.12","weight":"1","pos":10,"context":"<mark>21.12<\/mark>.1867","fid":"workTableDetail"}]}]}