{"stem":"341","instances":[{"docId":"JBWV_0008_op8_Klaviertrio-Nr1-H-Dur","docUri":"JBWV_0008_op8_Klaviertrio-Nr1-H-Dur.html","score":6,"contexts":[{"form":"341","weight":"1","pos":437,"context":"issue: Beiblatt zu Nr. <mark>341<\/mark>","fid":"recordid_669481"},{"form":"341","weight":"1","pos":459,"context":"Vaterland, Jg. 17, Beiblatt zu Nr. <mark>341<\/mark>, 10.12.1876, S. [2]","fid":"d5e1028"},{"form":"341","weight":"1","pos":469,"context":"issue: Nr. <mark>341<\/mark>","fid":"recordid_666927"},{"form":"341","weight":"1","pos":491,"context":"...Presse, Local-Anzeiger, Jg. 29, Nr. <mark>341<\/mark>, 10.12.1876, S. 8","fid":"d5e1096"},{"form":"341","weight":"1","pos":1127,"context":"issue: Nr. <mark>341<\/mark>","fid":"recordid_670557"},{"form":"341","weight":"1","pos":1145,"context":"Vaterland, Morgenblatt, Jg. 39, Nr. <mark>341<\/mark>, 11.12.1898, S. 10","fid":"d5e2472"}]},{"docId":"JBWV_0032_op32_Neun-Lieder-und-Gesaenge","docUri":"JBWV_0032_op32_Neun-Lieder-und-Gesaenge.html","score":2,"contexts":[{"form":"341","weight":"1","pos":183,"context":"issue: Nr. <mark>341<\/mark>","fid":"recordid_666987"},{"form":"341","weight":"1","pos":214,"context":"...Presse, Local-Anzeiger, Jg. 30, Nr. <mark>341<\/mark>, 12.12.1877, S. [9]","fid":"d6e469"}]},{"docId":"JBWV_0040_op39_Walzer","docUri":"JBWV_0040_op39_Walzer.html","score":2,"contexts":[{"form":"341","weight":"1","pos":16,"context":"issue: Nr. <mark>341<\/mark>","fid":"recordid_666989"},{"form":"341","weight":"1","pos":45,"context":"...Presse, Local-Anzeiger, Jg. 30, Nr. <mark>341<\/mark>, 12.12.1877, S. [9]","fid":"d7e127"}]}]}