{"stem":"ausstellung","instances":[{"docId":"JBWV_0148_WoO21_Mondnacht-recordid_668446--1","docUri":"JBWV_0148_WoO21_Mondnacht-recordid_668446--1.html","score":0.05351988059578853,"contexts":[{"form":"Ausstellung","weight":"1","pos":42,"context":"...im \"Wiener Componisten-Album\" zur Feier der Internationalen <mark>Ausstellung<\/mark> für Musik- und Theaterwesen; siehe ÖNB-..."}]},{"docId":"JBWV_0028_op28_Vier-Duette-recordid_668453-recordid_668454-recordid_668455--9","docUri":"JBWV_0028_op28_Vier-Duette-recordid_668453-recordid_668454-recordid_668455--9.html","score":0.05351988059578853,"contexts":[{"form":"Ausstellung","weight":"1","pos":42,"context":"...eine offizielle Publikation der Musik- und Theater-<mark>Ausstellung<\/mark>; vgl. BrahmsWV, S. 97"}]},{"docId":"JBWV_0028_op28_Vier-Duette-recordid_668450--7","docUri":"JBWV_0028_op28_Vier-Duette-recordid_668450--7.html","score":0.05660756601477633,"contexts":[{"form":"Ausstellung","weight":"1","pos":38,"context":"...im Rahmen der Internationalen Musik- und Theater-<mark>Ausstellung<\/mark> herausgegebene \"Album der Wiener Meister\" enthalte eine Reihe von..."}]},{"docId":"JBWV_0028_op28_Vier-Duette-recordid_669947--1","docUri":"JBWV_0028_op28_Vier-Duette-recordid_669947--1.html","score":0.07955657926400998,"contexts":[{"form":"Ausstellung","weight":"1","pos":33,"context":"...als Publikation der Internationalen Musik- und Theater-<mark>Ausstellung<\/mark> 1892, \"welches Compositionen von Brahms\" u.a. enthalte;..."}]},{"docId":"JBWV_0028_op28_Vier-Duette-recordid_668435--5","docUri":"JBWV_0028_op28_Vier-Duette-recordid_668435--5.html","score":0.06689985074473566,"contexts":[{"form":"Ausstellung","weight":"1","pos":35,"context":"...der Ausstellungskommission der Internationalen Musik- und Theater-<mark>Ausstellung<\/mark> herausgegebene \"Album der Wiener Meister\" werde u.a. Brahms' \"Es..."}]}]}