{"stem":"blumen","instances":[{"docId":"JBWV_0066_op63_Neun-Lieder-und-Gesaenge-recordid_670251--11","docUri":"JBWV_0066_op63_Neun-Lieder-und-Gesaenge-recordid_670251--11.html","score":0.18679812497971218,"contexts":[{"form":"Blumen","weight":"1","pos":39,"context":"...doch den Weg zurück\", \"Ich sah als Kind einst <mark>Blumen<\/mark> steh'n\" [recte: \"Ich sah als Knabe Blumen..."},{"form":"Blumen","weight":"1","pos":43,"context":"...Blumen steh'n\" [recte: \"Ich sah als Knabe <mark>Blumen<\/mark> blühn\"]"}]}]}