{"stem":"brüll","instances":[{"docId":"JBWV_0008_op8_Klaviertrio-Nr1-H-Dur","docUri":"JBWV_0008_op8_Klaviertrio-Nr1-H-Dur.html","score":3,"contexts":[{"form":"Brüll","weight":"1","pos":35,"context":" Ignaz <mark>Brüll<\/mark> 15.12.1896 Wien                                 ","fid":"work_op8"},{"form":"Brüll","weight":"1","pos":54,"context":"...Kammermusikabend des Rosé-Quartetts; Mitglieder des Rosé-Quartetts, Ignaz <mark>Brüll<\/mark>: Klavier)","fid":"d5e197"},{"form":"Brüll","weight":"1","pos":78,"context":"(3. Kammermusikabend des Rosé-Quartetts unter Mitwirkung von Ignaz <mark>Brüll<\/mark>)","fid":"d5e261"}]}]}