{"stem":"eduard","instances":[{"docId":"JBWV_0050_op49_Fuenf-Lieder-recordid_670263--17","docUri":"JBWV_0050_op49_Fuenf-Lieder-recordid_670263--17.html","score":0.09296991572527463,"contexts":[{"form":"Eduard","weight":"1","pos":9,"context":"<mark>Eduard<\/mark> Kremser (musikalische_r_Direktor_in)"},{"form":"Eduard","weight":"1","pos":36,"context":"Volkskonzert des Wiener Männergesangvereins unter der Leitung von <mark>Eduard<\/mark> Kremser, großer Musikvereinssaal; des Weiteren \"vier Brahms'sche..."}]},{"docId":"JBWV_0050_op49_Fuenf-Lieder-recordid_670821--25","docUri":"JBWV_0050_op49_Fuenf-Lieder-recordid_670821--25.html","score":0.08240515257467525,"contexts":[{"form":"Eduard","weight":"1","pos":7,"context":"<mark>Eduard<\/mark> Kremser (musikalische_r_Direktor_in)"},{"form":"Eduard","weight":"1","pos":46,"context":"...u.a. mit dem Wiener Männergesangverein unter der Leitung von <mark>Eduard<\/mark> Kremser; u.a. \"'Wiegenlied' von Brahms\""}]},{"docId":"JBWV_0050_op49_Fuenf-Lieder-recordid_669169--18","docUri":"JBWV_0050_op49_Fuenf-Lieder-recordid_669169--18.html","score":0.054936768383116834,"contexts":[{"form":"Eduard","weight":"1","pos":9,"context":"<mark>Eduard<\/mark> Kremser (musikalische_r_Direktor_in)"}]},{"docId":"JBWV_0050_op49_Fuenf-Lieder-recordid_668700--36","docUri":"JBWV_0050_op49_Fuenf-Lieder-recordid_668700--36.html","score":0.03357246956746029,"contexts":[{"form":"Eduard","weight":"1","pos":9,"context":"<mark>Eduard<\/mark> Kremser (musikalische_r_Direktor_in)"}]},{"docId":"JBWV_0007_op7_Sechs-Ges%C3%A4nge-recordid_667758--21","docUri":"JBWV_0007_op7_Sechs-Ges%C3%A4nge-recordid_667758--21.html","score":0.04216077573588036,"contexts":[{"form":"Eduard","weight":"1","pos":17,"context":"Schütt, <mark>Eduard<\/mark> (Mitwirkende_r)"}]}]}