{"stem":"geisler","instances":[{"docId":"0088","docUri":"0088.html","score":8,"contexts":[{"form":"Geisler","weight":"1","pos":10,"context":"<mark>Geisler<\/mark>-Schubert, Caroline","fid":"page"},{"form":"Geisler","weight":"1","pos":15,"context":"<mark>Geisler<\/mark>-Schubert","fid":"registerTableDetail"},{"form":"Geisler","weight":"1","pos":22,"context":"<mark>Geisler<\/mark>-Schubert, Karoline","fid":"registerTableDetail"},{"form":"Geisler","weight":"1","pos":26,"context":"<mark>Geisler<\/mark>-Schubert, Carolina","fid":"registerTableDetail"},{"form":"Geisler","weight":"1","pos":30,"context":"<mark>Geisler<\/mark>-Schubert, Carola","fid":"registerTableDetail"},{"form":"Geisler","weight":"1","pos":33,"context":"<mark>Geisler<\/mark>, Karoline (Theresa, Theresia)","fid":"registerTableDetail"},{"form":"Geisler","weight":"1","pos":37,"context":"<mark>Geisler<\/mark>, Carolina","fid":"registerTableDetail"},{"form":"Geisler","weight":"1","pos":39,"context":"<mark>Geisler<\/mark>, Carola","fid":"registerTableDetail"}]},{"docId":"Personenregister-verkuerzt","docUri":"Personenregister-verkuerzt.html","score":1,"contexts":[{"form":"Geisler","weight":"1","pos":233,"context":"<mark>Geisler<\/mark>-Schubert, Caroline","fid":"registerTable"}]}]}