{"stem":"geschicht","instances":[{"docId":"work_op49","docUri":"work_op49.html","score":2,"contexts":[{"form":"Geschichte","weight":"2","pos":29,"context":"Eintr채ge zu Bibliographien (<mark>Geschichte<\/mark>)","fid":"page"}]},{"docId":"work_op39","docUri":"work_op39.html","score":2,"contexts":[{"form":"Geschichte","weight":"2","pos":29,"context":"Eintr채ge zu Bibliographien (<mark>Geschichte<\/mark>)","fid":"page"}]},{"docId":"work_op32","docUri":"work_op32.html","score":2,"contexts":[{"form":"Geschichte","weight":"2","pos":29,"context":"Eintr채ge zu Bibliographien (<mark>Geschichte<\/mark>)","fid":"page"}]},{"docId":"work_op8","docUri":"work_op8.html","score":2,"contexts":[{"form":"Geschichte","weight":"2","pos":29,"context":"Eintr채ge zu Bibliographien (<mark>Geschichte<\/mark>)","fid":"page"}]}]}