{"stem":"hausmann","instances":[{"docId":"JBWV_0008_op8_Klaviertrio-Nr1-H-Dur-recordid_670834--36","docUri":"JBWV_0008_op8_Klaviertrio-Nr1-H-Dur-recordid_670834--36.html","score":0.10784650562511675,"contexts":[{"form":"Hausmann","weight":"1","pos":16,"context":"Robert <mark>Hausmann<\/mark> (Violoncellist_in)"},{"form":"Hausmann","weight":"1","pos":54,"context":"...: Violine, Marie Baumayer: Klavier, Robert <mark>Hausmann<\/mark>: Violoncello; \"neue Bearbeitung\""}]},{"docId":"JBWV_0002_op2_Klaviersonate-Nr2-fis-Moll-recordid_667963--5","docUri":"JBWV_0002_op2_Klaviersonate-Nr2-fis-Moll-recordid_667963--5.html","score":0.0650250989798498,"contexts":[{"form":"Hausmann","weight":"1","pos":8,"context":"<mark>Hausmann<\/mark>, Richard (Pianist_in)"}]}]}