{"stem":"helpdesk","instances":[{"docId":"about","docUri":"about.html","score":3,"contexts":[{"form":"HELPDESK","weight":"2","pos":72,"context":"<mark>HELPDESK<\/mark>","fid":"footer-full-content"},{"form":"helpdesk","weight":"1","pos":76,"context":"ACDH-CH runs a <mark>helpdesk<\/mark> offering advice for questions related to various digital humanities...","fid":"footer-full-content"}]},{"docId":"f_001","docUri":"f_001.html","score":3,"contexts":[{"form":"HELPDESK","weight":"2","pos":74,"context":"<mark>HELPDESK<\/mark>","fid":"footer-full-content"},{"form":"helpdesk","weight":"1","pos":78,"context":"ACDH-CH runs a <mark>helpdesk<\/mark> offering advice for questions related to various digital humanities...","fid":"footer-full-content"}]},{"docId":"index","docUri":"index.html","score":3,"contexts":[{"form":"HELPDESK","weight":"2","pos":141,"context":"<mark>HELPDESK<\/mark>","fid":"footer-full-content"},{"form":"helpdesk","weight":"1","pos":145,"context":"ACDH-CH runs a <mark>helpdesk<\/mark> offering advice for questions related to various digital humanities...","fid":"footer-full-content"}]},{"docId":"search","docUri":"search.html","score":3,"contexts":[{"form":"HELPDESK","weight":"2","pos":69,"context":"<mark>HELPDESK<\/mark>","fid":"footer-full-content"},{"form":"helpdesk","weight":"1","pos":73,"context":"ACDH-CH runs a <mark>helpdesk<\/mark> offering advice for questions related to various digital humanities...","fid":"footer-full-content"}]},{"docId":"f_002","docUri":"f_002.html","score":3,"contexts":[{"form":"HELPDESK","weight":"2","pos":74,"context":"<mark>HELPDESK<\/mark>","fid":"footer-full-content"},{"form":"helpdesk","weight":"1","pos":78,"context":"ACDH-CH runs a <mark>helpdesk<\/mark> offering advice for questions related to various digital humanities...","fid":"footer-full-content"}]},{"docId":"toc","docUri":"toc.html","score":3,"contexts":[{"form":"HELPDESK","weight":"2","pos":82,"context":"<mark>HELPDESK<\/mark>","fid":"footer-full-content"},{"form":"helpdesk","weight":"1","pos":86,"context":"ACDH-CH runs a <mark>helpdesk<\/mark> offering advice for questions related to various digital humanities...","fid":"footer-full-content"}]},{"docId":"imprint","docUri":"imprint.html","score":3,"contexts":[{"form":"HELPDESK","weight":"2","pos":696,"context":"<mark>HELPDESK<\/mark>","fid":"footer-full-content"},{"form":"helpdesk","weight":"1","pos":700,"context":"ACDH-CH runs a <mark>helpdesk<\/mark> offering advice for questions related to various digital humanities...","fid":"footer-full-content"}]}]}