{"stem":"joseph","instances":[{"docId":"personenregister-id-0109","docUri":"personenregister-id-0109.html","score":0.29894498472660685,"contexts":[{"form":"Joseph","weight":"1","pos":4,"context":"<mark>Joseph<\/mark>"},{"form":"Joseph","weight":"1","pos":8,"context":"Hellmesberger, <mark>Joseph<\/mark> d. J."},{"form":"Joseph","weight":"1","pos":10,"context":"Hellmesberger, <mark>Joseph<\/mark>"},{"form":"Joseph","weight":"1","pos":19,"context":"Helmesberger, <mark>Joseph<\/mark> jun."},{"form":"Joseph","weight":"1","pos":22,"context":"Helmesberger, <mark>Joseph<\/mark> d. J."}]},{"docId":"personenregister-id-0110","docUri":"personenregister-id-0110.html","score":0.2587023906287944,"contexts":[{"form":"Joseph","weight":"1","pos":4,"context":"<mark>Joseph<\/mark>"},{"form":"Joseph","weight":"1","pos":8,"context":"Hellmesberger, <mark>Joseph<\/mark> d. Ä."},{"form":"Joseph","weight":"1","pos":10,"context":"Hellmesberger, <mark>Joseph<\/mark>"},{"form":"Joseph","weight":"1","pos":19,"context":"Helmesberger, <mark>Joseph<\/mark> sen."},{"form":"Joseph","weight":"1","pos":22,"context":"Helmesberger, <mark>Joseph<\/mark> d. Ä."}]},{"docId":"JBWV_0050_op49_Fuenf-Lieder-recordid_669586--2","docUri":"JBWV_0050_op49_Fuenf-Lieder-recordid_669586--2.html","score":0.09608945937640935,"contexts":[{"form":"Joseph","weight":"1","pos":9,"context":"<mark>Joseph<\/mark> Waldner (Sänger_in)"},{"form":"Joseph","weight":"1","pos":31,"context":"Orgelkonzert von <mark>Joseph<\/mark> Labor, abends, großer Musikvereinssaal; Joseph Waldner..."},{"form":"Joseph","weight":"1","pos":35,"context":"...von Joseph Labor, abends, großer Musikvereinssaal; <mark>Joseph<\/mark> Waldner: Gesang; \"ein Wiegenlied von Brahms mit..."}]},{"docId":"personenregister-id-0114","docUri":"personenregister-id-0114.html","score":0.08304027353516857,"contexts":[{"form":"Joseph","weight":"1","pos":6,"context":"Richard Franz <mark>Joseph<\/mark>"},{"form":"Joseph","weight":"1","pos":16,"context":"Heuberger, Richard Franz <mark>Joseph<\/mark>"}]},{"docId":"personenregister-id-0229","docUri":"personenregister-id-0229.html","score":0.08007454948034112,"contexts":[{"form":"Joseph","weight":"1","pos":8,"context":"Schantl, <mark>Joseph<\/mark>"},{"form":"Joseph","weight":"1","pos":12,"context":"Schandl, <mark>Joseph<\/mark>"}]},{"docId":"JBWV_0008_op8_Klaviertrio-Nr1-H-Dur-recordid_668256--25","docUri":"JBWV_0008_op8_Klaviertrio-Nr1-H-Dur-recordid_668256--25.html","score":0.025478265743744906,"contexts":[{"form":"Joseph","weight":"1","pos":12,"context":"<mark>Joseph<\/mark> Hellmesberger jun. (Violinist_in)"}]},{"docId":"JBWV_0008_op8_Klaviertrio-Nr1-H-Dur-recordid_669910--24","docUri":"JBWV_0008_op8_Klaviertrio-Nr1-H-Dur-recordid_669910--24.html","score":0.028744710069866043,"contexts":[{"form":"Joseph","weight":"1","pos":12,"context":"<mark>Joseph<\/mark> Hellmesberger jun. (Violinist_in)"}]},{"docId":"JBWV_0050_op49_Fuenf-Lieder-recordid_669657--3","docUri":"JBWV_0050_op49_Fuenf-Lieder-recordid_669657--3.html","score":0.029501149808546734,"contexts":[{"form":"Joseph","weight":"1","pos":42,"context":".... Anna Baier: Gesang; u.a. \"'Wiegenlied' von <mark>Joseph<\/mark> [sic] Brahms\""}]},{"docId":"JBWV_0008_op8_Klaviertrio-Nr1-H-Dur-recordid_669905--23","docUri":"JBWV_0008_op8_Klaviertrio-Nr1-H-Dur-recordid_669905--23.html","score":0.022878442708668893,"contexts":[{"form":"Joseph","weight":"1","pos":12,"context":"<mark>Joseph<\/mark> Hellmesberger jun. (Violinist_in)"}]},{"docId":"JBWV_0008_op8_Klaviertrio-Nr1-H-Dur-recordid_668258--26","docUri":"JBWV_0008_op8_Klaviertrio-Nr1-H-Dur-recordid_668258--26.html","score":0.024912082060550574,"contexts":[{"form":"Joseph","weight":"1","pos":12,"context":"<mark>Joseph<\/mark> Hellmesberger jun. (Violinist_in)"}]},{"docId":"JBWV_0008_op8_Klaviertrio-Nr1-H-Dur-recordid_668272--27","docUri":"JBWV_0008_op8_Klaviertrio-Nr1-H-Dur-recordid_668272--27.html","score":0.022878442708668893,"contexts":[{"form":"Joseph","weight":"1","pos":12,"context":"<mark>Joseph<\/mark> Hellmesberger jun. (Violinist_in)"}]},{"docId":"JBWV_0032_op32_Neun-Lieder-und-Gesaenge-recordid_669713--8","docUri":"JBWV_0032_op32_Neun-Lieder-und-Gesaenge-recordid_669713--8.html","score":0.028026092318119394,"contexts":[{"form":"Joseph","weight":"1","pos":10,"context":"Hellmesberger, <mark>Joseph<\/mark> (musikalische_r_Direktor_in)"}]},{"docId":"personenregister-id-0273","docUri":"personenregister-id-0273.html","score":0.04874103011846851,"contexts":[{"form":"Joseph","weight":"1","pos":4,"context":"<mark>Joseph<\/mark>"}]},{"docId":"JBWV_0032_op32_Neun-Lieder-und-Gesaenge-recordid_667804--9","docUri":"JBWV_0032_op32_Neun-Lieder-und-Gesaenge-recordid_667804--9.html","score":0.025478265743744906,"contexts":[{"form":"Joseph","weight":"1","pos":10,"context":"Hellmesberger, <mark>Joseph<\/mark> (musikalische_r_Direktor_in)"}]}]}