{"stem":"kunst","instances":[{"docId":"JBWV_0085_op81_Tragische-Ouvertuere-d-Moll-recordid_669254--33","docUri":"JBWV_0085_op81_Tragische-Ouvertuere-d-Moll-recordid_669254--33.html","score":0.06252151685504301,"contexts":[{"form":"Kunst","weight":"1","pos":38,"context":"...J. Brahms anlässlich der Verleihung des österreichischen \"Ehrenzeichen für <mark>Kunst<\/mark> und Wissenschaft\", vgl. Hofmann, Zeittafel,..."}]},{"docId":"JBWV_0011_op11_Serenade-Nr1-D-Dur-recordid_669251--28","docUri":"JBWV_0011_op11_Serenade-Nr1-D-Dur-recordid_669251--28.html","score":0.0692805997582909,"contexts":[{"form":"Kunst","weight":"1","pos":34,"context":"...J. Brahms anlässlich der Verleihung des österreichischen \"Ehrenzeichen für <mark>Kunst<\/mark> und Wissenschaft\", vgl. Hofmann, Zeittafel,..."}]},{"docId":"JBWV_0016_op16_Serenade-Nr_-2-A-Dur-recordid_669252--27","docUri":"JBWV_0016_op16_Serenade-Nr.-2-A-Dur-recordid_669252--27.html","score":0.06408455477641908,"contexts":[{"form":"Kunst","weight":"1","pos":38,"context":"...J. Brahms anlässlich der Verleihung des österreichischen \"Ehrenzeichen für <mark>Kunst<\/mark> und Wissenschaft\", vgl. Hofmann, Zeittafel,..."}]},{"docId":"JBWV_0111_op106_Fuenf-Lieder-recordid_670166--15","docUri":"JBWV_0111_op106_Fuenf-Lieder-recordid_670166--15.html","score":0.07120506086268787,"contexts":[{"form":"Kunst","weight":"1","pos":32,"context":"2. Geselliger Abend der Sektion für Literatur und <mark>Kunst<\/mark> der Leo-Gesellschaft; Datum gemäß Reichspost,..."}]},{"docId":"JBWV_0084_op80_Akademische-Festouvertuere-c-Moll-recordid_669253--58","docUri":"JBWV_0084_op80_Akademische-Festouvertuere-c-Moll-recordid_669253--58.html","score":0.06408455477641908,"contexts":[{"form":"Kunst","weight":"1","pos":37,"context":"...J. Brahms anlässlich der Verleihung des österreichischen \"Ehrenzeichen für <mark>Kunst<\/mark> und Wissenschaft\", vgl. Hofmann, Zeittafel,..."}]},{"docId":"JBWV_0046_op45_Ein-deutsches-Requiem-recordid_669248--86","docUri":"JBWV_0046_op45_Ein-deutsches-Requiem-recordid_669248--86.html","score":0.06572774848863495,"contexts":[{"form":"Kunst","weight":"1","pos":36,"context":"...J. Brahms anlässlich der Verleihung des österreichischen \"Ehrenzeichen für <mark>Kunst<\/mark> und Wissenschaft\", vgl. Hofmann, Zeittafel,..."}]},{"docId":"JBWV_0072_op68_Symphonie-Nr_-1-c-Moll-recordid_668472--31","docUri":"JBWV_0072_op68_Symphonie-Nr.-1-c-Moll-recordid_668472--31.html","score":0.04747004057512524,"contexts":[{"form":"Kunst","weight":"1","pos":56,"context":"...denn Heuberger sei \"wie Wenige mit dem Wesen Brahms'scher <mark>Kunst<\/mark> vertraut\"; Datum gemäß Die Presse, Local-..."}]},{"docId":"JBWV_0057_op55_Triumphlied-recordid_669249--45","docUri":"JBWV_0057_op55_Triumphlied-recordid_669249--45.html","score":0.06745742608044114,"contexts":[{"form":"Kunst","weight":"1","pos":35,"context":"...J. Brahms anlässlich der Verleihung des österreichischen \"Ehrenzeichen für <mark>Kunst<\/mark> und Wissenschaft\", vgl. Hofmann, Zeittafel,..."}]},{"docId":"JBWV_0056_op54_Schicksalslied-recordid_667593--42","docUri":"JBWV_0056_op54_Schicksalslied-recordid_667593--42.html","score":0.059613539326901464,"contexts":[{"form":"Kunst","weight":"1","pos":37,"context":"...Musikfestes unter der Ägide des Vereins zur Förderung der <mark>Kunst<\/mark> und unter dem Protektorat des Prinzen Hermann zu Sachsen..."}]},{"docId":"JBWV_0072_op68_Symphonie-Nr_-1-c-Moll-recordid_670914--55","docUri":"JBWV_0072_op68_Symphonie-Nr.-1-c-Moll-recordid_670914--55.html","score":0.0434471557806231,"contexts":[{"form":"Kunst","weight":"1","pos":54,"context":"...\"musikalisch künstlerische Ausdruck eines Mannes genommen werden, der seiner <mark>Kunst<\/mark> nach seiner Art wahrhaft ergeben war und in den..."}]},{"docId":"JBWV_0120_op115_Klarinettenquintett-h-Moll-recordid_669255--91","docUri":"JBWV_0120_op115_Klarinettenquintett-h-Moll-recordid_669255--91.html","score":0.06408455477641908,"contexts":[{"form":"Kunst","weight":"1","pos":37,"context":"...J. Brahms anlässlich der Verleihung des österreichischen \"Ehrenzeichen für <mark>Kunst<\/mark> und Wissenschaft\", vgl. Hofmann, Zeittafel,..."}]},{"docId":"JBWV_0046_op45_Ein-deutsches-Requiem-recordid_668518--115","docUri":"JBWV_0046_op45_Ein-deutsches-Requiem-recordid_668518--115.html","score":0.06408455477641908,"contexts":[{"form":"Kunst","weight":"1","pos":38,"context":"Konzert in der Gesellschaft für <mark>Kunst<\/mark> und Wissenschaften mit zwei Vorträgen des Wiener Konzertsängers Eduard..."}]}]}