{"stem":"local","instances":[{"docId":"F%C3%BCnf-Lieder-recordid_668700","docUri":"F%C3%BCnf-Lieder-recordid_668700.html","score":2,"contexts":[{"form":"Local","weight":"1","pos":47,"context":"Presse, <mark>Local<\/mark>-Anzeiger, Jg. 46, Nr. 351, 20.12...","fid":"workTableDetail"},{"form":"Local","weight":"1","pos":79,"context":"...Vereins eingelullt zu werden?\"; Datum gemäß Die Presse, <mark>Local<\/mark>-Anzeiger, 12.12.1893, S. 11...","fid":"workTableDetail"}]},{"docId":"Neun-Lieder-und-Ges%C3%A4nge-recordid_668694","docUri":"Neun-Lieder-und-Ges%C3%A4nge-recordid_668694.html","score":2,"contexts":[{"form":"Local","weight":"1","pos":50,"context":"Presse, <mark>Local<\/mark>-Anzeiger, Jg. 46, Nr. 347, 16.12...","fid":"workTableDetail"},{"form":"Local","weight":"1","pos":88,"context":"...das \"Vergebliche Ständchen\"; Datum gemäß Die Presse, <mark>Local<\/mark>-Anzeiger, 13.12.1893, S. 15...","fid":"workTableDetail"}]},{"docId":"Neun-Lieder-und-Ges%C3%A4nge-recordid_667691","docUri":"Neun-Lieder-und-Ges%C3%A4nge-recordid_667691.html","score":1,"contexts":[{"form":"Local","weight":"1","pos":49,"context":"Presse, <mark>Local<\/mark>-Anzeiger, Jg. 39, Nr. 77, 18.03....","fid":"workTableDetail"}]},{"docId":"F%C3%BCnf-Lieder-recordid_667201","docUri":"F%C3%BCnf-Lieder-recordid_667201.html","score":1,"contexts":[{"form":"Local","weight":"1","pos":46,"context":"Presse, <mark>Local<\/mark>-Anzeiger, Jg. 34, Nr. 85, 27.03....","fid":"workTableDetail"}]},{"docId":"Neun-Lieder-und-Ges%C3%A4nge-recordid_668697","docUri":"Neun-Lieder-und-Ges%C3%A4nge-recordid_668697.html","score":1,"contexts":[{"form":"Local","weight":"1","pos":41,"context":"Presse, <mark>Local<\/mark>-Anzeiger, Jg. 46, Nr. 347, 16.12...","fid":"workTableDetail"}]},{"docId":"F%C3%BCnf-Lieder-recordid_668910","docUri":"F%C3%BCnf-Lieder-recordid_668910.html","score":1,"contexts":[{"form":"Local","weight":"1","pos":58,"context":"...großem Beifall\" aufgenommen worden; Datum gemäß Die Presse, <mark>Local<\/mark>-Anzeiger, 01.12.1894, S. 11...","fid":"workTableDetail"}]},{"docId":"F%C3%BCnf-Lieder-recordid_667131","docUri":"F%C3%BCnf-Lieder-recordid_667131.html","score":1,"contexts":[{"form":"Local","weight":"1","pos":64,"context":"...stürmisches Verlangen\" wiederholt werden; Datum gemäß Die Presse, <mark>Local<\/mark>-Anzeiger, 04.11.1879, S. 11...","fid":"workTableDetail"}]},{"docId":"Neun-Lieder-und-Ges%C3%A4nge-recordid_667296","docUri":"Neun-Lieder-und-Ges%C3%A4nge-recordid_667296.html","score":1,"contexts":[{"form":"Local","weight":"1","pos":51,"context":"Presse, <mark>Local<\/mark>-Anzeiger, Jg. 35, Nr. 122, 04.05...","fid":"workTableDetail"}]},{"docId":"Neun-Lieder-und-Ges%C3%A4nge-recordid_667708","docUri":"Neun-Lieder-und-Ges%C3%A4nge-recordid_667708.html","score":1,"contexts":[{"form":"Local","weight":"1","pos":74,"context":"...Nr. 4; Datum und Werke gemäß Die Presse, <mark>Local<\/mark>-Anzeiger, 18.03.1886, S. 11...","fid":"workTableDetail"}]},{"docId":"F%C3%BCnf-Lieder-recordid_668565","docUri":"F%C3%BCnf-Lieder-recordid_668565.html","score":1,"contexts":[{"form":"Local","weight":"1","pos":43,"context":"Presse, <mark>Local<\/mark>-Anzeiger, Jg. 46, Nr. 60, 01.03....","fid":"workTableDetail"}]},{"docId":"Neun-Lieder-und-Ges%C3%A4nge-recordid_668359","docUri":"Neun-Lieder-und-Ges%C3%A4nge-recordid_668359.html","score":1,"contexts":[{"form":"Local","weight":"1","pos":57,"context":"..., großer Musikvereinssaal; Datum gemäß Die Presse, <mark>Local<\/mark>-Anzeiger, 22.11.1891, S. 16...","fid":"workTableDetail"}]},{"docId":"F%C3%BCnf-Lieder-recordid_668463","docUri":"F%C3%BCnf-Lieder-recordid_668463.html","score":1,"contexts":[{"form":"Local","weight":"1","pos":40,"context":"Presse, <mark>Local<\/mark>-Anzeiger, Jg. 45, Nr. 199, 19.07...","fid":"workTableDetail"}]},{"docId":"Neun-Lieder-und-Ges%C3%A4nge-recordid_667297","docUri":"Neun-Lieder-und-Ges%C3%A4nge-recordid_667297.html","score":1,"contexts":[{"form":"Local","weight":"1","pos":51,"context":"Presse, <mark>Local<\/mark>-Anzeiger, Jg. 35, Nr. 123, 05.05...","fid":"workTableDetail"}]},{"docId":"Klaviertrio-Nr-1-H-Dur-recordid_668228","docUri":"Klaviertrio-Nr-1-H-Dur-recordid_668228.html","score":1,"contexts":[{"form":"Local","weight":"1","pos":47,"context":"...Pianistin Marie Baumayer; Datum gemäß Die Presse, <mark>Local<\/mark>-Anzeiger, 08.03.1891, S. 15...","fid":"workTableDetail"}]},{"docId":"Neun-Lieder-und-Ges%C3%A4nge-recordid_668440","docUri":"Neun-Lieder-und-Ges%C3%A4nge-recordid_668440.html","score":1,"contexts":[{"form":"Local","weight":"1","pos":42,"context":"Presse, <mark>Local<\/mark>-Anzeiger, Jg. 45, Nr. 107, 16.04...","fid":"workTableDetail"}]},{"docId":"F%C3%BCnf-Lieder-recordid_667928","docUri":"F%C3%BCnf-Lieder-recordid_667928.html","score":1,"contexts":[{"form":"Local","weight":"1","pos":49,"context":"Presse, <mark>Local<\/mark>-Anzeiger, Jg. 41, Nr. 54, 23.02....","fid":"workTableDetail"}]},{"docId":"Neun-Lieder-und-Ges%C3%A4nge-recordid_666978","docUri":"Neun-Lieder-und-Ges%C3%A4nge-recordid_666978.html","score":1,"contexts":[{"form":"Local","weight":"1","pos":47,"context":"Presse, <mark>Local<\/mark>-Anzeiger, Jg. 30, Nr. 301, 01.11...","fid":"workTableDetail"}]},{"docId":"F%C3%BCnf-Lieder-recordid_670980","docUri":"F%C3%BCnf-Lieder-recordid_670980.html","score":1,"contexts":[{"form":"Local","weight":"1","pos":47,"context":"Presse, <mark>Local<\/mark>-Anzeiger, Jg. 45, Nr. 113, 23.04...","fid":"workTableDetail"}]},{"docId":"F%C3%BCnf-Lieder-recordid_667243","docUri":"F%C3%BCnf-Lieder-recordid_667243.html","score":1,"contexts":[{"form":"Local","weight":"1","pos":37,"context":"Presse, <mark>Local<\/mark>-Anzeiger, Jg. 34, Nr. 346, 16.12...","fid":"workTableDetail"}]},{"docId":"Neun-Lieder-und-Ges%C3%A4nge-recordid_666987","docUri":"Neun-Lieder-und-Ges%C3%A4nge-recordid_666987.html","score":1,"contexts":[{"form":"Local","weight":"1","pos":42,"context":"Presse, <mark>Local<\/mark>-Anzeiger, Jg. 30, Nr. 341, 12.12...","fid":"workTableDetail"}]},{"docId":"F%C3%BCnf-Lieder-recordid_668701","docUri":"F%C3%BCnf-Lieder-recordid_668701.html","score":1,"contexts":[{"form":"Local","weight":"1","pos":47,"context":"Presse, <mark>Local<\/mark>-Anzeiger, Jg. 46, Nr. 351, 20.12...","fid":"workTableDetail"}]},{"docId":"Walzer-recordid_667352","docUri":"Walzer-recordid_667352.html","score":1,"contexts":[{"form":"Local","weight":"1","pos":40,"context":"Presse, <mark>Local<\/mark>-Anzeiger, Jg. 36, Nr. 65, 08.03....","fid":"workTableDetail"}]},{"docId":"Neun-Lieder-und-Ges%C3%A4nge-recordid_667785","docUri":"Neun-Lieder-und-Ges%C3%A4nge-recordid_667785.html","score":1,"contexts":[{"form":"Local","weight":"1","pos":47,"context":"Presse, <mark>Local<\/mark>-Anzeiger, Jg. 40, Nr. 1, 01.01....","fid":"workTableDetail"}]},{"docId":"Neun-Lieder-und-Ges%C3%A4nge-recordid_667786","docUri":"Neun-Lieder-und-Ges%C3%A4nge-recordid_667786.html","score":1,"contexts":[{"form":"Local","weight":"1","pos":47,"context":"Presse, <mark>Local<\/mark>-Anzeiger, Jg. 40, Nr. 3, 04.01....","fid":"workTableDetail"}]},{"docId":"F%C3%BCnf-Lieder-recordid_666584","docUri":"F%C3%BCnf-Lieder-recordid_666584.html","score":1,"contexts":[{"form":"Local","weight":"1","pos":46,"context":"Presse, <mark>Local<\/mark>-Anzeiger, Jg. 26, Nr. 108, 20.04...","fid":"workTableDetail"}]},{"docId":"Neun-Lieder-und-Ges%C3%A4nge-recordid_668686","docUri":"Neun-Lieder-und-Ges%C3%A4nge-recordid_668686.html","score":1,"contexts":[{"form":"Local","weight":"1","pos":50,"context":"Presse, <mark>Local<\/mark>-Anzeiger, Jg. 46, Nr. 344, 13.12...","fid":"workTableDetail"}]},{"docId":"Walzer-recordid_666989","docUri":"Walzer-recordid_666989.html","score":1,"contexts":[{"form":"Local","weight":"1","pos":39,"context":"Presse, <mark>Local<\/mark>-Anzeiger, Jg. 30, Nr. 341, 12.12...","fid":"workTableDetail"}]},{"docId":"F%C3%BCnf-Lieder-recordid_668932","docUri":"F%C3%BCnf-Lieder-recordid_668932.html","score":1,"contexts":[{"form":"Local","weight":"1","pos":47,"context":"Presse, <mark>Local<\/mark>-Anzeiger, Jg. 48, Nr. 9, 09.01....","fid":"workTableDetail"}]},{"docId":"Neun-Lieder-und-Ges%C3%A4nge-recordid_667715","docUri":"Neun-Lieder-und-Ges%C3%A4nge-recordid_667715.html","score":1,"contexts":[{"form":"Local","weight":"1","pos":44,"context":"Presse, <mark>Local<\/mark>-Anzeiger, Jg. 39, Nr. 128, 09.05...","fid":"workTableDetail"}]},{"docId":"F%C3%BCnf-Lieder-recordid_666769","docUri":"F%C3%BCnf-Lieder-recordid_666769.html","score":1,"contexts":[{"form":"Local","weight":"1","pos":37,"context":"Presse, <mark>Local<\/mark>-Anzeiger, Jg. 27, Nr. 296, 28.10...","fid":"workTableDetail"}]},{"docId":"Neun-Lieder-und-Ges%C3%A4nge-recordid_669914","docUri":"Neun-Lieder-und-Ges%C3%A4nge-recordid_669914.html","score":1,"contexts":[{"form":"Local","weight":"1","pos":67,"context":"...\"Nicht mehr zu Dir\"; Datum gemäß Die Presse, <mark>Local<\/mark>-Anzeiger, 22.11.1891, S. 16...","fid":"workTableDetail"}]},{"docId":"F%C3%BCnf-Lieder-recordid_668503","docUri":"F%C3%BCnf-Lieder-recordid_668503.html","score":1,"contexts":[{"form":"Local","weight":"1","pos":40,"context":"Presse, <mark>Local<\/mark>-Anzeiger, Jg. 45, Nr. 340, 08.12...","fid":"workTableDetail"}]},{"docId":"F%C3%BCnf-Lieder-recordid_668462","docUri":"F%C3%BCnf-Lieder-recordid_668462.html","score":1,"contexts":[{"form":"Local","weight":"1","pos":40,"context":"Presse, <mark>Local<\/mark>-Anzeiger, Jg. 45, Nr. 194, 14.07...","fid":"workTableDetail"}]},{"docId":"F%C3%BCnf-Lieder-recordid_667192","docUri":"F%C3%BCnf-Lieder-recordid_667192.html","score":1,"contexts":[{"form":"Local","weight":"1","pos":46,"context":"Presse, <mark>Local<\/mark>-Anzeiger, Jg. 34, Nr. 78, 20.03....","fid":"workTableDetail"}]},{"docId":"Neun-Lieder-und-Ges%C3%A4nge-recordid_667804","docUri":"Neun-Lieder-und-Ges%C3%A4nge-recordid_667804.html","score":1,"contexts":[{"form":"Local","weight":"1","pos":50,"context":"Presse, <mark>Local<\/mark>-Anzeiger, Jg. 40, Nr. 29, 30.01....","fid":"workTableDetail"}]}]}