{"stem":"prill","instances":[{"docId":"JBWV_0003_op3_Sechs-Gesaenge-recordid_670626--30","docUri":"JBWV_0003_op3_Sechs-Gesaenge-recordid_670626--30.html","score":0.11637893015502107,"contexts":[{"form":"Prill","weight":"1","pos":13,"context":"<mark>Prill<\/mark>, Carl (Violinist_in)"},{"form":"Prill","weight":"1","pos":37,"context":"...von Lotte Barensfeld unter Mitwirkung von Konzertmeister Prof. <mark>Prill<\/mark>, 19.30 Uhr; u.a. 3 Lieder von Brahms:..."}]},{"docId":"JBWV_0052_op51_Zwei-Streichquartette-recordid_670746--53","docUri":"JBWV_0052_op51_Zwei-Streichquartette-recordid_670746--53.html","score":0.10786339868026344,"contexts":[{"form":"Prill","weight":"1","pos":10,"context":"<mark>Prill<\/mark>, Karl (Violinist_in)"},{"form":"Prill","weight":"1","pos":42,"context":"<mark>Prill<\/mark>-Quartett; Datum gemäß Vaterland, Morgenblatt,..."}]},{"docId":"JBWV_0026%20_op26_Klavierquartett-Nr_-2-A-Dur-recordid_670724--21","docUri":"JBWV_0026%20_op26_Klavierquartett-Nr.-2-A-Dur-recordid_670724--21.html","score":0.11637893015502107,"contexts":[{"form":"Prill","weight":"1","pos":7,"context":"<mark>Prill<\/mark>, Karl (1_Violinist_in)"},{"form":"Prill","weight":"1","pos":36,"context":"1. Kammermusikabend des <mark>Prill<\/mark>-Quartetts; Datum gemäß Neue Freie Presse,..."}]},{"docId":"JBWV_0026%20_op26_Klavierquartett-Nr_-2-A-Dur-recordid_670932--22","docUri":"JBWV_0026%20_op26_Klavierquartett-Nr.-2-A-Dur-recordid_670932--22.html","score":0.11055998364727003,"contexts":[{"form":"Prill","weight":"1","pos":7,"context":"<mark>Prill<\/mark>, Karl (1_Violinist_in)"},{"form":"Prill","weight":"1","pos":37,"context":"1. Abonnementquartett von Konzertmeister <mark>Prill<\/mark>; fälschlich: \"Brahm's\"; Datum gemäß Neue Freie..."}]},{"docId":"JBWV_0052_op51_Zwei-Streichquartette-recordid_670739--52","docUri":"JBWV_0052_op51_Zwei-Streichquartette-recordid_670739--52.html","score":0.11637893015502107,"contexts":[{"form":"Prill","weight":"1","pos":10,"context":"<mark>Prill<\/mark>, Karl (Violinist_in)"},{"form":"Prill","weight":"1","pos":41,"context":"2. Kammermusikabend des <mark>Prill<\/mark>-Quartetts"}]},{"docId":"JBWV_0052_op51_Zwei-Streichquartette-recordid_670726--49","docUri":"JBWV_0052_op51_Zwei-Streichquartette-recordid_670726--49.html","score":0.11339485502284104,"contexts":[{"form":"Prill","weight":"1","pos":10,"context":"<mark>Prill<\/mark>, Karl (Violinist_in)"},{"form":"Prill","weight":"1","pos":42,"context":"2. Kammermusikabend des <mark>Prill<\/mark>-Quartetts"}]},{"docId":"JBWV_0071_op67_Streichquartett-Nr_-3-B-Dur-recordid_670543--28","docUri":"JBWV_0071_op67_Streichquartett-Nr.-3-B-Dur-recordid_670543--28.html","score":0.06700605069531516,"contexts":[{"form":"Prill","weight":"1","pos":34,"context":"Kammermusikabend des <mark>Prill<\/mark>-Quartetts; Datum und Werk gemäß Vaterland,..."}]},{"docId":"JBWV_0082_op78_Violinsonate-Nr_-1-G-Dur-recordid_670827--42","docUri":"JBWV_0082_op78_Violinsonate-Nr.-1-G-Dur-recordid_670827--42.html","score":0.06909998977954376,"contexts":[{"form":"Prill","weight":"1","pos":10,"context":"<mark>Prill<\/mark>, Carl (Violinist_in)"}]},{"docId":"JBWV_0025_op25_Klavierquartett-Nr_-1-g-Moll-recordid_670544--38","docUri":"JBWV_0025_op25_Klavierquartett-Nr.-1-g-Moll-recordid_670544--38.html","score":0.06503528449839413,"contexts":[{"form":"Prill","weight":"1","pos":36,"context":"2. Kammermusikabend des <mark>Prill<\/mark>-Quartetts"}]},{"docId":"JBWV_0081_op77_Violinkonzert-D-Dur--70","docUri":"JBWV_0081_op77_Violinkonzert-D-Dur--70.html","score":0.11637893015502107,"contexts":[{"form":"Prill","weight":"1","pos":7,"context":"<mark>Prill<\/mark>, Carl (Violinist_in)"}]},{"docId":"JBWV_0071_op67_Streichquartett-Nr_-3-B-Dur-recordid_670542--27","docUri":"JBWV_0071_op67_Streichquartett-Nr.-3-B-Dur-recordid_670542--27.html","score":0.07370665576484668,"contexts":[{"form":"Prill","weight":"1","pos":32,"context":"1. Kammermusikabend des <mark>Prill<\/mark>-Quartetts, 19.30 Uhr"}]},{"docId":"JBWV_0008_op8_Klaviertrio-Nr_-1-H-Dur-recordid_670528--31","docUri":"JBWV_0008_op8_Klaviertrio-Nr.-1-H-Dur-recordid_670528--31.html","score":0.047046801552029796,"contexts":[{"form":"Prill","weight":"1","pos":58,"context":"6 Kammermusikabende des <mark>Prill<\/mark>-Quartetts der Saison 1898\/1899; u.a...."}]},{"docId":"JBWV_0052_op51_Zwei-Streichquartette-recordid_670428--35","docUri":"JBWV_0052_op51_Zwei-Streichquartette-recordid_670428--35.html","score":0.07897141689090716,"contexts":[{"form":"Prill","weight":"1","pos":29,"context":"1. Abend des <mark>Prill<\/mark>-Quartetts, 19.30 Uhr"}]},{"docId":"JBWV_0018_op18_Streichsextett-Nr_-1-B-Dur-recordid_670789--41","docUri":"JBWV_0018_op18_Streichsextett-Nr.-1-B-Dur-recordid_670789--41.html","score":0.05142324820803257,"contexts":[{"form":"Prill","weight":"1","pos":30,"context":"1. Kammermusikabend des <mark>Prill<\/mark>-Quartetts; Brahms sei \"ein auf den Vorbergen..."}]},{"docId":"JBWV_0008_op8_Klaviertrio-Nr_-1-H-Dur-recordid_670582--34","docUri":"JBWV_0008_op8_Klaviertrio-Nr.-1-H-Dur-recordid_670582--34.html","score":0.06317713351272572,"contexts":[{"form":"Prill","weight":"1","pos":35,"context":"4. Kammermusikabend des <mark>Prill<\/mark>-Quartetts; Werk und Datum gemäß Vaterland,..."}]},{"docId":"JBWV_0102_op97_Sechs-Lieder-recordid_670627--21","docUri":"JBWV_0102_op97_Sechs-Lieder-recordid_670627--21.html","score":0.06142221313737224,"contexts":[{"form":"Prill","weight":"1","pos":34,"context":"...von Lotte Barensfeld unter Mitwirkung von Konzertmeister Prof. <mark>Prill<\/mark>, 19.30 Uhr; u.a. 3 Lieder von Brahms:..."}]},{"docId":"JBWV_0071_op67_Streichquartett-Nr_-3-B-Dur-recordid_670540--26","docUri":"JBWV_0071_op67_Streichquartett-Nr.-3-B-Dur-recordid_670540--26.html","score":0.06700605069531516,"contexts":[{"form":"Prill","weight":"1","pos":34,"context":"1. Kammermusikabend des <mark>Prill<\/mark>-Quartetts, 19.30 Uhr"}]},{"docId":"JBWV_0008_op8_Klaviertrio-Nr_-1-H-Dur-recordid_670559--33","docUri":"JBWV_0008_op8_Klaviertrio-Nr.-1-H-Dur-recordid_670559--33.html","score":0.06700605069531516,"contexts":[{"form":"Prill","weight":"1","pos":34,"context":"4. Kammermusikabend des <mark>Prill<\/mark>-Quartetts; \"neue Bearbeitung\""}]},{"docId":"JBWV_0113_op108_Violinsonate-Nr_-3-d-Moll-recordid_670829--17","docUri":"JBWV_0113_op108_Violinsonate-Nr.-3-d-Moll-recordid_670829--17.html","score":0.06909998977954376,"contexts":[{"form":"Prill","weight":"1","pos":10,"context":"<mark>Prill<\/mark>, Carl (Violinist_in)"}]},{"docId":"JBWV_0081_op77_Violinkonzert-D-Dur-recordid_670748--69","docUri":"JBWV_0081_op77_Violinkonzert-D-Dur-recordid_670748--69.html","score":0.06317713351272572,"contexts":[{"form":"Prill","weight":"1","pos":7,"context":"<mark>Prill<\/mark>, Carl (Violinist_in)"}]},{"docId":"JBWV_0120_op115_Klarinettenquintett-h-Moll-recordid_670625--78","docUri":"JBWV_0120_op115_Klarinettenquintett-h-Moll-recordid_670625--78.html","score":0.06503528449839413,"contexts":[{"form":"Prill","weight":"1","pos":35,"context":"1. Abend des <mark>Prill<\/mark>-Quartetts"}]},{"docId":"JBWV_0071_op67_Streichquartett-Nr_-3-B-Dur-recordid_670530--25","docUri":"JBWV_0071_op67_Streichquartett-Nr.-3-B-Dur-recordid_670530--25.html","score":0.05142324820803257,"contexts":[{"form":"Prill","weight":"1","pos":55,"context":"6 Kammermusikabende des <mark>Prill<\/mark>-Quartetts der Saison 1898\/1899; u.a...."}]},{"docId":"JBWV_0105_op100_Violinsonate-Nr_-2-A-Dur-recordid_670828--39","docUri":"JBWV_0105_op100_Violinsonate-Nr.-2-A-Dur-recordid_670828--39.html","score":0.06909998977954376,"contexts":[{"form":"Prill","weight":"1","pos":10,"context":"<mark>Prill<\/mark>, Carl (Violinist_in)"}]},{"docId":"JBWV_0025_op25_Klavierquartett-Nr_-1-g-Moll-recordid_670541--37","docUri":"JBWV_0025_op25_Klavierquartett-Nr.-1-g-Moll-recordid_670541--37.html","score":0.055279991823635015,"contexts":[{"form":"Prill","weight":"1","pos":38,"context":"2. Kammermusikabend des <mark>Prill<\/mark>-Quartetts; Datum gemäß Vaterland, Morgenblatt,..."}]},{"docId":"JBWV_0025_op25_Klavierquartett-Nr_-1-g-Moll-recordid_670529--36","docUri":"JBWV_0025_op25_Klavierquartett-Nr.-1-g-Moll-recordid_670529--36.html","score":0.05142324820803257,"contexts":[{"form":"Prill","weight":"1","pos":55,"context":"6 Kammermusikabende des <mark>Prill<\/mark>-Quartetts der Saison 1898\/1899; u.a...."}]},{"docId":"JBWV_0052_op51_Zwei-Streichquartette-recordid_670422--34","docUri":"JBWV_0052_op51_Zwei-Streichquartette-recordid_670422--34.html","score":0.06503528449839413,"contexts":[{"form":"Prill","weight":"1","pos":29,"context":"4 Abende des <mark>Prill<\/mark>-Quartetts der Saison 1897\/98 beginnend mit..."}]},{"docId":"JBWV_0052_op51_Zwei-Streichquartette-recordid_670874--58","docUri":"JBWV_0052_op51_Zwei-Streichquartette-recordid_670874--58.html","score":0.07897141689090716,"contexts":[{"form":"Prill","weight":"1","pos":29,"context":"2. Kammermusikabend des <mark>Prill<\/mark>-Quartetts"}]}]}