{"stem":"reih","instances":[{"docId":"work_op39_expressions_event_d8e248_recordid_667377","docUri":"work_op39_expressions_event_d8e248_recordid_667377.html","score":1,"contexts":[{"form":"Reihe","weight":"1","pos":63,"context":"...-Schubert und Hr. Door: Klavier; \"eine <mark>Reihe<\/mark> aus den Brahms'schen Walzern vierhändig\"; Datum gemäß Die...","fid":"page"}]},{"docId":"JBWV_0040_op39_Walzer","docUri":"JBWV_0040_op39_Walzer.html","score":1,"contexts":[{"form":"Reihe","weight":"1","pos":190,"context":"...-Schubert und Hr. Door: Klavier; \"eine <mark>Reihe<\/mark> aus den Brahms'schen Walzern vierhändig\"; Datum gemäß Die...","fid":"recordid_667377"}]}]}