{"stem":"sogar","instances":[{"docId":"JBWV_0053_op52_Liebeslieder_-Walzer-recordid_666445--5","docUri":"JBWV_0053_op52_Liebeslieder.-Walzer-recordid_666445--5.html","score":0.04869911049822655,"contexts":[{"form":"sogar","weight":"1","pos":64,"context":"...die Physiognomie des alten Strauß unverkennbar hervorlugt, mußte <mark>sogar<\/mark> wiederholt werden\"; Zählung der Nummern nicht nach heutigem BrahmsWV..."}]},{"docId":"JBWV_0015_op15_Klavierkonzert-Nr_-1-d-Moll-recordid_669366-recordid_669367--1","docUri":"JBWV_0015_op15_Klavierkonzert-Nr.-1-d-Moll-recordid_669366-recordid_669367--1.html","score":0.0659467121330151,"contexts":[{"form":"\"sogar","weight":"1","pos":38,"context":"...; \"als Novität gebrachte Concert\"; der Komponist sei <mark>\"sogar<\/mark> noch vor der Aufführung des Werkes, gleich bei..."}]},{"docId":"JBWV_0053_op52_Liebeslieder_-Walzer-recordid_666451--14","docUri":"JBWV_0053_op52_Liebeslieder.-Walzer-recordid_666451--14.html","score":0.05365156241330043,"contexts":[{"form":"sogar","weight":"1","pos":53,"context":"...Konzert von Clara Schumann; \"Eine der Nummern mußte <mark>sogar<\/mark> auf stürmisches Verlangen wiederholt werden\"; Erstaufführung des vollständigen Werkes..."}]}]}