{"stem":"soiréen","instances":[{"docId":"JBWV_0052_op51_Zwei-Streichquartette-recordid_670188--23","docUri":"JBWV_0052_op51_Zwei-Streichquartette-recordid_670188--23.html","score":0.10536436346586324,"contexts":[{"form":"Soiréen","weight":"1","pos":27,"context":"Vorankündigung der Wiener <mark>Soiréen<\/mark> des Böhmischen Streichquartetts der Saison 1895\/1896"}]},{"docId":"JBWV_0052_op51_Zwei-Streichquartette-recordid_669055--24","docUri":"JBWV_0052_op51_Zwei-Streichquartette-recordid_669055--24.html","score":0.09783833750401585,"contexts":[{"form":"Soiréen","weight":"1","pos":29,"context":"Vorankündigung der <mark>Soiréen<\/mark> des Böhmischen Streichquartetts der Saison 1895\/1896"}]},{"docId":"JBWV_0052_op51_Zwei-Streichquartette-recordid_670107--17","docUri":"JBWV_0052_op51_Zwei-Streichquartette-recordid_670107--17.html","score":0.10146197963379422,"contexts":[{"form":"Soiréen","weight":"1","pos":28,"context":"Vorankündigung der 4 Abonnement-<mark>Soiréen<\/mark> des Böhmischen Streichquartetts der Saison 1894\/1895"}]},{"docId":"JBWV_0092_op88_Streichquintett-Nr_-1-F-Dur-recordid_670425--6","docUri":"JBWV_0092_op88_Streichquintett-Nr.-1-F-Dur-recordid_670425--6.html","score":0.074039822976012,"contexts":[{"form":"Soiréen","weight":"1","pos":46,"context":"Vorankündigung der 4 Abonnements-<mark>Soiréen<\/mark> des Fitzner-Quartetts"}]},{"docId":"JBWV_0008_op8_Klaviertrio-Nr_-1-H-Dur-recordid_668861--22","docUri":"JBWV_0008_op8_Klaviertrio-Nr.-1-H-Dur-recordid_668861--22.html","score":0.058286669151328595,"contexts":[{"form":"Soiréen","weight":"1","pos":45,"context":"Vorankündigung der drei Trio-<mark>Soiréen<\/mark> am 30.11.1894, 12.12.1894 und..."}]},{"docId":"JBWV_0034_op34_Klavierquintett-f-Moll-recordid_670026--4","docUri":"JBWV_0034_op34_Klavierquintett-f-Moll-recordid_670026--4.html","score":0.08837011129394981,"contexts":[{"form":"Soiréen","weight":"1","pos":34,"context":"Vorankündigung der <mark>Soiréen<\/mark> des Böhmischen Streichquartetts der Saison 1893\/1894,..."}]},{"docId":"JBWV_0026%20_op26_Klavierquartett-Nr_-2-A-Dur-recordid_670189--14","docUri":"JBWV_0026%20_op26_Klavierquartett-Nr.-2-A-Dur-recordid_670189--14.html","score":0.08301434697310436,"contexts":[{"form":"Soiréen","weight":"1","pos":34,"context":"Vorankündigung der Wiener <mark>Soiréen<\/mark> des Böhmischen Streichquartetts der Saison 1895\/1896"}]},{"docId":"JBWV_0034_op34_Klavierquintett-f-Moll-recordid_668632--45","docUri":"JBWV_0034_op34_Klavierquintett-f-Moll-recordid_668632--45.html","score":0.07827067000321268,"contexts":[{"form":"Soiréen","weight":"1","pos":37,"context":"Vorankündigung der <mark>Soiréen<\/mark> des Böhmischen Streichquartetts der Saison 1893\/1894,..."}]}]}