{"stem":"sophiensa","instances":[{"docId":"JBWV_0032_op32_Neun-Lieder-und-Gesaenge-recordid_666987--6","docUri":"JBWV_0032_op32_Neun-Lieder-und-Gesaenge-recordid_666987--6.html","score":0.03619808124076199,"contexts":[{"form":"Sophiensaal","weight":"1","pos":38,"context":"...des Wiener akademischen Gesangvereins, 8 Uhr abends, <mark>Sophiensaal<\/mark>; \"Zwei Lieder für Bariton\"; Werk gemäß Hofmann..."}]},{"docId":"JBWV_0040_op39_Walzer-recordid_666989--1","docUri":"JBWV_0040_op39_Walzer-recordid_666989--1.html","score":0.03872352876918724,"contexts":[{"form":"Sophiensaal","weight":"1","pos":36,"context":"...des Wiener akademischen Gesangvereins, 8 Uhr abends, <mark>Sophiensaal<\/mark>; \"Walzer für Clavier\"; Werk gemäß Hofmann,..."}]},{"docId":"JBWV_0032_op32_Neun-Lieder-und-Gesaenge-recordid_669503--4","docUri":"JBWV_0032_op32_Neun-Lieder-und-Gesaenge-recordid_669503--4.html","score":0.03872352876918724,"contexts":[{"form":"Sophiensaal","weight":"1","pos":35,"context":"...des Wiener akademischen Gesangvereins, 8 Uhr abends, <mark>Sophiensaal<\/mark>; Werke von J. Brahms: \"Drei Chöre von..."}]},{"docId":"JBWV_0032_op32_Neun-Lieder-und-Gesaenge-recordid_669515--5","docUri":"JBWV_0032_op32_Neun-Lieder-und-Gesaenge-recordid_669515--5.html","score":0.03619808124076199,"contexts":[{"form":"Sophiensaal","weight":"1","pos":41,"context":"...seiner Lehrtätigkeit an der Wiener Universität, abends, <mark>Sophiensaal<\/mark>; Werke von Brahms gemäß Hofmann, Chronologie,..."}]}]}