{"stem":"the","instances":[{"docId":"JBWV_0040_op39_Walzer","docUri":"JBWV_0040_op39_Walzer.html","score":10,"contexts":[{"form":"the","weight":"2","pos":161,"context":"Jump to <mark>the<\/mark> top","fid":"expresssion1_op39"},{"form":"the","weight":"2","pos":231,"context":"Jump to <mark>the<\/mark> top","fid":"perfResList"},{"form":"the","weight":"2","pos":242,"context":"Jump to <mark>the<\/mark> top","fid":"expresssion2_op39"},{"form":"the","weight":"2","pos":288,"context":"Jump to <mark>the<\/mark> top","fid":"expresssion3_op39"},{"form":"the","weight":"2","pos":294,"context":"Jump to <mark>the<\/mark> top","fid":"expresssion4_op39"}]},{"docId":"JBWV_0008_op8_Klaviertrio-Nr1-H-Dur","docUri":"JBWV_0008_op8_Klaviertrio-Nr1-H-Dur.html","score":6,"contexts":[{"form":"the","weight":"2","pos":314,"context":"Jump to <mark>the<\/mark> top","fid":"expresssion1_op8"},{"form":"the","weight":"2","pos":763,"context":"Jump to <mark>the<\/mark> top","fid":"perfResList"},{"form":"the","weight":"2","pos":772,"context":"Jump to <mark>the<\/mark> top","fid":"expresssion2_op8"}]},{"docId":"JBWV_0050_op49_Fuenf-Lieder","docUri":"JBWV_0050_op49_Fuenf-Lieder.html","score":4,"contexts":[{"form":"the","weight":"2","pos":1696,"context":"Jump to <mark>the<\/mark> top","fid":"perfResList"},{"form":"the","weight":"2","pos":1702,"context":"Jump to <mark>the<\/mark> top","fid":"componentList"}]},{"docId":"JBWV_0032_op32_Neun-Lieder-und-Gesaenge","docUri":"JBWV_0032_op32_Neun-Lieder-und-Gesaenge.html","score":4,"contexts":[{"form":"the","weight":"2","pos":1511,"context":"Jump to <mark>the<\/mark> top","fid":"perfResList"},{"form":"the","weight":"2","pos":1517,"context":"Jump to <mark>the<\/mark> top","fid":"componentList"}]}]}