{"stem":"volkskonzert","instances":[{"docId":"JBWV_0003_op3_Sechs-Ges%C3%A4nge-recordid_668584--45","docUri":"JBWV_0003_op3_Sechs-Ges%C3%A4nge-recordid_668584--45.html","score":0.048762325428954326,"contexts":[{"form":"Volkskonzert","weight":"1","pos":35,"context":"<mark>Volkskonzert<\/mark> der Sängerin Leonie v. Spaczek, des Pianisten Josef..."}]},{"docId":"JBWV_0050_op49_Fuenf-Lieder-recordid_668503--34","docUri":"JBWV_0050_op49_Fuenf-Lieder-recordid_668503--34.html","score":0.04754326729323047,"contexts":[{"form":"Volkskonzert","weight":"1","pos":29,"context":"<mark>Volkskonzert<\/mark> der Sängerin Paula Drächsler, der Pianistin Hermine Urban..."}]},{"docId":"JBWV_0050_op49_Fuenf-Lieder-recordid_669169--18","docUri":"JBWV_0050_op49_Fuenf-Lieder-recordid_669169--18.html","score":0.057628202779673295,"contexts":[{"form":"Volkskonzert","weight":"1","pos":34,"context":"<mark>Volkskonzert<\/mark> des Wiener Männergesangvereins, großer Musikvereinssaal"}]},{"docId":"JBWV_0050_op49_Fuenf-Lieder-recordid_670263--17","docUri":"JBWV_0050_op49_Fuenf-Lieder-recordid_670263--17.html","score":0.048762325428954326,"contexts":[{"form":"Volkskonzert","weight":"1","pos":32,"context":"<mark>Volkskonzert<\/mark> des Wiener Männergesangvereins unter der Leitung von Eduard Kremser..."}]}]}