{"stem":"werk","instances":[{"docId":"JBWV_0032_op32_Neun-Lieder-und-Gesaenge","docUri":"JBWV_0032_op32_Neun-Lieder-und-Gesaenge.html","score":15,"contexts":[{"form":"Werke","weight":"1","pos":51,"context":"...Uhr abends, Festsaal des neuen akademischen Gymnasiums; <mark>Werke<\/mark> von J. Brahms gemäß Hofmann, Chronologie, S....","fid":"d6e117"},{"form":"Werk","weight":"1","pos":77,"context":"(Konzert der Wiener Singakademie; Datum und <mark>Werk<\/mark> gemäß Hofmann, Chronologie, S. 101 f.; weitere...","fid":"d6e180"},{"form":"Werke","weight":"1","pos":82,"context":"...gemäß Hofmann, Chronologie, S. 101 f.; weitere <mark>Werke<\/mark> von J. Brahms: WoO 34, Nr. 3 und...","fid":"d6e180"},{"form":"Werk","weight":"1","pos":111,"context":"...Schumann; Frau Dustmann: Gesang; Datum und <mark>Werk<\/mark> gemäß BrahmsWV, S. 106)","fid":"d6e258"},{"form":"Werke","weight":"1","pos":142,"context":"...akademischen Gesangvereins, 8 Uhr abends, Sophiensaal; <mark>Werke<\/mark> von J. Brahms: \"Drei Chöre von Brahms\",...","fid":"d6e336"},{"form":"Werk","weight":"1","pos":154,"context":"...Clavier\", \"Ungarische Tänze [Clavier und Violine]\"; <mark>Werk<\/mark> gemäß Hofmann, Chronologie, S. 169)","fid":"d6e336"},{"form":"Werke","weight":"1","pos":189,"context":"...an der Wiener Universität, abends, Sophiensaal; <mark>Werke<\/mark> von Brahms gemäß Hofmann, Chronologie, S. 169...","fid":"d6e399"},{"form":"Werk","weight":"1","pos":224,"context":"...abends, Sophiensaal; \"Zwei Lieder für Bariton\"; <mark>Werk<\/mark> gemäß Hofmann, Chronologie, S. 169; weitere...","fid":"d6e466"},{"form":"Werke","weight":"1","pos":229,"context":"...gemäß Hofmann, Chronologie, S. 169; weitere <mark>Werke<\/mark> von J. Brahms: op. 43, Nr. 3 und...","fid":"d6e466"},{"form":"Werke","weight":"1","pos":268,"context":"..., 7 1\/2 Uhr abends, Saal Bösendorfer; <mark>Werke<\/mark> von J. Brahms: op. 32, Nr. 9, op....","fid":"d6e543"},{"form":"Werke","weight":"1","pos":362,"context":"...: Gesang, Mary Wurm: Klavier; u.a. <mark>Werke<\/mark> von J. Brahms: \"Vor dem Fenster\", \"Liebe...","fid":"d6e770"},{"form":"Werke","weight":"1","pos":763,"context":"...Schumann und Brahms bezeichnen, unser Schubert\"; weitere <mark>Werke<\/mark> von J. Brahms gespielt von Julius Röntgen: op....","fid":"d6e1475"},{"form":"Werke","weight":"1","pos":1036,"context":"...Bösendorfer; Rosa Papier: Gesang; u.a. folgende <mark>Werke<\/mark> von Brahms: op. 32, Nr. 9, op. 33,...","fid":"d6e2024"},{"form":"Werke","weight":"1","pos":1070,"context":"..., Schubert und Brahms schwelgen ließen\"; u.a. folgende <mark>Werke<\/mark> von Brahms: op. 32, Nr. 9, op. 33,...","fid":"d6e2084"},{"form":"Werke","weight":"1","pos":1073,"context":"...5 und 6, op. 94, Nr. 4; Datum und <mark>Werke<\/mark> gemäß Die Presse, Local-Anzeiger, 18.03...","fid":"d6e2084"}]},{"docId":"JBWV_0008_op8_Klaviertrio-Nr1-H-Dur","docUri":"JBWV_0008_op8_Klaviertrio-Nr1-H-Dur.html","score":11,"contexts":[{"form":"Werke","weight":"1","pos":215,"context":"...Cesek und Paul Fischer, Saal Bösendorfer; weitere <mark>Werke<\/mark>: \"Mehrstimmige Gesänge\" und op. 111)","fid":"d5e507"},{"form":"Werke","weight":"1","pos":251,"context":"...: Baumayer]: Klavier; \"neue Bearbeitung\"; weitere <mark>Werke<\/mark> von Brahms: Lieder und op. 111)","fid":"d5e571"},{"form":"Werk","weight":"1","pos":285,"context":"...das in Wien noch nicht aufgeführt ist\"; Datum und <mark>Werk<\/mark> gemäß NFB, Morgenblatt, 02.12.1871,...","fid":"d5e671"},{"form":"Werk","weight":"1","pos":541,"context":"...auf die Saison 1876\/77; Datum, Interpret und <mark>Werk<\/mark> gemäß Quartett Hellmesberger, Programme, S. 93)","fid":"d5e1158"},{"form":"Werk","weight":"1","pos":618,"context":"..., 7 1\/2 Uhr abends, Saal Bösendorfer; <mark>Werk<\/mark> und Zuordnung gemäß Quartett Rosé, Programme, S....","fid":"d5e1326"},{"form":"Werk","weight":"1","pos":651,"context":"...Herren Rosé, Loh, Bachrich und Hummer; <mark>Werk<\/mark> gemäß Quartett Rosé, Programme, S. 15)","fid":"d5e1390"},{"form":"Werk","weight":"1","pos":703,"context":"...Klavier; Wiener EA gemäß BrahmsWV, S. 25; <mark>Werk<\/mark> und Datum gemäß Quartett Rosé, Programme, S....","fid":"d5e1506"},{"form":"Werk","weight":"1","pos":765,"context":"...Mitwirkung von Dr. Johannes Brahms, Saal Bösendorfer; <mark>Werk<\/mark> gemäß Hofmann, Chronologie, S. 280 f.)","fid":"d5e1642"},{"form":"Werk","weight":"1","pos":1079,"context":"...Böhmisches Streichquartett, Emil Sauer: Klavier; weiteres <mark>Werk<\/mark> von Brahms: op. 51, Nr. 1)","fid":"d5e2285"},{"form":"Werke","weight":"1","pos":1131,"context":"...Quartetts, Otto Hegner: Klavier; u.a. 3 <mark>Werke<\/mark> von Brahms: op. 8, 2. Fassung, op....","fid":"d5e2387"},{"form":"Werk","weight":"1","pos":1220,"context":"(4. Kammermusikabend des Prill-Quartetts; <mark>Werk<\/mark> und Datum gemäß Vaterland, Morgenblatt, 01.01....","fid":"d5e2615"}]},{"docId":"JBWV_0050_op49_Fuenf-Lieder","docUri":"JBWV_0050_op49_Fuenf-Lieder.html","score":7,"contexts":[{"form":"Werk","weight":"1","pos":51,"context":"...Schumann; Frau Dustmann: Gesang; Datum und <mark>Werk<\/mark> gemäß BrahmsWV, S. 197)","fid":"d8e120"},{"form":"Werk","weight":"1","pos":87,"context":"...\"ein Wiegenlied von Brahms mit eigenthümlicher Begleitung\"; weiteres <mark>Werk<\/mark> von J. Brahms: op. 56b)","fid":"d8e201"},{"form":"Werke","weight":"1","pos":149,"context":"...Liederabend der Kammersängerin Rosa Papier, Saal Bösendorfer; <mark>Werke<\/mark> von J. Brahms: \"Das Mädchen spricht\", \"Mädchenlied\"...","fid":"d8e356"},{"form":"Werk","weight":"1","pos":188,"context":"..., 7 1\/2 Uhr abends, Saal Bösendorfer; <mark>Werk<\/mark> von J. Brahms: \"Wiegenlied\")","fid":"d8e432"},{"form":"Werke","weight":"1","pos":502,"context":"...Sistermans: Gesang, Anton Rückauf: Klavier; <mark>Werke<\/mark> von J. Brahms: op. 63, Nr. 8, op....","fid":"d8e1072"},{"form":"Werk","weight":"1","pos":784,"context":"...P. Mohn, Kinderlieder und Reime, Berlin; <mark>Werk<\/mark> gemäß Digitalisat der Technischen Universität Braunschweig)","fid":"d8e1721"},{"form":"Werke","weight":"1","pos":1019,"context":"...von Marie Pflieger, abends, Saal Bösendorfer; <mark>Werke<\/mark> von J. Brahms: \"Alte Liebe\" und \"Wiegenlied\";...","fid":"d8e2195"}]},{"docId":"JBWV_0040_op39_Walzer","docUri":"JBWV_0040_op39_Walzer.html","score":3,"contexts":[{"form":"Werk","weight":"1","pos":56,"context":"...Uhr abends, Sophiensaal; \"Walzer für Clavier\"; <mark>Werk<\/mark> gemäß Hofmann, Chronologie, S. 169; weitere...","fid":"d7e124"},{"form":"Werke","weight":"1","pos":61,"context":"...gemäß Hofmann, Chronologie, S. 169; weitere <mark>Werke<\/mark> von J. Brahms: op. 43, Nr. 3 und...","fid":"d7e124"},{"form":"Werk","weight":"1","pos":197,"context":"(2. Konzert von Clara Schumann; <mark>Werk<\/mark> gemäß Hofmann, Chronologie, S. 114 f.; die...","fid":"d7e398"}]}]}